Workbook

Sheet Assumptions
A1: Tenbagger model: assumptions (edit the blue cells; everything else recalculates)
A2: Blue = input. Black = formula. Bear/Bull cells in black follow Base; type a value to override. Mirrors tenbagger/finance/assumptions.yaml (re-run model.py to refresh Python outputs).
A3: Section | B3: Key | C3: Driver | D3: Unit | E3: Base | F3: Bear | G3: Bull | H3: Source / why
A4: SWITCHES
A5: Switches | B5: ads_on | C5: In-app ads on the free tier | D5: toggle | E5: 1 | F5: =$E5 -> 1 | G5: =$E5 -> 1 | H5: Founder request. Never shown to Pro. [U]
A6: Switches | B6: affiliate_on | C6: Affiliate offers (education-adjacent only, no credit) | D6: toggle | E6: 1 | F6: =$E6 -> 1 | G6: =$E6 -> 1 | H6: Founder request. Brand guardrail PS §5: never reward trading. [U]
A7: Switches | B7: b2b_on | C7: B2B / Edu licences (Classroom Pro, campus) | D7: toggle | E7: 0 | F7: =$E7 -> 0 | G7: =$E7 -> 0 | H7: PS §4: 'Edu (later)'. Off by default.
A8: Switches | B8: llm_on | C8: AI tutor enabled (v2) | D8: toggle | E8: 1 | F8: =$E8 -> 1 | G8: =$E8 -> 1 | H8: PS idea #21; v2 feature
A9: Switches | B9: plaid_on | C9: Bank / brokerage linking (Plaid) enabled | D9: toggle | E9: 1 | F9: =$E9 -> 1 | G9: =$E9 -> 1 | H9: MH §5 Option C: free = 1 bank, Pro = unlimited
A10: Switches | B10: founder_salary_on | C10: Pay founder salary | D10: toggle | E10: 0 | F10: =$E10 -> 0 | G10: =$E10 -> 0 | H10: BENCHMARKS §C excludes founder pay; $5k/mo 'ramen' hurdle shown separately
A11: Switches | B11: soc2_on | C11: SOC 2 programme (needed only for B2B) | D11: toggle | E11: 0 | F11: =$E11 -> 0 | G11: =$E11 -> 0 | H11: [U] Off until a B2B buyer asks
A12: ACQUISITION
A13: Acquisition | B13: organic_installs_m1 | C13: Organic installs (SEO / ASO / social), month 1 | D13: count | E13: 1050 | F13: 560 | G13: 2100 | H13: BENCHMARKS C1 base 1,500 total m1 x 70% non-paid share; [S54] Stock Analysis SEO; [S35] Finelo ~2.1k/day
A14: Acquisition | B14: organic_growth | C14: Organic installs growth, month over month | D14: pct | E14: 0.07 | F14: 0.04 | G14: 0.09 | H14: BENCHMARKS C1 (7% base; author judgment)
A15: Acquisition | B15: referral_installs_per_mau | C15: Referral installs per prior-month MAU | D15: x | E15: 0.015 | F15: 0.008 | G15: 0.03 | H15: [U] author. Share cards (PS idea #2); Robinhood referral waitlist [S62]
A16: Acquisition | B16: creator_start_month | C16: Creator sponsorships start (month) | D16: month | E16: 4 | F16: =$E16 -> 4 | G16: =$E16 -> 4 | H16: [U] after onboarding is tuned (PS §7 gates)
A17: Acquisition | B17: creator_budget_m1 | C17: Creator spend in start month | D17: usd | E17: 500 | F17: 300 | G17: 1000 | H17: [U] author; Brilliant's main channel [S27]
A18: Acquisition | B18: creator_budget_growth | C18: Creator spend growth, month over month | D18: pct | E18: 0.05 | F18: 0.03 | G18: 0.07 | H18: [U] author
A19: Acquisition | B19: creator_cpi | C19: Creator cost per install | D19: usd_c | E19: 8 | F19: 12 | G19: 5 | H19: [S20][U] $40-80 CPM x ~0.5% view-to-install = ~$10 CPI; base assumes CPA-style deals
A20: Acquisition | B20: asa_start_month | C20: Apple Search Ads start (month) | D20: month | E20: 1 | F20: =$E20 -> 1 | G20: =$E20 -> 1 | H20: [U]
A21: Acquisition | B21: asa_budget_m1 | C21: Apple Search Ads spend in start month | D21: usd | E21: 500 | F21: =$E21 -> 500 | G21: 1000 | H21: [U] test budget; PS §7 ads tests $300-500
A22: Acquisition | B22: asa_budget_growth | C22: ASA spend growth, month over month | D22: pct | E22: 0.03 | F22: 0 | G22: 0.06 | H22: [U] kept small: paid LTV/CAC < 1 in BENCHMARKS B4
A23: Acquisition | B23: asa_cpi | C23: Apple Search Ads cost per install | D23: usd_c | E23: 6 | F23: 9 | G23: 4 | H23: [S17][S] Finance CPA $13.28, all-category $3.76; [S18][U] Education CPT ~$1.24. Base bids education keywords
A24: ENGAGEMENT
A25: Engagement | B25: activation_rate | C25: Installs that activate (finish first lesson) | D25: pct | E25: 0.65 | F25: 0.55 | G25: 0.75 | H25: PS §7 W8 target 150 of 200 (75%) invited testers; public installs lower [U]
A26: Engagement | B26: d30_retention | C26: Free installs still active the following month (D30) | D26: pct | E26: 0.12 | F26: 0.06 | G26: 0.2 | H26: [S85][U] finance D30 2-6%; PS §7 gate D30 >= 7%. Habit product assumed above median
A27: Engagement | B27: retained_decay | C27: Monthly decay of the retained free pool | D27: pct | E27: 0.08 | F27: 0.12 | G27: 0.06 | H27: BENCHMARKS C1 uses 7%/mo decay
A28: CONVERSION
A29: Conversion | B29: trial_start_rate | C29: Trial / paywall starts as share of activated users | D29: pct | E29: 0.1 | F29: 0.08 | G29: 0.14 | H29: PS §7 gate: trial starts >= 8% of activated
A30: Conversion | B30: trial_to_paid | C30: Trial-to-paid | D30: pct | E30: 0.38 | F30: 0.33 | G30: 0.4 | H30: [S13][S] 37.4% for 5-9 day trials; PS gate >= 25%
A31: Conversion | B31: mix_monthly | C31: New payers choosing monthly plan | D31: pct | E31: 0.35 | F31: 0.4 | G31: 0.3 | H31: BENCHMARKS B2: 60% annual among monthly+annual
A32: Conversion | B32: mix_annual | C32: New payers choosing annual plan (student = remainder) | D32: pct | E32: 0.5 | F32: 0.45 | G32: 0.55 | H32: BENCHMARKS B2; annual plans retain best [S14]
A33: Conversion | B33: pass_rate | C33: Recruiting Pass purchases per activated user | D33: pct | E33: 0.004 | F33: 0.002 | G33: 0.008 | H33: PS §7 gate: >= 5 purchases per ~100 student testers; students ~ a third of users [U]
A34: PRICING
A35: Pricing | B35: price_monthly | C35: Pro monthly price | D35: usd_c | E35: 12.99 | F35: 9.99 | G35: 14.99 | H35: PS §4; BENCHMARKS C1 base; Monarch/Copilot $13-15 [S30][S31]
A36: Pricing | B36: price_annual | C36: Pro annual price | D36: usd_c | E36: 79.99 | F36: 59.99 | G36: 99.99 | H36: PS §4; Stock Analysis $79 [S56]; Monarch $99.99 [S30]
A37: Pricing | B37: price_student | C37: Student annual price (.edu verified) | D37: usd_c | E37: 39.99 | F37: =$E37 -> 39.99 | G37: =$E37 -> 39.99 | H37: PS §4 (~50% off, Spotify Student norm)
A38: Pricing | B38: price_pass | C38: Recruiting Pass, one-time (4 months) | D38: usd_c | E38: 49 | F38: =$E38 -> 49 | G38: =$E38 -> 49 | H38: PS §4 (10% of WSP/BIWS [S69][S70])
A39: Pricing | B39: store_fee | C39: App store commission | D39: pct | E39: 0.15 | F39: =$E39 -> 0.15 | G39: =$E39 -> 0.15 | H39: [S83][S] Apple Small Business Program < $1M proceeds; Google 15% on subscriptions
A40: Pricing | B40: refund_rate | C40: Refunds as share of gross in-app sales | D40: pct | E40: 0.02 | F40: 0.03 | G40: 0.015 | H40: [U] author estimate; PS pricing rules (no weekly traps) limit refunds
A41: RETENTION
A42: Retention | B42: ret12_monthly | C42: Monthly plans still subscribed after 12 months | D42: pct | E42: 0.17 | F42: 0.095 | G42: 0.25 | H42: [S14][S] RevenueCat 2025: 17.0%
A43: Retention | B43: renew_annual | C43: Annual plan renewal rate | D43: pct | E43: 0.441 | F43: 0.307 | G43: 0.54 | H43: [S14][S] RevenueCat 2025: 44.1%
A44: Retention | B44: renew_student | C44: Student plan renewal rate | D44: pct | E44: 0.35 | F44: 0.25 | G44: 0.45 | H44: [U] below annual: students graduate / leave
A45: ADS
A46: Ads | B46: ads_start_month | C46: Ads start (month) | D46: month | E46: 4 | F46: =$E46 -> 4 | G46: =$E46 -> 4 | H46: [U] after launch trust is built
A47: Ads | B47: ad_share_free_mau | C47: Share of free MAU who see ads | D47: pct | E47: 0.7 | F47: 0.6 | G47: 0.8 | H47: [U] excludes under-18s, consent declines, ad-free trial periods
A48: Ads | B48: imps_article | C48: Impressions / ad-seeing free MAU / month: article & lesson end (banner/native) | D48: x | E48: 8 | F48: 5 | G48: 12 | H48: [U] author: ~2 per session x ~4 sessions
A49: Ads | B49: imps_screener | C49: Impressions / ad-seeing free MAU / month: screener native slot | D49: x | E49: 4 | F49: 2 | G49: 6 | H49: [U] author
A50: Ads | B50: imps_rewarded | C50: Impressions / ad-seeing free MAU / month: opt-in rewarded (e.g. unlock extra lesson) | D50: x | E50: 1 | F50: 0.5 | G50: 2 | H50: [U] author
A51: Ads | B51: ecpm_article | C51: eCPM: article-end banner/native | D51: usd_c | E51: 2.5 | F51: 1.5 | G51: 4 | H51: [U] typical US in-app banner $0.5-1.5, native $2-5; not in sources.json - verify with AdMob/AppLovin
A52: Ads | B52: ecpm_screener | C52: eCPM: screener native | D52: usd_c | E52: 3 | F52: 2 | G52: 5 | H52: [U] typical US in-app native $2-5; finance intent may price higher - verify
A53: Ads | B53: ecpm_rewarded | C53: eCPM: opt-in rewarded video | D53: usd_c | E53: 12 | F53: 8 | G53: 18 | H53: [U] typical US rewarded $8-20 - verify
A54: Ads | B54: ad_fill_rate | C54: Ad fill rate | D54: pct | E54: 0.85 | F54: 0.7 | G54: 0.95 | H54: [U] mediated fill, US
A55: AFFILIATE
A56: Affiliate | B56: affiliate_start_month | C56: Affiliate offers start (month) | D56: month | E56: 7 | F56: =$E56 -> 7 | G56: =$E56 -> 7 | H56: [U] after counsel review (PS §6 #4)
A57: Affiliate | B57: aff_clicks_per_1k_mau | C57: Affiliate clicks per 1,000 MAU per month | D57: x | E57: 5 | F57: 3 | G57: 10 | H57: [U] author; offers shown only in 'open a Roth / brokerage' lessons
A58: Affiliate | B58: aff_conversion | C58: Clicks that become funded accounts | D58: pct | E58: 0.04 | F58: 0.02 | G58: 0.06 | H58: [U] author
A59: Affiliate | B59: aff_payout | C59: Payout per funded account | D59: usd | E59: 50 | F59: 30 | G59: 75 | H59: [U] typical broker/Roth bounties $25-150; education offers only, never credit
A60: B2B
A61: B2B | B61: b2b_start_month | C61: B2B / Edu sales start (month) | D61: month | E61: 19 | F61: =$E61 -> 19 | G61: =$E61 -> 19 | H61: PS §4 'later'; Zogo model year 2 (PS idea #20)
A62: B2B | B62: teachers_at_start | C62: Classroom Pro teachers at start | D62: count | E62: 5 | F62: =$E62 -> 5 | G62: =$E62 -> 5 | H62: [U]
A63: B2B | B63: teachers_added_per_month | C63: Teachers added per month (net) | D63: count | E63: 3 | F63: =$E63 -> 3 | G63: =$E63 -> 3 | H63: [U]
A64: B2B | B64: teacher_price_annual | C64: Classroom Pro price per teacher per year | D64: usd | E64: 149 | F64: =$E64 -> 149 | G64: =$E64 -> 149 | H64: PS §4 (Kahoot anchor)
A65: B2B | B65: campus_at_start | C65: Campus / club licences at start | D65: count | E65: 1 | F65: =$E65 -> 1 | G65: =$E65 -> 1 | H65: [U]
A66: B2B | B66: campus_added_per_month | C66: Campus licences added per month (net) | D66: count | E66: 0.25 | F66: =$E66 -> 0.25 | G66: =$E66 -> 0.25 | H66: [U] one a quarter
A67: B2B | B67: campus_price_annual | C67: Campus / club licence per year | D67: usd | E67: 3000 | F67: =$E67 -> 3000 | G67: =$E67 -> 3000 | H67: PS §4 $1.5-5k/yr [assumption]
A68: B2B | B68: b2b_processing_rate | C68: Card processing on B2B invoices | D68: pct | E68: 0.03 | F68: =$E68 -> 0.03 | G68: =$E68 -> 0.03 | H68: [U] Stripe ~2.9% + 30c
A69: COGS
A70: COGS | B70: data_beta_cost | C70: Data licence, public-beta phase (EOD prices w/ redistribution) | D70: usd | E70: 400 | F70: 450 | G70: 350 | H70: DS §6 $250-450 (Tiingo $250 / EODHD $399); BENCHMARKS C1 $400
A71: COGS | B71: data_scale_cost | C71: Data licence, scale phase (delayed quotes, ETFs) | D71: usd | E71: 3000 | F71: 3500 | G71: 2500 | H71: DS §6 $2-5k [U: enterprise quotes]
A72: COGS | B72: data_scale_mau | C72: MAU that triggers the scale data phase | D72: count | E72: 100000 | F72: =$E72 -> 100000 | G72: =$E72 -> 100000 | H72: [U] author; DS: scale = when product needs delayed quotes
A73: COGS | B73: plaid_start_month | C73: Linking launches (month) | D73: month | E73: 13 | F73: =$E73 -> 13 | G73: =$E73 -> 13 | H73: BENCHMARKS C1: linking starts month 13
A74: COGS | B74: plaid_free_link_share | C74: Free MAU with a linked bank (capped at 1 Item) | D74: pct | E74: 0.1 | F74: 0.12 | G74: 0.08 | H74: MH §3 lever 1-2: free = 1 Item, auto-unlink after 30 days idle [U]
A75: COGS | B75: plaid_free_item_cost | C75: Plaid cost per free Item per month (Transactions only) | D75: usd_c | E75: 0.45 | F75: 0.6 | G75: 0.3 | H75: MH §3 illustrative $0.30-0.60 [U]; [S89] rates not public
A76: COGS | B76: plaid_pro_link_share | C76: Pro subscribers who link accounts | D76: pct | E76: 0.4 | F76: 0.35 | G76: 0.5 | H76: BENCHMARKS C1 20/30/40%; raised for the Money Hub [U]
A77: COGS | B77: plaid_pro_items | C77: Average linked Items per linking Pro user | D77: x | E77: 2.5 | F77: =$E77 -> 2.5 | G77: 3 | H77: MH §3: ~3 Items, often 2
A78: COGS | B78: plaid_pro_item_cost | C78: Plaid cost per Pro Item per month (Tx + Liabilities + Investments mix) | D78: usd_c | E78: 0.7 | F78: 0.9 | G78: 0.55 | H78: MH §3: $0.80-2.00 per fully linked user [U]; BENCHMARKS $1.25-2.50/user [S86]
A79: COGS | B79: plaid_platform_fee | C79: Aggregator platform minimum per month | D79: usd | E79: 100 | F79: =$E79 -> 100 | G79: =$E79 -> 100 | H79: [S86][P] SnapTrade $100/mo as proxy; Plaid minimum unknown
A80: COGS | B80: hosting_fixed | C80: Hosting fixed (Supabase Pro, Expo) | D80: usd | E80: 50 | F80: =$E80 -> 50 | G80: =$E80 -> 50 | H80: [S87] Supabase Pro $25; [S88] Expo $19; BENCHMARKS C1
A81: COGS | B81: hosting_per_mau | C81: Hosting per MAU per month | D81: usd_c | E81: 0.01 | F81: =$E81 -> 0.01 | G81: =$E81 -> 0.01 | H81: BENCHMARKS C1 ($0.01/MAU)
A82: COGS | B82: llm_start_month | C82: AI tutor launches (month) | D82: month | E82: 7 | F82: =$E82 -> 7 | G82: =$E82 -> 7 | H82: PS: tutor is v2 (months 4-9)
A83: COGS | B83: llm_cost_per_payer | C83: LLM tokens per Pro user per month (capped) | D83: usd_c | E83: 0.45 | F83: 0.65 | G83: 0.3 | H83: PS idea #21: $0.30-0.65 per Pro user at 40 answers/mo
A84: COGS | B84: llm_cost_per_free_mau | C84: LLM tokens per free MAU per month (taster) | D84: usd_c | E84: 0.01 | F84: =$E84 -> 0.01 | G84: =$E84 -> 0.01 | H84: PS idea #21: ~$0.008-0.016 per answer, ~1 free answer/mo [U]
A85: COGS | B85: rc_threshold | C85: RevenueCat free up to this monthly tracked revenue | D85: usd | E85: 2500 | F85: =$E85 -> 2500 | G85: =$E85 -> 2500 | H85: [S84][P]
A86: COGS | B86: rc_rate | C86: RevenueCat fee above threshold | D86: pct | E86: 0.01 | F86: =$E86 -> 0.01 | G86: =$E86 -> 0.01 | H86: [S84][P]
A87: OPEX
A88: OpEx | B88: founder_salary | C88: Founder salary per month (if switched on) | D88: usd | E88: 5000 | F88: =$E88 -> 5000 | G88: =$E88 -> 5000 | H88: BENCHMARKS §C $5k ramen hurdle
A89: OpEx | B89: contractors_fy1 | C89: Contractors per month, FY1 (content QA, design) | D89: usd | E89: 500 | F89: 300 | G89: 1000 | H89: [U] author
A90: OpEx | B90: contractors_fy2 | C90: Contractors per month, FY2 | D90: usd | E90: 1500 | F90: 800 | G90: 3000 | H90: [U] author
A91: OpEx | B91: contractors_fy3 | C91: Contractors per month, FY3 | D91: usd | E91: 3000 | F91: 1500 | G91: 6000 | H91: [U] author
A92: OpEx | B92: mkt_other_monthly | C92: Other marketing per month (newsletter, community, landing tests) | D92: usd | E92: 150 | F92: =$E92 -> 150 | G92: =$E92 -> 150 | H92: PS §7 budget [U]
A93: OpEx | B93: legal_llc | C93: LLC + D-U-N-S (one-time, month 1) | D93: usd | E93: 500 | F93: =$E93 -> 500 | G93: =$E93 -> 500 | H93: PS §7: $100-500
A94: OpEx | B94: legal_counsel_review | C94: Securities counsel review (one-time, month 1) | D94: usd | E94: 2000 | F94: =$E94 -> 2000 | G94: =$E94 -> 2000 | H94: PS §6 #4: $1-2k [U]
A95: OpEx | B95: legal_privacy | C95: Privacy policy / ToS (one-time, month 1) | D95: usd | E95: 500 | F95: =$E95 -> 500 | G95: =$E95 -> 500 | H95: [U] template + review
A96: OpEx | B96: legal_trademark | C96: Trademark filing, 2 classes (one-time, month 1) | D96: usd | E96: 700 | F96: =$E96 -> 700 | G96: =$E96 -> 700 | H96: [U] USPTO ~$350/class; PS §3 classes 9 and 41
A97: OpEx | B97: legal_monthly | C97: Ongoing legal / compliance per month | D97: usd | E97: 100 | F97: =$E97 -> 100 | G97: =$E97 -> 100 | H97: [U]
A98: OpEx | B98: legal_annual_review | C98: Annual counsel refresh (months 13, 25) | D98: usd | E98: 1000 | F98: =$E98 -> 1000 | G98: =$E98 -> 1000 | H98: [U]
A99: OpEx | B99: soc2_start_month | C99: SOC 2 starts (month, if switched on) | D99: month | E99: 25 | F99: =$E99 -> 25 | G99: =$E99 -> 25 | H99: [U]
A100: OpEx | B100: soc2_monthly | C100: SOC 2 tooling + audit per month | D100: usd | E100: 1500 | F100: =$E100 -> 1500 | G100: =$E100 -> 1500 | H100: [U] Vanta/Drata + audit ~$15-25k/yr
...

Sheet Monthly_Base
A1: Tenbagger: Base case, monthly (USD). All cells are formulas driven by the Assumptions sheet.
A2: Month | C2: 1 | D2: 2 | E2: 3 | F2: 4 | G2: 5 | H2: 6 | I2: 7 | J2: 8 | K2: 9 | L2: 10 | M2: 11 | N2: 12 | O2: 13 | P2: 14 | Q2: 15 | R2: 16 | S2: 17 | T2: 18 | U2: 19 | V2: 20 | W2: 21 | X2: 22 | Y2: 23 | Z2: 24 | AA2: 25 | AB2: 26 | AC2: 27 | AD2: 28 | AE2: 29 | AF2: 30 | AG2: 31 | AH2: 32 | AI2: 33 | AJ2: 34 | AK2: 35 | AL2: 36
A3: Fiscal year | C3: 1 | D3: 1 | E3: 1 | F3: 1 | G3: 1 | H3: 1 | I3: 1 | J3: 1 | K3: 1 | L3: 1 | M3: 1 | N3: 1 | O3: 2 | P3: 2 | Q3: 2 | R3: 2 | S3: 2 | T3: 2 | U3: 2 | V3: 2 | W3: 2 | X3: 2 | Y3: 2 | Z3: 2 | AA3: 3 | AB3: 3 | AC3: 3 | AD3: 3 | AE3: 3 | AF3: 3 | AG3: 3 | AH3: 3 | AI3: 3 | AJ3: 3 | AK3: 3 | AL3: 3
A4: Calendar month | C4: Jan-27 | D4: Feb-27 | E4: Mar-27 | F4: Apr-27 | G4: May-27 | H4: Jun-27 | I4: Jul-27 | J4: Aug-27 | K4: Sep-27 | L4: Oct-27 | M4: Nov-27 | N4: Dec-27 | O4: Jan-28 | P4: Feb-28 | Q4: Mar-28 | R4: Apr-28 | S4: May-28 | T4: Jun-28 | U4: Jul-28 | V4: Aug-28 | W4: Sep-28 | X4: Oct-28 | Y4: Nov-28 | Z4: Dec-28 | AA4: Jan-29 | AB4: Feb-29 | AC4: Mar-29 | AD4: Apr-29 | AE4: May-29 | AF4: Jun-29 | AG4: Jul-29 | AH4: Aug-29 | AI4: Sep-29 | AJ4: Oct-29 | AK4: Nov-29 | AL4: Dec-29
A5: ACQUISITION
A6: Installs: organic / SEO / ASO | B6: inst_org | C6: =(Assumptions!$E$13*((1+Assumptions!$E$14)^(C$2-1))) -> 1050 | D6: =(Assumptions!$E$13*((1+Assumptions!$E$14)^(D$2-1))) -> 1123.5 | E6: =(Assumptions!$E$13*((1+Assumptions!$E$14)^(E$2-1))) -> 1202.145 | F6: =(Assumptions!$E$13*((1+Assumptions!$E$14)^(F$2-1))) -> 1286.2951 | G6: =(Assumptions!$E$13*((1+Assumptions!$E$14)^(G$2-1))) -> 1376.3358 | H6: =(Assumptions!$E$13*((1+Assumptions!$E$14)^(H$2-1))) -> 1472.6793 | I6: =(Assumptions!$E$13*((1+Assumptions!$E$14)^(I$2-1))) -> 1575.7669 | J6: =(Assumptions!$E$13*((1+Assumptions!$E$14)^(J$2-1))) -> 1686.0706 | ... AL6: =(Assumptions!$E$13*((1+Assumptions!$E$14)^(AL$2-1))) -> 11210.411
A7: Installs: referral (x prior-month MAU) | B7: inst_ref | C7: =(Assumptions!$E$15*0) -> 0 | D7: =(Assumptions!$E$15*C36) -> 17 | E7: =(Assumptions!$E$15*D36) -> 20.784337 | F7: =(Assumptions!$E$15*E36) -> 24.468231 | G7: =(Assumptions!$E$15*F36) -> 29.175122 | H7: =(Assumptions!$E$15*G36) -> 33.244648 | I7: =(Assumptions!$E$15*H36) -> 37.431646 | J7: =(Assumptions!$E$15*I36) -> 41.766536 | K7: =(Assumptions!$E$15*J36) -> 46.270942 | ... AL7: =(Assumptions!$E$15*AK36) -> 334.27625
A8: Creator spend | B8: spend_creators | C8: =IF((C$2>=Assumptions!$E$16),(Assumptions!$E$17*((1+Assumptions!$E$18)^(C$2-Assumptions!$E$16))),0) -> 0 | D8: =IF((D$2>=Assumptions!$E$16),(Assumptions!$E$17*((1+Assumptions!$E$18)^(D$2-Assumptions!$E$16))),0) -> 0 | E8: =IF((E$2>=Assumptions!$E$16),(Assumptions!$E$17*((1+Assumptions!$E$18)^(E$2-Assumptions!$E$16))),0) -> 0 | F8: =IF((F$2>=Assumptions!$E$16),(Assumptions!$E$17*((1+Assumptions!$E$18)^(F$2-Assumptions!$E$16))),0) -> 500 | G8: =IF((G$2>=Assumptions!$E$16),(Assumptions!$E$17*((1+Assumptions!$E$18)^(G$2-Assumptions!$E$16))),0) -> 525 | H8: =IF((H$2>=Assumptions!$E$16),(Assumptions!$E$17*((1+Assumptions!$E$18)^(H$2-Assumptions!$E$16))),0) -> 551.25 | I8: =IF((I$2>=Assumptions!$E$16),(Assumptions!$E$17*((1+Assumptions!$E$18)^(I$2-Assumptions!$E$16))),0) -> 578.8125 | J8: =IF((J$2>=Assumptions!$E$16),(Assumptions!$E$17*((1+Assumptions!$E$18)^(J$2-Assumptions!$E$16))),0) -> 607.75312 | ... AL8: =IF((AL$2>=Assumptions!$E$16),(Assumptions!$E$17*((1+Assumptions!$E$18)^(AL$2-Assumptions!$E$16))),0) -> 2382.4707
A9: Installs: creators | B9: inst_creators | C9: =IF(Assumptions!$E$19=0,0,C8/Assumptions!$E$19) -> 0 | D9: =IF(Assumptions!$E$19=0,0,D8/Assumptions!$E$19) -> 0 | E9: =IF(Assumptions!$E$19=0,0,E8/Assumptions!$E$19) -> 0 | F9: =IF(Assumptions!$E$19=0,0,F8/Assumptions!$E$19) -> 62.5 | G9: =IF(Assumptions!$E$19=0,0,G8/Assumptions!$E$19) -> 65.625 | H9: =IF(Assumptions!$E$19=0,0,H8/Assumptions!$E$19) -> 68.90625 | I9: =IF(Assumptions!$E$19=0,0,I8/Assumptions!$E$19) -> 72.351562 | J9: =IF(Assumptions!$E$19=0,0,J8/Assumptions!$E$19) -> 75.969141 | ... AL9: =IF(Assumptions!$E$19=0,0,AL8/Assumptions!$E$19) -> 297.80884
A10: Apple Search Ads spend | B10: spend_asa | C10: =IF((C$2>=Assumptions!$E$20),(Assumptions!$E$21*((1+Assumptions!$E$22)^(C$2-Assumptions!$E$20))),0) -> 500 | D10: =IF((D$2>=Assumptions!$E$20),(Assumptions!$E$21*((1+Assumptions!$E$22)^(D$2-Assumptions!$E$20))),0) -> 515 | E10: =IF((E$2>=Assumptions!$E$20),(Assumptions!$E$21*((1+Assumptions!$E$22)^(E$2-Assumptions!$E$20))),0) -> 530.45 | F10: =IF((F$2>=Assumptions!$E$20),(Assumptions!$E$21*((1+Assumptions!$E$22)^(F$2-Assumptions!$E$20))),0) -> 546.3635 | G10: =IF((G$2>=Assumptions!$E$20),(Assumptions!$E$21*((1+Assumptions!$E$22)^(G$2-Assumptions!$E$20))),0) -> 562.75441 | H10: =IF((H$2>=Assumptions!$E$20),(Assumptions!$E$21*((1+Assumptions!$E$22)^(H$2-Assumptions!$E$20))),0) -> 579.63704 | I10: =IF((I$2>=Assumptions!$E$20),(Assumptions!$E$21*((1+Assumptions!$E$22)^(I$2-Assumptions!$E$20))),0) -> 597.02615 | J10: =IF((J$2>=Assumptions!$E$20),(Assumptions!$E$21*((1+Assumptions!$E$22)^(J$2-Assumptions!$E$20))),0) -> 614.93693 | ... AL10: =IF((AL$2>=Assumptions!$E$20),(Assumptions!$E$21*((1+Assumptions!$E$22)^(AL$2-Assumptions!$E$20))),0) -> 1406.9312
A11: Installs: paid Apple Search Ads | B11: inst_asa | C11: =IF(Assumptions!$E$23=0,0,C10/Assumptions!$E$23) -> 83.333333 | D11: =IF(Assumptions!$E$23=0,0,D10/Assumptions!$E$23) -> 85.833333 | E11: =IF(Assumptions!$E$23=0,0,E10/Assumptions!$E$23) -> 88.408333 | F11: =IF(Assumptions!$E$23=0,0,F10/Assumptions!$E$23) -> 91.060583 | G11: =IF(Assumptions!$E$23=0,0,G10/Assumptions!$E$23) -> 93.792401 | H11: =IF(Assumptions!$E$23=0,0,H10/Assumptions!$E$23) -> 96.606173 | I11: =IF(Assumptions!$E$23=0,0,I10/Assumptions!$E$23) -> 99.504358 | J11: =IF(Assumptions!$E$23=0,0,J10/Assumptions!$E$23) -> 102.48949 | ... AL11: =IF(Assumptions!$E$23=0,0,AL10/Assumptions!$E$23) -> 234.48854
A12: Total installs | B12: inst_total | C12: =(((C6+C7)+C9)+C11) -> 1133.3333 | D12: =(((D6+D7)+D9)+D11) -> 1226.3333 | E12: =(((E6+E7)+E9)+E11) -> 1311.3377 | F12: =(((F6+F7)+F9)+F11) -> 1464.324 | G12: =(((G6+G7)+G9)+G11) -> 1564.9283 | H12: =(((H6+H7)+H9)+H11) -> 1671.4364 | I12: =(((I6+I7)+I9)+I11) -> 1785.0544 | J12: =(((J6+J7)+J9)+J11) -> 1906.2957 | ... AL12: =(((AL6+AL7)+AL9)+AL11) -> 12076.984
A14: FUNNEL (free -> trial -> paid)
A15: Activated users | B15: activated | C15: =(C12*Assumptions!$E$25) -> 736.66667 | D15: =(D12*Assumptions!$E$25) -> 797.11667 | E15: =(E12*Assumptions!$E$25) -> 852.36949 | F15: =(F12*Assumptions!$E$25) -> 951.81058 | G15: =(G12*Assumptions!$E$25) -> 1017.2034 | H15: =(H12*Assumptions!$E$25) -> 1086.4337 | I15: =(I12*Assumptions!$E$25) -> 1160.2854 | J15: =(J12*Assumptions!$E$25) -> 1239.0922 | ... AL15: =(AL12*Assumptions!$E$25) -> 7850.0397
A16: Trial / paywall starts | B16: trial_starts | C16: =(C15*Assumptions!$E$29) -> 73.666667 | D16: =(D15*Assumptions!$E$29) -> 79.711667 | E16: =(E15*Assumptions!$E$29) -> 85.236949 | F16: =(F15*Assumptions!$E$29) -> 95.181058 | G16: =(G15*Assumptions!$E$29) -> 101.72034 | H16: =(H15*Assumptions!$E$29) -> 108.64337 | I16: =(I15*Assumptions!$E$29) -> 116.02854 | J16: =(J15*Assumptions!$E$29) -> 123.90922 | ... AL16: =(AL15*Assumptions!$E$29) -> 785.00397
A17: New paid subscribers | B17: new_paid | C17: =(C16*Assumptions!$E$30) -> 27.993333 | D17: =(D16*Assumptions!$E$30) -> 30.290433 | E17: =(E16*Assumptions!$E$30) -> 32.39004 | F17: =(F16*Assumptions!$E$30) -> 36.168802 | G17: =(G16*Assumptions!$E$30) -> 38.65373 | H17: =(H16*Assumptions!$E$30) -> 41.284479 | I17: =(I16*Assumptions!$E$30) -> 44.090845 | J17: =(J16*Assumptions!$E$30) -> 47.085504 | ... AL17: =(AL16*Assumptions!$E$30) -> 298.30151
A18: of which monthly plan | B18: new_monthly | C18: =(C17*Assumptions!$E$31) -> 9.7976667 | D18: =(D17*Assumptions!$E$31) -> 10.601652 | E18: =(E17*Assumptions!$E$31) -> 11.336514 | F18: =(F17*Assumptions!$E$31) -> 12.659081 | G18: =(G17*Assumptions!$E$31) -> 13.528805 | H18: =(H17*Assumptions!$E$31) -> 14.449568 | I18: =(I17*Assumptions!$E$31) -> 15.431796 | J18: =(J17*Assumptions!$E$31) -> 16.479926 | ... AL18: =(AL17*Assumptions!$E$31) -> 104.40553
A19: of which annual plan | B19: new_annual | C19: =(C17*Assumptions!$E$32) -> 13.996667 | D19: =(D17*Assumptions!$E$32) -> 15.145217 | E19: =(E17*Assumptions!$E$32) -> 16.19502 | F19: =(F17*Assumptions!$E$32) -> 18.084401 | G19: =(G17*Assumptions!$E$32) -> 19.326865 | H19: =(H17*Assumptions!$E$32) -> 20.642239 | I19: =(I17*Assumptions!$E$32) -> 22.045422 | J19: =(J17*Assumptions!$E$32) -> 23.542752 | ... AL19: =(AL17*Assumptions!$E$32) -> 149.15075
A20: of which student plan | B20: new_student | C20: =(C17*Assumptions!$E$109) -> 4.199 | D20: =(D17*Assumptions!$E$109) -> 4.543565 | E20: =(E17*Assumptions!$E$109) -> 4.8585061 | F20: =(F17*Assumptions!$E$109) -> 5.4253203 | G20: =(G17*Assumptions!$E$109) -> 5.7980595 | H20: =(H17*Assumptions!$E$109) -> 6.1926718 | I20: =(I17*Assumptions!$E$109) -> 6.6136267 | J20: =(J17*Assumptions!$E$109) -> 7.0628256 | ... AL20: =(AL17*Assumptions!$E$109) -> 44.745226
A21: Recruiting Pass purchases (one-time) | B21: pass_sales | C21: =(C15*Assumptions!$E$33) -> 2.9466667 | D21: =(D15*Assumptions!$E$33) -> 3.1884667 | E21: =(E15*Assumptions!$E$33) -> 3.4094779 | F21: =(F15*Assumptions!$E$33) -> 3.8072423 | G21: =(G15*Assumptions!$E$33) -> 4.0688137 | H21: =(H15*Assumptions!$E$33) -> 4.3457346 | I21: =(I15*Assumptions!$E$33) -> 4.6411415 | J21: =(J15*Assumptions!$E$33) -> 4.9563689 | ... AL21: =(AL15*Assumptions!$E$33) -> 31.400159
A23: SUBSCRIBERS
A24: Monthly-plan subscribers (end of month) | B24: subs_monthly | C24: =((0*(1-Assumptions!$E$110))+C18) -> 9.7976667 | D24: =((C24*(1-Assumptions!$E$110))+D18) -> 19.054312 | E24: =((D24*(1-Assumptions!$E$110))+E18) -> 27.775083 | F24: =((E24*(1-Assumptions!$E$110))+F18) -> 36.621249 | G24: =((F24*(1-Assumptions!$E$110))+G18) -> 45.122753 | H24: =((G24*(1-Assumptions!$E$110))+H18) -> 53.377948 | I24: =((H24*(1-Assumptions!$E$110))+I18) -> 61.482112 | J24: =((I24*(1-Assumptions!$E$110))+J18) -> 69.521881 | K24: =((J24*(1-Assumptions!$E$110))+K18) -> 77.576649 | ... AL24: =((AK24*(1-Assumptions!$E$110))+AL18) -> 541.86091
A25: Annual plans billed (new + renewals) | B25: bill_annual | C25: =(C19+0) -> 13.996667 | D25: =(D19+0) -> 15.145217 | E25: =(E19+0) -> 16.19502 | F25: =(F19+0) -> 18.084401 | G25: =(G19+0) -> 19.326865 | H25: =(H19+0) -> 20.642239 | I25: =(I19+0) -> 22.045422 | J25: =(J19+0) -> 23.542752 | ... N25: =(N19+0) -> 30.613343 | O25: =(O19+(Assumptions!$E$43*C25)) -> 38.86307 | P25: =(P19+(Assumptions!$E$43*D25)) -> 41.586248 | Q25: =(Q19+(Assumptions!$E$43*E25)) -> 44.416986 | R25: =(R19+(Assumptions!$E$43*F25)) -> 47.77967 | S25: =(S19+(Assumptions!$E$43*G25)) -> 51.029917 | T25: =(T19+(Assumptions!$E$43*H25)) -> 54.497315 | U25: =(U19+(Assumptions!$E$43*I25)) -> 58.201316 | V25: =(V19+(Assumptions!$E$43*J25)) -> 62.158483 | ... AL25: =(AL19+(Assumptions!$E$43*Z25)) -> 184.82354
A26: Annual-plan subscribers (billed in last 12 months) | B26: subs_annual | C26: =SUM(C25:C25) -> 13.996667 | D26: =SUM(C25:D25) -> 29.141883 | E26: =SUM(C25:E25) -> 45.336904 | F26: =SUM(C25:F25) -> 63.421305 | G26: =SUM(C25:G25) -> 82.748169 | H26: =SUM(C25:H25) -> 103.39041 | I26: =SUM(C25:I25) -> 125.43583 | J26: =SUM(C25:J25) -> 148.97858 | K26: =SUM(C25:K25) -> 174.11946 | L26: =SUM(C25:L25) -> 200.96633 | M26: =SUM(C25:M25) -> 229.63467 | N26: =SUM(C25:N25) -> 260.24801 | O26: =SUM(D25:O25) -> 285.11442 | P26: =SUM(E25:P25) -> 311.55545 | Q26: =SUM(F25:Q25) -> 339.77741 | R26: =SUM(G25:R25) -> 369.47268 | S26: =SUM(H25:S25) -> 401.17573 | T26: =SUM(I25:T25) -> 435.03081 | U26: =SUM(J25:U25) -> 471.1867 | ... AL26: =SUM(AA25:AL25) -> 1581.1018
A27: Student plans billed (new + renewals) | B27: bill_student | C27: =(C20+0) -> 4.199 | D27: =(D20+0) -> 4.543565 | E27: =(E20+0) -> 4.8585061 | F27: =(F20+0) -> 5.4253203 | G27: =(G20+0) -> 5.7980595 | H27: =(H20+0) -> 6.1926718 | I27: =(I20+0) -> 6.6136267 | J27: =(J20+0) -> 7.0628256 | ... N27: =(N20+0) -> 9.184003 | O27: =(O20+(Assumptions!$E$44*C27)) -> 11.276812 | P27: =(P20+(Assumptions!$E$44*D27)) -> 12.06241 | Q27: =(Q20+(Assumptions!$E$44*E27)) -> 12.882972 | R27: =(R20+(Assumptions!$E$44*F27)) -> 13.840197 | S27: =(S20+(Assumptions!$E$44*G27)) -> 14.781352 | T27: =(T20+(Assumptions!$E$44*H27)) -> 15.785661 | U27: =(U20+(Assumptions!$E$44*I27)) -> 16.858555 | V27: =(V20+(Assumptions!$E$44*J27)) -> 18.004828 | ... AL27: =(AL20+(Assumptions!$E$44*Z27)) -> 52.946237
A28: Student-plan subscribers | B28: subs_student | C28: =SUM(C27:C27) -> 4.199 | D28: =SUM(C27:D27) -> 8.742565 | E28: =SUM(C27:E27) -> 13.601071 | F28: =SUM(C27:F27) -> 19.026391 | G28: =SUM(C27:G27) -> 24.824451 | H28: =SUM(C27:H27) -> 31.017123 | I28: =SUM(C27:I27) -> 37.630749 | J28: =SUM(C27:J27) -> 44.693575 | K28: =SUM(C27:K27) -> 52.235837 | L28: =SUM(C27:L27) -> 60.2899 | M28: =SUM(C27:M27) -> 68.890401 | N28: =SUM(C27:N27) -> 78.074404 | O28: =SUM(D27:O27) -> 85.152216 | P28: =SUM(E27:P27) -> 92.671061 | Q28: =SUM(F27:Q27) -> 100.69553 | R28: =SUM(G27:R27) -> 109.1104 | S28: =SUM(H27:S27) -> 118.0937 | T28: =SUM(I27:T27) -> 127.68668 | U28: =SUM(J27:U27) -> 137.93161 | ... AL28: =SUM(AA27:AL27) -> 452.94009
A29: Paid subscribers (end of month) | B29: subs_paid | C29: =((C24+C26)+C28) -> 27.993333 | D29: =((D24+D26)+D28) -> 56.93876 | E29: =((E24+E26)+E28) -> 86.713058 | F29: =((F24+F26)+F28) -> 119.06894 | G29: =((G24+G26)+G28) -> 152.69537 | H29: =((H24+H26)+H28) -> 187.78548 | I29: =((I24+I26)+I28) -> 224.54869 | J29: =((J24+J26)+J28) -> 263.19404 | ... AL29: =((AL24+AL26)+AL28) -> 2575.9028
A30: Gross in-app billings, cash basis (= RevenueCat MTR) | B30: bill_gross | C30: =((((C24*Assumptions!$E$35)+(C25*Assumptions!$E$36))+(C27*Assumptions!$E$37))+(C21*Assumptions!$E$38)) -> 1559.1697 | D30: =((((D24*Assumptions!$E$35)+(D25*Assumptions!$E$36))+(D27*Assumptions!$E$37))+(D21*Assumptions!$E$38)) -> 1796.9134 | E30: =((((E24*Assumptions!$E$35)+(E25*Assumptions!$E$36))+(E27*Assumptions!$E$37))+(E21*Assumptions!$E$38)) -> 2017.5941 | F30: =((((F24*Assumptions!$E$35)+(F25*Assumptions!$E$36))+(F27*Assumptions!$E$37))+(F21*Assumptions!$E$38)) -> 2325.7947 | G30: =((((G24*Assumptions!$E$35)+(G25*Assumptions!$E$36))+(G27*Assumptions!$E$37))+(G21*Assumptions!$E$38)) -> 2563.3368 | H30: =((((H24*Assumptions!$E$35)+(H25*Assumptions!$E$36))+(H27*Assumptions!$E$37))+(H21*Assumptions!$E$38)) -> 2805.1382 | I30: =((((I24*Assumptions!$E$35)+(I25*Assumptions!$E$36))+(I27*Assumptions!$E$37))+(I21*Assumptions!$E$38)) -> 3053.9608 | J30: =((((J24*Assumptions!$E$35)+(J25*Assumptions!$E$36))+(J27*Assumptions!$E$37))+(J21*Assumptions!$E$38)) -> 3311.5784 | ... AL30: =((((AL24*Assumptions!$E$35)+(AL25*Assumptions!$E$36))+(AL27*Assumptions!$E$37))+(AL21*Assumptions!$E$38)) -> 25478.736
A32: ACTIVE USERS
A33: New free users this month | B33: free_new | C33: =(C12-C17) -> 1105.34 | D33: =(D12-D17) -> 1196.0429 | E33: =(E12-E17) -> 1278.9476 | F33: =(F12-F17) -> 1428.1552 | G33: =(G12-G17) -> 1526.2746 | H33: =(H12-H17) -> 1630.1519 | I33: =(I12-I17) -> 1740.9636 | J33: =(J12-J17) -> 1859.2102 | ... AL33: =(AL12-AL17) -> 11778.683
A34: Retained free users from earlier months | B34: free_pool | C34: =((0*(1-Assumptions!$E$27))+(0*Assumptions!$E$26)) -> 0 | D34: =((C34*(1-Assumptions!$E$27))+(C33*Assumptions!$E$26)) -> 132.6408 | E34: =((D34*(1-Assumptions!$E$27))+(D33*Assumptions!$E$26)) -> 265.55468 | F34: =((E34*(1-Assumptions!$E$27))+(E33*Assumptions!$E$26)) -> 397.78402 | G34: =((F34*(1-Assumptions!$E$27))+(F33*Assumptions!$E$26)) -> 537.33992 | H34: =((G34*(1-Assumptions!$E$27))+(G33*Assumptions!$E$26)) -> 677.50568 | I34: =((H34*(1-Assumptions!$E$27))+(H33*Assumptions!$E$26)) -> 818.92346 | J34: =((I34*(1-Assumptions!$E$27))+(I33*Assumptions!$E$26)) -> 962.32521 | K34: =((J34*(1-Assumptions!$E$27))+(J33*Assumptions!$E$26)) -> 1108.4444 | ... AL34: =((AK34*(1-Assumptions!$E$27))+(AK33*Assumptions!$E$26)) -> 9469.7587
A35: Free MAU | B35: mau_free | C35: =(C33+C34) -> 1105.34 | D35: =(D33+D34) -> 1328.6837 | E35: =(E33+E34) -> 1544.5023 | F35: =(F33+F34) -> 1825.9392 | G35: =(G33+G34) -> 2063.6145 | H35: =(H33+H34) -> 2307.6576 | I35: =(I33+I34) -> 2559.887 | J35: =(J33+J34) -> 2821.5354 | ... AL35: =(AL33+AL34) -> 21248.441
A36: Total MAU (free + paid) | B36: mau_total | C36: =(C35+C29) -> 1133.3333 | D36: =(D35+D29) -> 1385.6225 | E36: =(E35+E29) -> 1631.2154 | F36: =(F35+F29) -> 1945.0081 | G36: =(G35+G29) -> 2216.3099 | H36: =(H35+H29) -> 2495.4431 | I36: =(I35+I29) -> 2784.4357 | J36: =(J35+J29) -> 3084.7295 | ... AL36: =(AL35+AL29) -> 23824.344
A37: Paid subscribers / MAU | B37: paid_share | C37: =IF(C36=0,0,C29/C36) -> 0.0247 | D37: =IF(D36=0,0,D29/D36) -> 0.04109255 | E37: =IF(E36=0,0,E29/E36) -> 0.053158559 | F37: =IF(F36=0,0,F29/F36) -> 0.06121771 | G37: =IF(G36=0,0,G29/G36) -> 0.06889622 | H37: =IF(H36=0,0,H29/H36) -> 0.075251358 | I37: =IF(I36=0,0,I29/I36) -> 0.080644236 | J37: =IF(J36=0,0,J29/J36) -> 0.085321595 | ... AL37: =IF(AL36=0,0,AL29/AL36) -> 0.10812062
A39: ADS, AFFILIATE, B2B AND LINKING VOLUMES
A40: Free MAU seeing ads | B40: ad_mau | C40: =IF(AND((Assumptions!$E$5=1),(C$2>=Assumptions!$E$46)),(C35*Assumptions!$E$47),0) -> 0 | D40: =IF(AND((Assumptions!$E$5=1),(D$2>=Assumptions!$E$46)),(D35*Assumptions!$E$47),0) -> 0 | E40: =IF(AND((Assumptions!$E$5=1),(E$2>=Assumptions!$E$46)),(E35*Assumptions!$E$47),0) -> 0 | F40: =IF(AND((Assumptions!$E$5=1),(F$2>=Assumptions!$E$46)),(F35*Assumptions!$E$47),0) -> 1278.1574 | G40: =IF(AND((Assumptions!$E$5=1),(G$2>=Assumptions!$E$46)),(G35*Assumptions!$E$47),0) -> 1444.5302 | H40: =IF(AND((Assumptions!$E$5=1),(H$2>=Assumptions!$E$46)),(H35*Assumptions!$E$47),0) -> 1615.3603 | I40: =IF(AND((Assumptions!$E$5=1),(I$2>=Assumptions!$E$46)),(I35*Assumptions!$E$47),0) -> 1791.9209 | J40: =IF(AND((Assumptions!$E$5=1),(J$2>=Assumptions!$E$46)),(J35*Assumptions!$E$47),0) -> 1975.0748 | ... AL40: =IF(AND((Assumptions!$E$5=1),(AL$2>=Assumptions!$E$46)),(AL35*Assumptions!$E$47),0) -> 14873.909
A41: Ad impressions: article / lesson end | B41: imps_article | C41: =(C40*Assumptions!$E$48) -> 0 | D41: =(D40*Assumptions!$E$48) -> 0 | E41: =(E40*Assumptions!$E$48) -> 0 | F41: =(F40*Assumptions!$E$48) -> 10225.259 | G41: =(G40*Assumptions!$E$48) -> 11556.241 | H41: =(H40*Assumptions!$E$48) -> 12922.883 | I41: =(I40*Assumptions!$E$48) -> 14335.367 | J41: =(J40*Assumptions!$E$48) -> 15800.598 | ... AL41: =(AL40*Assumptions!$E$48) -> 118991.27
A42: Ad impressions: screener native | B42: imps_screener | C42: =(C40*Assumptions!$E$49) -> 0 | D42: =(D40*Assumptions!$E$49) -> 0 | E42: =(E40*Assumptions!$E$49) -> 0 | F42: =(F40*Assumptions!$E$49) -> 5112.6297 | G42: =(G40*Assumptions!$E$49) -> 5778.1207 | H42: =(H40*Assumptions!$E$49) -> 6461.4413 | I42: =(I40*Assumptions!$E$49) -> 7167.6837 | J42: =(J40*Assumptions!$E$49) -> 7900.2992 | ... AL42: =(AL40*Assumptions!$E$49) -> 59495.636
A43: Ad impressions: opt-in rewarded | B43: imps_rewarded | C43: =(C40*Assumptions!$E$50) -> 0 | D43: =(D40*Assumptions!$E$50) -> 0 | E43: =(E40*Assumptions!$E$50) -> 0 | F43: =(F40*Assumptions!$E$50) -> 1278.1574 | G43: =(G40*Assumptions!$E$50) -> 1444.5302 | H43: =(H40*Assumptions!$E$50) -> 1615.3603 | I43: =(I40*Assumptions!$E$50) -> 1791.9209 | J43: =(J40*Assumptions!$E$50) -> 1975.0748 | ... AL43: =(AL40*Assumptions!$E$50) -> 14873.909
A44: Affiliate clicks | B44: aff_clicks | C44: =IF(AND((Assumptions!$E$6=1),(C$2>=Assumptions!$E$56)),((C36/1000)*Assumptions!$E$57),0) -> 0 | D44: =IF(AND((Assumptions!$E$6=1),(D$2>=Assumptions!$E$56)),((D36/1000)*Assumptions!$E$57),0) -> 0 | E44: =IF(AND((Assumptions!$E$6=1),(E$2>=Assumptions!$E$56)),((E36/1000)*Assumptions!$E$57),0) -> 0 | F44: =IF(AND((Assumptions!$E$6=1),(F$2>=Assumptions!$E$56)),((F36/1000)*Assumptions!$E$57),0) -> 0 | G44: =IF(AND((Assumptions!$E$6=1),(G$2>=Assumptions!$E$56)),((G36/1000)*Assumptions!$E$57),0) -> 0 | H44: =IF(AND((Assumptions!$E$6=1),(H$2>=Assumptions!$E$56)),((H36/1000)*Assumptions!$E$57),0) -> 0 | I44: =IF(AND((Assumptions!$E$6=1),(I$2>=Assumptions!$E$56)),((I36/1000)*Assumptions!$E$57),0) -> 13.922179 | J44: =IF(AND((Assumptions!$E$6=1),(J$2>=Assumptions!$E$56)),((J36/1000)*Assumptions!$E$57),0) -> 15.423647 | ... AL44: =IF(AND((Assumptions!$E$6=1),(AL$2>=Assumptions!$E$56)),((AL36/1000)*Assumptions!$E$57),0) -> 119.12172
A45: Affiliate funded accounts | B45: aff_funded | C45: =(C44*Assumptions!$E$58) -> 0 | D45: =(D44*Assumptions!$E$58) -> 0 | E45: =(E44*Assumptions!$E$58) -> 0 | F45: =(F44*Assumptions!$E$58) -> 0 | G45: =(G44*Assumptions!$E$58) -> 0 | H45: =(H44*Assumptions!$E$58) -> 0 | I45: =(I44*Assumptions!$E$58) -> 0.55688715 | J45: =(J44*Assumptions!$E$58) -> 0.61694589 | ... AL45: =(AL44*Assumptions!$E$58) -> 4.7648688
A46: Classroom Pro teachers | B46: teachers | C46: =IF(AND((Assumptions!$E$7=1),(C$2>=Assumptions!$E$61)),(Assumptions!$E$62+(Assumptions!$E$63*(C$2-Assumptions!$E$61))),0) -> 0 | D46: =IF(AND((Assumptions!$E$7=1),(D$2>=Assumptions!$E$61)),(Assumptions!$E$62+(Assumptions!$E$63*(D$2-Assumptions!$E$61))),0) -> 0 | E46: =IF(AND((Assumptions!$E$7=1),(E$2>=Assumptions!$E$61)),(Assumptions!$E$62+(Assumptions!$E$63*(E$2-Assumptions!$E$61))),0) -> 0 | F46: =IF(AND((Assumptions!$E$7=1),(F$2>=Assumptions!$E$61)),(Assumptions!$E$62+(Assumptions!$E$63*(F$2-Assumptions!$E$61))),0) -> 0 | G46: =IF(AND((Assumptions!$E$7=1),(G$2>=Assumptions!$E$61)),(Assumptions!$E$62+(Assumptions!$E$63*(G$2-Assumptions!$E$61))),0) -> 0 | H46: =IF(AND((Assumptions!$E$7=1),(H$2>=Assumptions!$E$61)),(Assumptions!$E$62+(Assumptions!$E$63*(H$2-Assumptions!$E$61))),0) -> 0 | I46: =IF(AND((Assumptions!$E$7=1),(I$2>=Assumptions!$E$61)),(Assumptions!$E$62+(Assumptions!$E$63*(I$2-Assumptions!$E$61))),0) -> 0 | J46: =IF(AND((Assumptions!$E$7=1),(J$2>=Assumptions!$E$61)),(Assumptions!$E$62+(Assumptions!$E$63*(J$2-Assumptions!$E$61))),0) -> 0 | ... AL46: =IF(AND((Assumptions!$E$7=1),(AL$2>=Assumptions!$E$61)),(Assumptions!$E$62+(Assumptions!$E$63*(AL$2-Assumptions!$E$61))),0) -> 0
A47: Campus / club licences | B47: campus | C47: =IF(AND((Assumptions!$E$7=1),(C$2>=Assumptions!$E$61)),(Assumptions!$E$65+(Assumptions!$E$66*(C$2-Assumptions!$E$61))),0) -> 0 | D47: =IF(AND((Assumptions!$E$7=1),(D$2>=Assumptions!$E$61)),(Assumptions!$E$65+(Assumptions!$E$66*(D$2-Assumptions!$E$61))),0) -> 0 | E47: =IF(AND((Assumptions!$E$7=1),(E$2>=Assumptions!$E$61)),(Assumptions!$E$65+(Assumptions!$E$66*(E$2-Assumptions!$E$61))),0) -> 0 | F47: =IF(AND((Assumptions!$E$7=1),(F$2>=Assumptions!$E$61)),(Assumptions!$E$65+(Assumptions!$E$66*(F$2-Assumptions!$E$61))),0) -> 0 | G47: =IF(AND((Assumptions!$E$7=1),(G$2>=Assumptions!$E$61)),(Assumptions!$E$65+(Assumptions!$E$66*(G$2-Assumptions!$E$61))),0) -> 0 | H47: =IF(AND((Assumptions!$E$7=1),(H$2>=Assumptions!$E$61)),(Assumptions!$E$65+(Assumptions!$E$66*(H$2-Assumptions!$E$61))),0) -> 0 | I47: =IF(AND((Assumptions!$E$7=1),(I$2>=Assumptions!$E$61)),(Assumptions!$E$65+(Assumptions!$E$66*(I$2-Assumptions!$E$61))),0) -> 0 | J47: =IF(AND((Assumptions!$E$7=1),(J$2>=Assumptions!$E$61)),(Assumptions!$E$65+(Assumptions!$E$66*(J$2-Assumptions!$E$61))),0) -> 0 | ... AL47: =IF(AND((Assumptions!$E$7=1),(AL$2>=Assumptions!$E$61)),(Assumptions!$E$65+(Assumptions!$E$66*(AL$2-Assumptions!$E$61))),0) -> 0
A48: Linking live (1 = yes) | B48: link_on | C48: =IF(AND((Assumptions!$E$9=1),(C$2>=Assumptions!$E$73)),1,0) -> 0 | D48: =IF(AND((Assumptions!$E$9=1),(D$2>=Assumptions!$E$73)),1,0) -> 0 | E48: =IF(AND((Assumptions!$E$9=1),(E$2>=Assumptions!$E$73)),1,0) -> 0 | F48: =IF(AND((Assumptions!$E$9=1),(F$2>=Assumptions!$E$73)),1,0) -> 0 | G48: =IF(AND((Assumptions!$E$9=1),(G$2>=Assumptions!$E$73)),1,0) -> 0 | H48: =IF(AND((Assumptions!$E$9=1),(H$2>=Assumptions!$E$73)),1,0) -> 0 | I48: =IF(AND((Assumptions!$E$9=1),(I$2>=Assumptions!$E$73)),1,0) -> 0 | J48: =IF(AND((Assumptions!$E$9=1),(J$2>=Assumptions!$E$73)),1,0) -> 0 | ... AL48: =IF(AND((Assumptions!$E$9=1),(AL$2>=Assumptions!$E$73)),1,0) -> 1
A49: Linked Items: free users (capped at 1 bank) | B49: items_free | C49: =((C48*C35)*Assumptions!$E$74) -> 0 | D49: =((D48*D35)*Assumptions!$E$74) -> 0 | E49: =((E48*E35)*Assumptions!$E$74) -> 0 | F49: =((F48*F35)*Assumptions!$E$74) -> 0 | G49: =((G48*G35)*Assumptions!$E$74) -> 0 | H49: =((H48*H35)*Assumptions!$E$74) -> 0 | I49: =((I48*I35)*Assumptions!$E$74) -> 0 | J49: =((J48*J35)*Assumptions!$E$74) -> 0 | ... AL49: =((AL48*AL35)*Assumptions!$E$74) -> 2124.8441
A50: Linked Items: Pro users | B50: items_pro | C50: =(((C48*C29)*Assumptions!$E$76)*Assumptions!$E$77) -> 0 | D50: =(((D48*D29)*Assumptions!$E$76)*Assumptions!$E$77) -> 0 | E50: =(((E48*E29)*Assumptions!$E$76)*Assumptions!$E$77) -> 0 | F50: =(((F48*F29)*Assumptions!$E$76)*Assumptions!$E$77) -> 0 | G50: =(((G48*G29)*Assumptions!$E$76)*Assumptions!$E$77) -> 0 | H50: =(((H48*H29)*Assumptions!$E$76)*Assumptions!$E$77) -> 0 | I50: =(((I48*I29)*Assumptions!$E$76)*Assumptions!$E$77) -> 0 | J50: =(((J48*J29)*Assumptions!$E$76)*Assumptions!$E$77) -> 0 | ... AL50: =(((AL48*AL29)*Assumptions!$E$76)*Assumptions!$E$77) -> 2575.9028
A52: REVENUE
A53: Gross: monthly plans | B53: rev_monthly | C53: =(C24*Assumptions!$E$35) -> 127.27169 | D53: =(D24*Assumptions!$E$35) -> 247.51551 | E53: =(E24*Assumptions!$E$35) -> 360.79833 | F53: =(F24*Assumptions!$E$35) -> 475.71002 | G53: =(G24*Assumptions!$E$35) -> 586.14456 | H53: =(H24*Assumptions!$E$35) -> 693.37954 | I53: =(I24*Assumptions!$E$35) -> 798.65263 | J53: =(J24*Assumptions!$E$35) -> 903.08923 | ... AL53: =(AL24*Assumptions!$E$35) -> 7038.7733
A54: Gross: annual plans (recognised 1/12 a month) | B54: rev_annual | C54: =((C26*Assumptions!$E$36)/12) -> 93.299447 | D54: =((D26*Assumptions!$E$36)/12) -> 194.25494 | E54: =((E26*Assumptions!$E$36)/12) -> 302.20824 | F54: =((F26*Assumptions!$E$36)/12) -> 422.75585 | G54: =((G26*Assumptions!$E$36)/12) -> 551.58551 | H54: =((H26*Assumptions!$E$36)/12) -> 689.18323 | I54: =((I26*Assumptions!$E$36)/12) -> 836.13434 | J54: =((J26*Assumptions!$E$36)/12) -> 993.06641 | ... AL54: =((AL26*Assumptions!$E$36)/12) -> 10539.361
A55: Gross: student plans (recognised 1/12 a month) | B55: rev_student | C55: =((C28*Assumptions!$E$37)/12) -> 13.993168 | D55: =((D28*Assumptions!$E$37)/12) -> 29.134598 | E55: =((E28*Assumptions!$E$37)/12) -> 45.325569 | F55: =((F28*Assumptions!$E$37)/12) -> 63.405449 | G55: =((G28*Assumptions!$E$37)/12) -> 82.727482 | H55: =((H28*Assumptions!$E$37)/12) -> 103.36456 | I55: =((I28*Assumptions!$E$37)/12) -> 125.40447 | J55: =((J28*Assumptions!$E$37)/12) -> 148.94134 | ... AL55: =((AL28*Assumptions!$E$37)/12) -> 1509.4228
A56: Gross: Recruiting Pass | B56: rev_pass | C56: =(C21*Assumptions!$E$38) -> 144.38667 | D56: =(D21*Assumptions!$E$38) -> 156.23487 | E56: =(E21*Assumptions!$E$38) -> 167.06442 | F56: =(F21*Assumptions!$E$38) -> 186.55487 | G56: =(G21*Assumptions!$E$38) -> 199.37187 | H56: =(H21*Assumptions!$E$38) -> 212.941 | I56: =(I21*Assumptions!$E$38) -> 227.41594 | J56: =(J21*Assumptions!$E$38) -> 242.86207 | ... AL56: =(AL21*Assumptions!$E$38) -> 1538.6078
A57: Gross in-app sales | B57: rev_iap_gross | C57: =(((C53+C54)+C55)+C56) -> 378.95097 | D57: =(((D53+D54)+D55)+D56) -> 627.13991 | E57: =(((E53+E54)+E55)+E56) -> 875.39656 | F57: =(((F53+F54)+F55)+F56) -> 1148.4262 | G57: =(((G53+G54)+G55)+G56) -> 1419.8294 | H57: =(((H53+H54)+H55)+H56) -> 1698.8683 | I57: =(((I53+I54)+I55)+I56) -> 1987.6074 | J57: =(((J53+J54)+J55)+J56) -> 2287.9591 | ... AL57: =(((AL53+AL54)+AL55)+AL56) -> 20626.165
A58: Less: refunds | B58: refunds | C58: =((-C57)*Assumptions!$E$40) -> -7.5790194 | D58: =((-D57)*Assumptions!$E$40) -> -12.542798 | E58: =((-E57)*Assumptions!$E$40) -> -17.507931 | F58: =((-F57)*Assumptions!$E$40) -> -22.968524 | G58: =((-G57)*Assumptions!$E$40) -> -28.396588 | H58: =((-H57)*Assumptions!$E$40) -> -33.977367 | I58: =((-I57)*Assumptions!$E$40) -> -39.752148 | J58: =((-J57)*Assumptions!$E$40) -> -45.759181 | ... AL58: =((-AL57)*Assumptions!$E$40) -> -412.5233
A59: Less: app store commission | B59: store_fee | C59: =((-(C57+C58))*Assumptions!$E$39) -> -55.705793 | D59: =((-(D57+D58))*Assumptions!$E$39) -> -92.189567 | E59: =((-(E57+E58))*Assumptions!$E$39) -> -128.68329 | F59: =((-(F57+F58))*Assumptions!$E$39) -> -168.81865 | G59: =((-(G57+G58))*Assumptions!$E$39) -> -208.71492 | H59: =((-(H57+H58))*Assumptions!$E$39) -> -249.73364 | I59: =((-(I57+I58))*Assumptions!$E$39) -> -292.17829 | J59: =((-(J57+J58))*Assumptions!$E$39) -> -336.32998 | ... AL59: =((-(AL57+AL58))*Assumptions!$E$39) -> -3032.0462
A60: Subscriptions & in-app, net of store fee | B60: rev_subs_net | C60: =((C57+C58)+C59) -> 315.66616 | D60: =((D57+D58)+D59) -> 522.40755 | E60: =((E57+E58)+E59) -> 729.20534 | F60: =((F57+F58)+F59) -> 956.63902 | G60: =((G57+G58)+G59) -> 1182.7179 | H60: =((H57+H58)+H59) -> 1415.1573 | I60: =((I57+I58)+I59) -> 1655.6769 | J60: =((J57+J58)+J59) -> 1905.8699 | ... AL60: =((AL57+AL58)+AL59) -> 17181.595
A61: Ads: article / lesson end | B61: rev_ads_article | C61: =(((C41/1000)*Assumptions!$E$51)*Assumptions!$E$54) -> 0 | D61: =(((D41/1000)*Assumptions!$E$51)*Assumptions!$E$54) -> 0 | E61: =(((E41/1000)*Assumptions!$E$51)*Assumptions!$E$54) -> 0 | F61: =(((F41/1000)*Assumptions!$E$51)*Assumptions!$E$54) -> 21.728676 | G61: =(((G41/1000)*Assumptions!$E$51)*Assumptions!$E$54) -> 24.557013 | H61: =(((H41/1000)*Assumptions!$E$51)*Assumptions!$E$54) -> 27.461125 | I61: =(((I41/1000)*Assumptions!$E$51)*Assumptions!$E$54) -> 30.462656 | J61: =(((J41/1000)*Assumptions!$E$51)*Assumptions!$E$54) -> 33.576272 | ... AL61: =(((AL41/1000)*Assumptions!$E$51)*Assumptions!$E$54) -> 252.85645
A62: Ads: screener native | B62: rev_ads_screener | C62: =(((C42/1000)*Assumptions!$E$52)*Assumptions!$E$54) -> 0 | D62: =(((D42/1000)*Assumptions!$E$52)*Assumptions!$E$54) -> 0 | E62: =(((E42/1000)*Assumptions!$E$52)*Assumptions!$E$54) -> 0 | F62: =(((F42/1000)*Assumptions!$E$52)*Assumptions!$E$54) -> 13.037206 | G62: =(((G42/1000)*Assumptions!$E$52)*Assumptions!$E$54) -> 14.734208 | H62: =(((H42/1000)*Assumptions!$E$52)*Assumptions!$E$54) -> 16.476675 | I62: =(((I42/1000)*Assumptions!$E$52)*Assumptions!$E$54) -> 18.277594 | J62: =(((J42/1000)*Assumptions!$E$52)*Assumptions!$E$54) -> 20.145763 | ... AL62: =(((AL42/1000)*Assumptions!$E$52)*Assumptions!$E$54) -> 151.71387
A63: Ads: opt-in rewarded | B63: rev_ads_rewarded | C63: =(((C43/1000)*Assumptions!$E$53)*Assumptions!$E$54) -> 0 | D63: =(((D43/1000)*Assumptions!$E$53)*Assumptions!$E$54) -> 0 | E63: =(((E43/1000)*Assumptions!$E$53)*Assumptions!$E$54) -> 0 | F63: =(((F43/1000)*Assumptions!$E$53)*Assumptions!$E$54) -> 13.037206 | G63: =(((G43/1000)*Assumptions!$E$53)*Assumptions!$E$54) -> 14.734208 | H63: =(((H43/1000)*Assumptions!$E$53)*Assumptions!$E$54) -> 16.476675 | I63: =(((I43/1000)*Assumptions!$E$53)*Assumptions!$E$54) -> 18.277594 | J63: =(((J43/1000)*Assumptions!$E$53)*Assumptions!$E$54) -> 20.145763 | ... AL63: =(((AL43/1000)*Assumptions!$E$53)*Assumptions!$E$54) -> 151.71387
A64: Advertising revenue | B64: rev_ads | C64: =((C61+C62)+C63) -> 0 | D64: =((D61+D62)+D63) -> 0 | E64: =((E61+E62)+E63) -> 0 | F64: =((F61+F62)+F63) -> 47.803088 | G64: =((G61+G62)+G63) -> 54.025428 | H64: =((H61+H62)+H63) -> 60.414476 | I64: =((I61+I62)+I63) -> 67.017843 | J64: =((J61+J62)+J63) -> 73.867797 | ... AL64: =((AL61+AL62)+AL63) -> 556.28419
A65: Affiliate revenue | B65: rev_aff | C65: =(C45*Assumptions!$E$59) -> 0 | D65: =(D45*Assumptions!$E$59) -> 0 | E65: =(E45*Assumptions!$E$59) -> 0 | F65: =(F45*Assumptions!$E$59) -> 0 | G65: =(G45*Assumptions!$E$59) -> 0 | H65: =(H45*Assumptions!$E$59) -> 0 | I65: =(I45*Assumptions!$E$59) -> 27.844357 | J65: =(J45*Assumptions!$E$59) -> 30.847295 | ... AL65: =(AL45*Assumptions!$E$59) -> 238.24344
A66: B2B / Edu licence revenue | B66: rev_b2b | C66: =(((C46*Assumptions!$E$64)/12)+((C47*Assumptions!$E$67)/12)) -> 0 | D66: =(((D46*Assumptions!$E$64)/12)+((D47*Assumptions!$E$67)/12)) -> 0 | E66: =(((E46*Assumptions!$E$64)/12)+((E47*Assumptions!$E$67)/12)) -> 0 | F66: =(((F46*Assumptions!$E$64)/12)+((F47*Assumptions!$E$67)/12)) -> 0 | G66: =(((G46*Assumptions!$E$64)/12)+((G47*Assumptions!$E$67)/12)) -> 0 | H66: =(((H46*Assumptions!$E$64)/12)+((H47*Assumptions!$E$67)/12)) -> 0 | I66: =(((I46*Assumptions!$E$64)/12)+((I47*Assumptions!$E$67)/12)) -> 0 | J66: =(((J46*Assumptions!$E$64)/12)+((J47*Assumptions!$E$67)/12)) -> 0 | ... AL66: =(((AL46*Assumptions!$E$64)/12)+((AL47*Assumptions!$E$67)/12)) -> 0
A67: TOTAL REVENUE | B67: rev_total | C67: =(((C60+C64)+C65)+C66) -> 315.66616 | D67: =(((D60+D64)+D65)+D66) -> 522.40755 | E67: =(((E60+E64)+E65)+E66) -> 729.20534 | F67: =(((F60+F64)+F65)+F66) -> 1004.4421 | G67: =(((G60+G64)+G65)+G66) -> 1236.7433 | H67: =(((H60+H64)+H65)+H66) -> 1475.5718 | I67: =(((I60+I64)+I65)+I66) -> 1750.5391 | J67: =(((J60+J64)+J65)+J66) -> 2010.585 | ... AL67: =(((AL60+AL64)+AL65)+AL66) -> 17976.123
A69: COST OF REVENUE (COGS)
A70: Data licensing (beta, or scale phase above MAU threshold) | B70: cogs_data | C70: =IF((C36>=Assumptions!$E$72),Assumptions!$E$71,Assumptions!$E$70) -> 400 | D70: =IF((D36>=Assumptions!$E$72),Assumptions!$E$71,Assumptions!$E$70) -> 400 | E70: =IF((E36>=Assumptions!$E$72),Assumptions!$E$71,Assumptions!$E$70) -> 400 | F70: =IF((F36>=Assumptions!$E$72),Assumptions!$E$71,Assumptions!$E$70) -> 400 | G70: =IF((G36>=Assumptions!$E$72),Assumptions!$E$71,Assumptions!$E$70) -> 400 | H70: =IF((H36>=Assumptions!$E$72),Assumptions!$E$71,Assumptions!$E$70) -> 400 | I70: =IF((I36>=Assumptions!$E$72),Assumptions!$E$71,Assumptions!$E$70) -> 400 | J70: =IF((J36>=Assumptions!$E$72),Assumptions!$E$71,Assumptions!$E$70) -> 400 | ... AL70: =IF((AL36>=Assumptions!$E$72),Assumptions!$E$71,Assumptions!$E$70) -> 400
A71: Plaid / aggregation | B71: cogs_plaid | C71: =(((C49*Assumptions!$E$75)+(C50*Assumptions!$E$78))+(C48*Assumptions!$E$79)) -> 0 | D71: =(((D49*Assumptions!$E$75)+(D50*Assumptions!$E$78))+(D48*Assumptions!$E$79)) -> 0 | E71: =(((E49*Assumptions!$E$75)+(E50*Assumptions!$E$78))+(E48*Assumptions!$E$79)) -> 0 | F71: =(((F49*Assumptions!$E$75)+(F50*Assumptions!$E$78))+(F48*Assumptions!$E$79)) -> 0 | G71: =(((G49*Assumptions!$E$75)+(G50*Assumptions!$E$78))+(G48*Assumptions!$E$79)) -> 0 | H71: =(((H49*Assumptions!$E$75)+(H50*Assumptions!$E$78))+(H48*Assumptions!$E$79)) -> 0 | I71: =(((I49*Assumptions!$E$75)+(I50*Assumptions!$E$78))+(I48*Assumptions!$E$79)) -> 0 | J71: =(((J49*Assumptions!$E$75)+(J50*Assumptions!$E$78))+(J48*Assumptions!$E$79)) -> 0 | ... AL71: =(((AL49*Assumptions!$E$75)+(AL50*Assumptions!$E$78))+(AL48*Assumptions!$E$79)) -> 2859.3118
A72: Hosting / Supabase / Expo | B72: cogs_hosting | C72: =(Assumptions!$E$80+(Assumptions!$E$81*C36)) -> 61.333333 | D72: =(Assumptions!$E$80+(Assumptions!$E$81*D36)) -> 63.856225 | E72: =(Assumptions!$E$80+(Assumptions!$E$81*E36)) -> 66.312154 | F72: =(Assumptions!$E$80+(Assumptions!$E$81*F36)) -> 69.450081 | G72: =(Assumptions!$E$80+(Assumptions!$E$81*G36)) -> 72.163099 | H72: =(Assumptions!$E$80+(Assumptions!$E$81*H36)) -> 74.954431 | I72: =(Assumptions!$E$80+(Assumptions!$E$81*I36)) -> 77.844357 | J72: =(Assumptions!$E$80+(Assumptions!$E$81*J36)) -> 80.847295 | ... AL72: =(Assumptions!$E$80+(Assumptions!$E$81*AL36)) -> 288.24344
A73: LLM tutor tokens | B73: cogs_llm | C73: =IF(AND((Assumptions!$E$8=1),(C$2>=Assumptions!$E$82)),((C29*Assumptions!$E$83)+(C35*Assumptions!$E$84)),0) -> 0 | D73: =IF(AND((Assumptions!$E$8=1),(D$2>=Assumptions!$E$82)),((D29*Assumptions!$E$83)+(D35*Assumptions!$E$84)),0) -> 0 | E73: =IF(AND((Assumptions!$E$8=1),(E$2>=Assumptions!$E$82)),((E29*Assumptions!$E$83)+(E35*Assumptions!$E$84)),0) -> 0 | F73: =IF(AND((Assumptions!$E$8=1),(F$2>=Assumptions!$E$82)),((F29*Assumptions!$E$83)+(F35*Assumptions!$E$84)),0) -> 0 | G73: =IF(AND((Assumptions!$E$8=1),(G$2>=Assumptions!$E$82)),((G29*Assumptions!$E$83)+(G35*Assumptions!$E$84)),0) -> 0 | H73: =IF(AND((Assumptions!$E$8=1),(H$2>=Assumptions!$E$82)),((H29*Assumptions!$E$83)+(H35*Assumptions!$E$84)),0) -> 0 | I73: =IF(AND((Assumptions!$E$8=1),(I$2>=Assumptions!$E$82)),((I29*Assumptions!$E$83)+(I35*Assumptions!$E$84)),0) -> 126.64578 | J73: =IF(AND((Assumptions!$E$8=1),(J$2>=Assumptions!$E$82)),((J29*Assumptions!$E$83)+(J35*Assumptions!$E$84)),0) -> 146.65267 | ... AL73: =IF(AND((Assumptions!$E$8=1),(AL$2>=Assumptions!$E$82)),((AL29*Assumptions!$E$83)+(AL35*Assumptions!$E$84)),0) -> 1371.6407
A74: RevenueCat (1% of MTR above $2.5k) | B74: cogs_rc | C74: =(MAX(0,(C30-Assumptions!$E$85))*Assumptions!$E$86) -> 0 | D74: =(MAX(0,(D30-Assumptions!$E$85))*Assumptions!$E$86) -> 0 | E74: =(MAX(0,(E30-Assumptions!$E$85))*Assumptions!$E$86) -> 0 | F74: =(MAX(0,(F30-Assumptions!$E$85))*Assumptions!$E$86) -> 0 | G74: =(MAX(0,(G30-Assumptions!$E$85))*Assumptions!$E$86) -> 0.63336755 | H74: =(MAX(0,(H30-Assumptions!$E$85))*Assumptions!$E$86) -> 3.0513821 | I74: =(MAX(0,(I30-Assumptions!$E$85))*Assumptions!$E$86) -> 5.5396083 | J74: =(MAX(0,(J30-Assumptions!$E$85))*Assumptions!$E$86) -> 8.1157844 | ... AL74: =(MAX(0,(AL30-Assumptions!$E$85))*Assumptions!$E$86) -> 229.78736
A75: B2B card processing | B75: cogs_b2b | C75: =(C66*Assumptions!$E$68) -> 0 | D75: =(D66*Assumptions!$E$68) -> 0 | E75: =(E66*Assumptions!$E$68) -> 0 | F75: =(F66*Assumptions!$E$68) -> 0 | G75: =(G66*Assumptions!$E$68) -> 0 | H75: =(H66*Assumptions!$E$68) -> 0 | I75: =(I66*Assumptions!$E$68) -> 0 | J75: =(J66*Assumptions!$E$68) -> 0 | ... AL75: =(AL66*Assumptions!$E$68) -> 0
A76: Total COGS | B76: cogs_total | C76: =(((((C70+C71)+C72)+C73)+C74)+C75) -> 461.33333 | D76: =(((((D70+D71)+D72)+D73)+D74)+D75) -> 463.85622 | E76: =(((((E70+E71)+E72)+E73)+E74)+E75) -> 466.31215 | F76: =(((((F70+F71)+F72)+F73)+F74)+F75) -> 469.45008 | G76: =(((((G70+G71)+G72)+G73)+G74)+G75) -> 472.79647 | H76: =(((((H70+H71)+H72)+H73)+H74)+H75) -> 478.00581 | I76: =(((((I70+I71)+I72)+I73)+I74)+I75) -> 610.02975 | J76: =(((((J70+J71)+J72)+J73)+J74)+J75) -> 635.61575 | ... AL76: =(((((AL70+AL71)+AL72)+AL73)+AL74)+AL75) -> 5148.9833
A77: GROSS PROFIT | B77: gross_profit | C77: =(C67-C76) -> -145.66717 | D77: =(D67-D76) -> 58.551321 | E77: =(E67-E76) -> 262.89318 | F77: =(F67-F76) -> 534.99202 | G77: =(G67-G76) -> 763.94687 | H77: =(H67-H76) -> 997.56598 | I77: =(I67-I76) -> 1140.5094 | J77: =(J67-J76) -> 1374.9692 | ... AL77: =(AL67-AL76) -> 12827.14
A78: Gross margin | B78: gross_margin | C78: =IF(C67=0,0,C77/C67) -> -0.46145958 | D78: =IF(D67=0,0,D77/D67) -> 0.11207978 | E78: =IF(E67=0,0,E77/E67) -> 0.3605201 | F78: =IF(F67=0,0,F77/F67) -> 0.53262604 | G78: =IF(G67=0,0,G77/G67) -> 0.6177085 | H78: =IF(H67=0,0,H77/H67) -> 0.67605384 | I78: =IF(I67=0,0,I77/I67) -> 0.65151893 | J78: =IF(J67=0,0,J77/J67) -> 0.68386526 | ... AL78: =IF(AL67=0,0,AL77/AL67) -> 0.71356542
A80: OPERATING EXPENSES
A81: Founder salary | B81: opex_founder | C81: =(Assumptions!$E$10*Assumptions!$E$88) -> 0 | D81: =(Assumptions!$E$10*Assumptions!$E$88) -> 0 | E81: =(Assumptions!$E$10*Assumptions!$E$88) -> 0 | F81: =(Assumptions!$E$10*Assumptions!$E$88) -> 0 | G81: =(Assumptions!$E$10*Assumptions!$E$88) -> 0 | H81: =(Assumptions!$E$10*Assumptions!$E$88) -> 0 | I81: =(Assumptions!$E$10*Assumptions!$E$88) -> 0 | J81: =(Assumptions!$E$10*Assumptions!$E$88) -> 0 | ... AL81: =(Assumptions!$E$10*Assumptions!$E$88) -> 0
A82: Contractors | B82: opex_contractors | C82: =CHOOSE(C$3,Assumptions!$E$89,Assumptions!$E$90,Assumptions!$E$91) -> 500 | D82: =CHOOSE(D$3,Assumptions!$E$89,Assumptions!$E$90,Assumptions!$E$91) -> 500 | E82: =CHOOSE(E$3,Assumptions!$E$89,Assumptions!$E$90,Assumptions!$E$91) -> 500 | F82: =CHOOSE(F$3,Assumptions!$E$89,Assumptions!$E$90,Assumptions!$E$91) -> 500 | G82: =CHOOSE(G$3,Assumptions!$E$89,Assumptions!$E$90,Assumptions!$E$91) -> 500 | H82: =CHOOSE(H$3,Assumptions!$E$89,Assumptions!$E$90,Assumptions!$E$91) -> 500 | I82: =CHOOSE(I$3,Assumptions!$E$89,Assumptions!$E$90,Assumptions!$E$91) -> 500 | J82: =CHOOSE(J$3,Assumptions!$E$89,Assumptions!$E$90,Assumptions!$E$91) -> 500 | ... AL82: =CHOOSE(AL$3,Assumptions!$E$89,Assumptions!$E$90,Assumptions!$E$91) -> 3000
A83: Marketing: Apple Search Ads | B83: opex_asa | C83: =C10 -> 500 | D83: =D10 -> 515 | E83: =E10 -> 530.45 | F83: =F10 -> 546.3635 | G83: =G10 -> 562.75441 | H83: =H10 -> 579.63704 | I83: =I10 -> 597.02615 | J83: =J10 -> 614.93693 | ... AL83: =AL10 -> 1406.9312
A84: Marketing: creators | B84: opex_creators | C84: =C8 -> 0 | D84: =D8 -> 0 | E84: =E8 -> 0 | F84: =F8 -> 500 | G84: =G8 -> 525 | H84: =H8 -> 551.25 | I84: =I8 -> 578.8125 | J84: =J8 -> 607.75312 | ... AL84: =AL8 -> 2382.4707
A85: Marketing: other | B85: opex_mkt_other | C85: =Assumptions!$E$92 -> 150 | D85: =Assumptions!$E$92 -> 150 | E85: =Assumptions!$E$92 -> 150 | F85: =Assumptions!$E$92 -> 150 | G85: =Assumptions!$E$92 -> 150 | H85: =Assumptions!$E$92 -> 150 | I85: =Assumptions!$E$92 -> 150 | J85: =Assumptions!$E$92 -> 150 | ... AL85: =Assumptions!$E$92 -> 150
A86: Legal & compliance | B86: opex_legal | C86: =(((IF((C$2=1),(((Assumptions!$E$93+Assumptions!$E$94)+Assumptions!$E$95)+Assumptions!$E$96),0)+Assumptions!$E$97)+IF(AND((C$2>1),(MOD((C$2-1),12)=0)),Assumptions!$E$98,0))+IF(AND((Assumptions!$E$11=1),(C$2>=Assumptions!$E$99)),Assumptions!$E$100,0)) -> 3800 | D86: =(((IF((D$2=1),(((Assumptions!$E$93+Assumptions!$E$94)+Assumptions!$E$95)+Assumptions!$E$96),0)+Assumptions!$E$97)+IF(AND((D$2>1),(MOD((D$2-1),12)=0)),Assumptions!$E$98,0))+IF(AND((Assumptions!$E$11=1),(D$2>=Assumptions!$E$99)),Assumptions!$E$100,0)) -> 100 | E86: =(((IF((E$2=1),(((Assumptions!$E$93+Assumptions!$E$94)+Assumptions!$E$95)+Assumptions!$E$96),0)+Assumptions!$E$97)+IF(AND((E$2>1),(MOD((E$2-1),12)=0)),Assumptions!$E$98,0))+IF(AND((Assumptions!$E$11=1),(E$2>=Assumptions!$E$99)),Assumptions!$E$100,0)) -> 100 | F86: =(((IF((F$2=1),(((Assumptions!$E$93+Assumptions!$E$94)+Assumptions!$E$95)+Assumptions!$E$96),0)+Assumptions!$E$97)+IF(AND((F$2>1),(MOD((F$2-1),12)=0)),Assumptions!$E$98,0))+IF(AND((Assumptions!$E$11=1),(F$2>=Assumptions!$E$99)),Assumptions!$E$100,0)) -> 100 | G86: =(((IF((G$2=1),(((Assumptions!$E$93+Assumptions!$E$94)+Assumptions!$E$95)+Assumptions!$E$96),0)+Assumptions!$E$97)+IF(AND((G$2>1),(MOD((G$2-1),12)=0)),Assumptions!$E$98,0))+IF(AND((Assumptions!$E$11=1),(G$2>=Assumptions!$E$99)),Assumptions!$E$100,0)) -> 100 | H86: =(((IF((H$2=1),(((Assumptions!$E$93+Assumptions!$E$94)+Assumptions!$E$95)+Assumptions!$E$96),0)+Assumptions!$E$97)+IF(AND((H$2>1),(MOD((H$2-1),12)=0)),Assumptions!$E$98,0))+IF(AND((Assumptions!$E$11=1),(H$2>=Assumptions!$E$99)),Assumptions!$E$100,0)) -> 100 | I86: =(((IF((I$2=1),(((Assumptions!$E$93+Assumptions!$E$94)+Assumptions!$E$95)+Assumptions!$E$96),0)+Assumptions!$E$97)+IF(AND((I$2>1),(MOD((I$2-1),12)=0)),Assumptions!$E$98,0))+IF(AND((Assumptions!$E$11=1),(I$2>=Assumptions!$E$99)),Assumptions!$E$100,0)) -> 100 | J86: =(((IF((J$2=1),(((Assumptions!$E$93+Assumptions!$E$94)+Assumptions!$E$95)+Assumptions!$E$96),0)+Assumptions!$E$97)+IF(AND((J$2>1),(MOD((J$2-1),12)=0)),Assumptions!$E$98,0))+IF(AND((Assumptions!$E$11=1),(J$2>=Assumptions!$E$99)),Assumptions!$E$100,0)) -> 100 | ... AL86: =(((IF((AL$2=1),(((Assumptions!$E$93+Assumptions!$E$94)+Assumptions!$E$95)+Assumptions!$E$96),0)+Assumptions!$E$97)+IF(AND((AL$2>1),(MOD((AL$2-1),12)=0)),Assumptions!$E$98,0))+IF(AND((Assumptions!$E$11=1),(AL$2>=Assumptions!$E$99)),Assumptions!$E$100,0)) -> 100
A87: Software / tools | B87: opex_tools | C87: =CHOOSE(C$3,Assumptions!$E$101,Assumptions!$E$102,Assumptions!$E$103) -> 150 | D87: =CHOOSE(D$3,Assumptions!$E$101,Assumptions!$E$102,Assumptions!$E$103) -> 150 | E87: =CHOOSE(E$3,Assumptions!$E$101,Assumptions!$E$102,Assumptions!$E$103) -> 150 | F87: =CHOOSE(F$3,Assumptions!$E$101,Assumptions!$E$102,Assumptions!$E$103) -> 150 | G87: =CHOOSE(G$3,Assumptions!$E$101,Assumptions!$E$102,Assumptions!$E$103) -> 150 | H87: =CHOOSE(H$3,Assumptions!$E$101,Assumptions!$E$102,Assumptions!$E$103) -> 150 | I87: =CHOOSE(I$3,Assumptions!$E$101,Assumptions!$E$102,Assumptions!$E$103) -> 150 | J87: =CHOOSE(J$3,Assumptions!$E$101,Assumptions!$E$102,Assumptions!$E$103) -> 150 | ... AL87: =CHOOSE(AL$3,Assumptions!$E$101,Assumptions!$E$102,Assumptions!$E$103) -> 400
A88: Apple / Google developer fees | B88: opex_stores | C88: =(IF((MOD((C$2-1),12)=0),Assumptions!$E$104,0)+IF((C$2=1),Assumptions!$E$105,0)) -> 124 | D88: =(IF((MOD((D$2-1),12)=0),Assumptions!$E$104,0)+IF((D$2=1),Assumptions!$E$105,0)) -> 0 | E88: =(IF((MOD((E$2-1),12)=0),Assumptions!$E$104,0)+IF((E$2=1),Assumptions!$E$105,0)) -> 0 | F88: =(IF((MOD((F$2-1),12)=0),Assumptions!$E$104,0)+IF((F$2=1),Assumptions!$E$105,0)) -> 0 | G88: =(IF((MOD((G$2-1),12)=0),Assumptions!$E$104,0)+IF((G$2=1),Assumptions!$E$105,0)) -> 0 | H88: =(IF((MOD((H$2-1),12)=0),Assumptions!$E$104,0)+IF((H$2=1),Assumptions!$E$105,0)) -> 0 | I88: =(IF((MOD((I$2-1),12)=0),Assumptions!$E$104,0)+IF((I$2=1),Assumptions!$E$105,0)) -> 0 | J88: =(IF((MOD((J$2-1),12)=0),Assumptions!$E$104,0)+IF((J$2=1),Assumptions!$E$105,0)) -> 0 | ... AL88: =(IF((MOD((AL$2-1),12)=0),Assumptions!$E$104,0)+IF((AL$2=1),Assumptions!$E$105,0)) -> 0
A89: Insurance | B89: opex_insurance | C89: =Assumptions!$E$106 -> 100 | D89: =Assumptions!$E$106 -> 100 | E89: =Assumptions!$E$106 -> 100 | F89: =Assumptions!$E$106 -> 100 | G89: =Assumptions!$E$106 -> 100 | H89: =Assumptions!$E$106 -> 100 | I89: =Assumptions!$E$106 -> 100 | J89: =Assumptions!$E$106 -> 100 | ... AL89: =Assumptions!$E$106 -> 100
A90: Total operating expenses | B90: opex_total | C90: =((((((((C81+C82)+C83)+C84)+C85)+C86)+C87)+C88)+C89) -> 5324 | D90: =((((((((D81+D82)+D83)+D84)+D85)+D86)+D87)+D88)+D89) -> 1515 | E90: =((((((((E81+E82)+E83)+E84)+E85)+E86)+E87)+E88)+E89) -> 1530.45 | F90: =((((((((F81+F82)+F83)+F84)+F85)+F86)+F87)+F88)+F89) -> 2046.3635 | G90: =((((((((G81+G82)+G83)+G84)+G85)+G86)+G87)+G88)+G89) -> 2087.7544 | H90: =((((((((H81+H82)+H83)+H84)+H85)+H86)+H87)+H88)+H89) -> 2130.887 | I90: =((((((((I81+I82)+I83)+I84)+I85)+I86)+I87)+I88)+I89) -> 2175.8386 | J90: =((((((((J81+J82)+J83)+J84)+J85)+J86)+J87)+J88)+J89) -> 2222.6901 | ... AL90: =((((((((AL81+AL82)+AL83)+AL84)+AL85)+AL86)+AL87)+AL88)+AL89) -> 7539.402
A91: OPERATING INCOME (EBIT) | B91: ebit | C91: =(C77-C90) -> -5469.6672 | D91: =(D77-D90) -> -1456.4487 | E91: =(E77-E90) -> -1267.5568 | F91: =(F77-F90) -> -1511.3715 | G91: =(G77-G90) -> -1323.8075 | H91: =(H77-H90) -> -1133.3211 | I91: =(I77-I90) -> -1035.3292 | J91: =(J77-J90) -> -847.72083 | ... AL91: =(AL77-AL90) -> 5287.7377
A92: Operating margin | B92: ebit_margin | C92: =IF(C67=0,0,C91/C67) -> -17.327379 | D92: =IF(D67=0,0,D91/D67) -> -2.7879549 | E92: =IF(E67=0,0,E91/E67) -> -1.7382715 | F92: =IF(F67=0,0,F91/F67) -> -1.5046875 | G92: =IF(G67=0,0,G91/G67) -> -1.070398 | H92: =IF(H67=0,0,H91/H67) -> -0.76805551 | I92: =IF(I67=0,0,I91/I67) -> -0.5914345 | J92: =IF(J67=0,0,J91/J67) -> -0.42162895 | ... AL92: =IF(AL67=0,0,AL91/AL67) -> 0.2941534
A94: CASH
A95: In-app billings net of refunds & store fee | B95: bill_net | C95: =(C30*Assumptions!$E$112) -> 1298.7884 | D95: =(D30*Assumptions!$E$112) -> 1496.8289 | E95: =(E30*Assumptions!$E$112) -> 1680.6559 | F95: =(F30*Assumptions!$E$112) -> 1937.387 | G95: =(G30*Assumptions!$E$112) -> 2135.2595 | H95: =(H30*Assumptions!$E$112) -> 2336.6801 | I95: =(I30*Assumptions!$E$112) -> 2543.9494 | J95: =(J30*Assumptions!$E$112) -> 2758.5448 | ... AL95: =(AL30*Assumptions!$E$112) -> 21223.787
A96: Change in deferred revenue (annual plans paid upfront) | B96: deferred_chg | C96: =(C95-C60) -> 983.12223 | D96: =(D95-D60) -> 974.42133 | E96: =(E95-E60) -> 951.45053 | F96: =(F95-F60) -> 980.74796 | G96: =(G95-G60) -> 952.54161 | H96: =(H95-H60) -> 921.52281 | I96: =(I95-I60) -> 888.27242 | J96: =(J95-J60) -> 852.67495 | ... AL96: =(AL95-AL60) -> 4042.1919
A97: Operating cash flow | B97: cash_flow | C97: =(C91+C96) -> -4486.5449 | D97: =(D91+D96) -> -482.02734 | E97: =(E91+E96) -> -316.10629 | F97: =(F91+F96) -> -530.62352 | G97: =(G91+G96) -> -371.26593 | H97: =(H91+H96) -> -211.79824 | I97: =(I91+I96) -> -147.05683 | J97: =(J91+J96) -> 4.9541279 | ... AL97: =(AL91+AL96) -> 9329.9296
A98: Cumulative cash (from $0 at launch) | B98: cash_cum | C98: =(0+C97) -> -4486.5449 | D98: =(C98+D97) -> -4968.5723 | E98: =(D98+E97) -> -5284.6786 | F98: =(E98+F97) -> -5815.3021 | G98: =(F98+G97) -> -6186.568 | H98: =(G98+H97) -> -6398.3663 | I98: =(H98+I97) -> -6545.4231 | J98: =(I98+J97) -> -6540.469 | K98: =(J98+K97) -> -6377.6107 | ... AL98: =(AK98+AL97) -> 66136.769
A99: Cumulative operating income | B99: ebit_cum | C99: =(0+C91) -> -5469.6672 | D99: =(C99+D91) -> -6926.1159 | E99: =(D99+E91) -> -8193.6727 | F99: =(E99+F91) -> -9705.0441 | G99: =(F99+G91) -> -11028.852 | H99: =(G99+H91) -> -12162.173 | I99: =(H99+I91) -> -13197.502 | J99: =(I99+J91) -> -14045.223 | K99: =(J99+K91) -> -14696.96 | ... AL99: =(AK99+AL91) -> 3091.4471
A101: KPIs
A102: ARPU: total revenue / MAU | B102: arpu | C102: =IF(C36=0,0,C67/C36) -> 0.27852896 | D102: =IF(D36=0,0,D67/D36) -> 0.37702012 | E102: =IF(E36=0,0,E67/E36) -> 0.44703192 | F102: =IF(F36=0,0,F67/F36) -> 0.51642052 | G102: =IF(G36=0,0,G67/G36) -> 0.55801914 | H102: =IF(H36=0,0,H67/H36) -> 0.59130654 | I102: =IF(I36=0,0,I67/I36) -> 0.62868721 | J102: =IF(J36=0,0,J67/J36) -> 0.65178649 | ... AL102: =IF(AL36=0,0,AL67/AL36) -> 0.75452751
A103: ARPPU: net subscription revenue / paid subscriber | B103: arppu | C103: =IF(C29=0,0,C60/C29) -> 11.276476 | D103: =IF(D29=0,0,D60/D29) -> 9.174902 | E103: =IF(E29=0,0,E60/E29) -> 8.4094063 | F103: =IF(F29=0,0,F60/F29) -> 8.0343285 | G103: =IF(G29=0,0,G60/G29) -> 7.7456041 | H103: =IF(H29=0,0,H60/H29) -> 7.5360317 | I103: =IF(I29=0,0,I60/I29) -> 7.3733538 | J103: =IF(J29=0,0,J60/J29) -> 7.241311 | ... AL103: =IF(AL29=0,0,AL60/AL29) -> 6.6701257
A104: CAC: paid channels (ASA + creators) per payer they bring | B104: cac_paid | C104: =IF(((C11+C9)*Assumptions!$E$111)=0,0,(C10+C8)/((C11+C9)*Assumptions!$E$111)) -> 242.91498 | D104: =IF(((D11+D9)*Assumptions!$E$111)=0,0,(D10+D8)/((D11+D9)*Assumptions!$E$111)) -> 242.91498 | E104: =IF(((E11+E9)*Assumptions!$E$111)=0,0,(E10+E8)/((E11+E9)*Assumptions!$E$111)) -> 242.91498 | F104: =IF(((F11+F9)*Assumptions!$E$111)=0,0,(F10+F8)/((F11+F9)*Assumptions!$E$111)) -> 275.87089 | G104: =IF(((G11+G9)*Assumptions!$E$111)=0,0,(G10+G8)/((G11+G9)*Assumptions!$E$111)) -> 276.24738 | H104: =IF(((H11+H9)*Assumptions!$E$111)=0,0,(H10+H8)/((H11+H9)*Assumptions!$E$111)) -> 276.62516 | I104: =IF(((I11+I9)*Assumptions!$E$111)=0,0,(I10+I8)/((I11+I9)*Assumptions!$E$111)) -> 277.00415 | J104: =IF(((J11+J9)*Assumptions!$E$111)=0,0,(J10+J8)/((J11+J9)*Assumptions!$E$111)) -> 277.3843 | ... AL104: =IF(((AL11+AL9)*Assumptions!$E$111)=0,0,(AL10+AL8)/((AL11+AL9)*Assumptions!$E$111)) -> 288.21687
A105: EBIT >= 0 this month (1 = yes) | B105: flag_be | C105: =IF((C91>=0),1,0) -> 0 | D105: =IF((D91>=0),1,0) -> 0 | E105: =IF((E91>=0),1,0) -> 0 | F105: =IF((F91>=0),1,0) -> 0 | G105: =IF((G91>=0),1,0) -> 0 | H105: =IF((H91>=0),1,0) -> 0 | I105: =IF((I91>=0),1,0) -> 0 | J105: =IF((J91>=0),1,0) -> 0 | ... AL105: =IF((AL91>=0),1,0) -> 1
A106: EBIT >= 0 this month and every month after | B106: flag_be_sus | C106: =IF(AND((C91>=0),(D106=1)),1,0) -> 0 | D106: =IF(AND((D91>=0),(E106=1)),1,0) -> 0 | E106: =IF(AND((E91>=0),(F106=1)),1,0) -> 0 | F106: =IF(AND((F91>=0),(G106=1)),1,0) -> 0 | G106: =IF(AND((G91>=0),(H106=1)),1,0) -> 0 | H106: =IF(AND((H91>=0),(I106=1)),1,0) -> 0 | I106: =IF(AND((I91>=0),(J106=1)),1,0) -> 0 | J106: =IF(AND((J91>=0),(K106=1)),1,0) -> 0 | ... AK106: =IF(AND((AK91>=0),(AL106=1)),1,0) -> 1 | AL106: =IF((AL91>=0),1,0) -> 1
A107: Cumulative cash >= 0 this month and every month after | B107: flag_cash_sus | C107: =IF(AND((C98>=0),(D107=1)),1,0) -> 0 | D107: =IF(AND((D98>=0),(E107=1)),1,0) -> 0 | E107: =IF(AND((E98>=0),(F107=1)),1,0) -> 0 | F107: =IF(AND((F98>=0),(G107=1)),1,0) -> 0 | G107: =IF(AND((G98>=0),(H107=1)),1,0) -> 0 | H107: =IF(AND((H98>=0),(I107=1)),1,0) -> 0 | I107: =IF(AND((I98>=0),(J107=1)),1,0) -> 0 | J107: =IF(AND((J98>=0),(K107=1)),1,0) -> 0 | ... AK107: =IF(AND((AK98>=0),(AL107=1)),1,0) -> 1 | AL107: =IF((AL98>=0),1,0) -> 1

Sheet Monthly_Bear
A1: Tenbagger: Bear case, monthly (USD). All cells are formulas driven by the Assumptions sheet.
A2: Month | C2: 1 | D2: 2 | E2: 3 | F2: 4 | G2: 5 | H2: 6 | I2: 7 | J2: 8 | K2: 9 | L2: 10 | M2: 11 | N2: 12 | O2: 13 | P2: 14 | Q2: 15 | R2: 16 | S2: 17 | T2: 18 | U2: 19 | V2: 20 | W2: 21 | X2: 22 | Y2: 23 | Z2: 24 | AA2: 25 | AB2: 26 | AC2: 27 | AD2: 28 | AE2: 29 | AF2: 30 | AG2: 31 | AH2: 32 | AI2: 33 | AJ2: 34 | AK2: 35 | AL2: 36
A3: Fiscal year | C3: 1 | D3: 1 | E3: 1 | F3: 1 | G3: 1 | H3: 1 | I3: 1 | J3: 1 | K3: 1 | L3: 1 | M3: 1 | N3: 1 | O3: 2 | P3: 2 | Q3: 2 | R3: 2 | S3: 2 | T3: 2 | U3: 2 | V3: 2 | W3: 2 | X3: 2 | Y3: 2 | Z3: 2 | AA3: 3 | AB3: 3 | AC3: 3 | AD3: 3 | AE3: 3 | AF3: 3 | AG3: 3 | AH3: 3 | AI3: 3 | AJ3: 3 | AK3: 3 | AL3: 3
A4: Calendar month | C4: Jan-27 | D4: Feb-27 | E4: Mar-27 | F4: Apr-27 | G4: May-27 | H4: Jun-27 | I4: Jul-27 | J4: Aug-27 | K4: Sep-27 | L4: Oct-27 | M4: Nov-27 | N4: Dec-27 | O4: Jan-28 | P4: Feb-28 | Q4: Mar-28 | R4: Apr-28 | S4: May-28 | T4: Jun-28 | U4: Jul-28 | V4: Aug-28 | W4: Sep-28 | X4: Oct-28 | Y4: Nov-28 | Z4: Dec-28 | AA4: Jan-29 | AB4: Feb-29 | AC4: Mar-29 | AD4: Apr-29 | AE4: May-29 | AF4: Jun-29 | AG4: Jul-29 | AH4: Aug-29 | AI4: Sep-29 | AJ4: Oct-29 | AK4: Nov-29 | AL4: Dec-29
A5: ACQUISITION
A6: Installs: organic / SEO / ASO | B6: inst_org | C6: =(Assumptions!$F$13*((1+Assumptions!$F$14)^(C$2-1))) -> 560 | D6: =(Assumptions!$F$13*((1+Assumptions!$F$14)^(D$2-1))) -> 582.4 | E6: =(Assumptions!$F$13*((1+Assumptions!$F$14)^(E$2-1))) -> 605.696 | F6: =(Assumptions!$F$13*((1+Assumptions!$F$14)^(F$2-1))) -> 629.92384 | G6: =(Assumptions!$F$13*((1+Assumptions!$F$14)^(G$2-1))) -> 655.12079 | H6: =(Assumptions!$F$13*((1+Assumptions!$F$14)^(H$2-1))) -> 681.32563 | I6: =(Assumptions!$F$13*((1+Assumptions!$F$14)^(I$2-1))) -> 708.57865 | J6: =(Assumptions!$F$13*((1+Assumptions!$F$14)^(J$2-1))) -> 736.9218 | ... AL6: =(Assumptions!$F$13*((1+Assumptions!$F$14)^(AL$2-1))) -> 2209.8098
A7: Installs: referral (x prior-month MAU) | B7: inst_ref | C7: =(Assumptions!$F$15*0) -> 0 | D7: =(Assumptions!$F$15*C36) -> 4.9244444 | E7: =(Assumptions!$F$15*D36) -> 5.5006251 | F7: =(Assumptions!$F$15*E36) -> 6.0259326 | G7: =(Assumptions!$F$15*F36) -> 6.7362293 | H7: =(Assumptions!$F$15*G36) -> 7.2577393 | I7: =(Assumptions!$F$15*H36) -> 7.7695165 | J7: =(Assumptions!$F$15*I36) -> 8.2761196 | K7: =(Assumptions!$F$15*J36) -> 8.780502 | ... AL7: =(Assumptions!$F$15*AK36) -> 27.037483
A8: Creator spend | B8: spend_creators | C8: =IF((C$2>=Assumptions!$F$16),(Assumptions!$F$17*((1+Assumptions!$F$18)^(C$2-Assumptions!$F$16))),0) -> 0 | D8: =IF((D$2>=Assumptions!$F$16),(Assumptions!$F$17*((1+Assumptions!$F$18)^(D$2-Assumptions!$F$16))),0) -> 0 | E8: =IF((E$2>=Assumptions!$F$16),(Assumptions!$F$17*((1+Assumptions!$F$18)^(E$2-Assumptions!$F$16))),0) -> 0 | F8: =IF((F$2>=Assumptions!$F$16),(Assumptions!$F$17*((1+Assumptions!$F$18)^(F$2-Assumptions!$F$16))),0) -> 300 | G8: =IF((G$2>=Assumptions!$F$16),(Assumptions!$F$17*((1+Assumptions!$F$18)^(G$2-Assumptions!$F$16))),0) -> 309 | H8: =IF((H$2>=Assumptions!$F$16),(Assumptions!$F$17*((1+Assumptions!$F$18)^(H$2-Assumptions!$F$16))),0) -> 318.27 | I8: =IF((I$2>=Assumptions!$F$16),(Assumptions!$F$17*((1+Assumptions!$F$18)^(I$2-Assumptions!$F$16))),0) -> 327.8181 | J8: =IF((J$2>=Assumptions!$F$16),(Assumptions!$F$17*((1+Assumptions!$F$18)^(J$2-Assumptions!$F$16))),0) -> 337.65264 | ... AL8: =IF((AL$2>=Assumptions!$F$16),(Assumptions!$F$17*((1+Assumptions!$F$18)^(AL$2-Assumptions!$F$16))),0) -> 772.52483
A9: Installs: creators | B9: inst_creators | C9: =IF(Assumptions!$F$19=0,0,C8/Assumptions!$F$19) -> 0 | D9: =IF(Assumptions!$F$19=0,0,D8/Assumptions!$F$19) -> 0 | E9: =IF(Assumptions!$F$19=0,0,E8/Assumptions!$F$19) -> 0 | F9: =IF(Assumptions!$F$19=0,0,F8/Assumptions!$F$19) -> 25 | G9: =IF(Assumptions!$F$19=0,0,G8/Assumptions!$F$19) -> 25.75 | H9: =IF(Assumptions!$F$19=0,0,H8/Assumptions!$F$19) -> 26.5225 | I9: =IF(Assumptions!$F$19=0,0,I8/Assumptions!$F$19) -> 27.318175 | J9: =IF(Assumptions!$F$19=0,0,J8/Assumptions!$F$19) -> 28.13772 | ... AL9: =IF(Assumptions!$F$19=0,0,AL8/Assumptions!$F$19) -> 64.377069
A10: Apple Search Ads spend | B10: spend_asa | C10: =IF((C$2>=Assumptions!$F$20),(Assumptions!$F$21*((1+Assumptions!$F$22)^(C$2-Assumptions!$F$20))),0) -> 500 | D10: =IF((D$2>=Assumptions!$F$20),(Assumptions!$F$21*((1+Assumptions!$F$22)^(D$2-Assumptions!$F$20))),0) -> 500 | E10: =IF((E$2>=Assumptions!$F$20),(Assumptions!$F$21*((1+Assumptions!$F$22)^(E$2-Assumptions!$F$20))),0) -> 500 | F10: =IF((F$2>=Assumptions!$F$20),(Assumptions!$F$21*((1+Assumptions!$F$22)^(F$2-Assumptions!$F$20))),0) -> 500 | G10: =IF((G$2>=Assumptions!$F$20),(Assumptions!$F$21*((1+Assumptions!$F$22)^(G$2-Assumptions!$F$20))),0) -> 500 | H10: =IF((H$2>=Assumptions!$F$20),(Assumptions!$F$21*((1+Assumptions!$F$22)^(H$2-Assumptions!$F$20))),0) -> 500 | I10: =IF((I$2>=Assumptions!$F$20),(Assumptions!$F$21*((1+Assumptions!$F$22)^(I$2-Assumptions!$F$20))),0) -> 500 | J10: =IF((J$2>=Assumptions!$F$20),(Assumptions!$F$21*((1+Assumptions!$F$22)^(J$2-Assumptions!$F$20))),0) -> 500 | ... AL10: =IF((AL$2>=Assumptions!$F$20),(Assumptions!$F$21*((1+Assumptions!$F$22)^(AL$2-Assumptions!$F$20))),0) -> 500
A11: Installs: paid Apple Search Ads | B11: inst_asa | C11: =IF(Assumptions!$F$23=0,0,C10/Assumptions!$F$23) -> 55.555556 | D11: =IF(Assumptions!$F$23=0,0,D10/Assumptions!$F$23) -> 55.555556 | E11: =IF(Assumptions!$F$23=0,0,E10/Assumptions!$F$23) -> 55.555556 | F11: =IF(Assumptions!$F$23=0,0,F10/Assumptions!$F$23) -> 55.555556 | G11: =IF(Assumptions!$F$23=0,0,G10/Assumptions!$F$23) -> 55.555556 | H11: =IF(Assumptions!$F$23=0,0,H10/Assumptions!$F$23) -> 55.555556 | I11: =IF(Assumptions!$F$23=0,0,I10/Assumptions!$F$23) -> 55.555556 | J11: =IF(Assumptions!$F$23=0,0,J10/Assumptions!$F$23) -> 55.555556 | ... AL11: =IF(Assumptions!$F$23=0,0,AL10/Assumptions!$F$23) -> 55.555556
A12: Total installs | B12: inst_total | C12: =(((C6+C7)+C9)+C11) -> 615.55556 | D12: =(((D6+D7)+D9)+D11) -> 642.88 | E12: =(((E6+E7)+E9)+E11) -> 666.75218 | F12: =(((F6+F7)+F9)+F11) -> 716.50533 | G12: =(((G6+G7)+G9)+G11) -> 743.16258 | H12: =(((H6+H7)+H9)+H11) -> 770.66142 | I12: =(((I6+I7)+I9)+I11) -> 799.2219 | J12: =(((J6+J7)+J9)+J11) -> 828.89119 | ... AL12: =(((AL6+AL7)+AL9)+AL11) -> 2356.7799
A14: FUNNEL (free -> trial -> paid)
A15: Activated users | B15: activated | C15: =(C12*Assumptions!$F$25) -> 338.55556 | D15: =(D12*Assumptions!$F$25) -> 353.584 | E15: =(E12*Assumptions!$F$25) -> 366.7137 | F15: =(F12*Assumptions!$F$25) -> 394.07793 | G15: =(G12*Assumptions!$F$25) -> 408.73942 | H15: =(H12*Assumptions!$F$25) -> 423.86378 | I15: =(I12*Assumptions!$F$25) -> 439.57204 | J15: =(J12*Assumptions!$F$25) -> 455.89016 | ... AL15: =(AL12*Assumptions!$F$25) -> 1296.229
A16: Trial / paywall starts | B16: trial_starts | C16: =(C15*Assumptions!$F$29) -> 27.084444 | D16: =(D15*Assumptions!$F$29) -> 28.28672 | E16: =(E15*Assumptions!$F$29) -> 29.337096 | F16: =(F15*Assumptions!$F$29) -> 31.526234 | G16: =(G15*Assumptions!$F$29) -> 32.699153 | H16: =(H15*Assumptions!$F$29) -> 33.909102 | I16: =(I15*Assumptions!$F$29) -> 35.165763 | J16: =(J15*Assumptions!$F$29) -> 36.471212 | ... AL16: =(AL15*Assumptions!$F$29) -> 103.69832
A17: New paid subscribers | B17: new_paid | C17: =(C16*Assumptions!$F$30) -> 8.9378667 | D17: =(D16*Assumptions!$F$30) -> 9.3346176 | E17: =(E16*Assumptions!$F$30) -> 9.6812417 | F17: =(F16*Assumptions!$F$30) -> 10.403657 | G17: =(G16*Assumptions!$F$30) -> 10.790721 | H17: =(H16*Assumptions!$F$30) -> 11.190004 | I17: =(I16*Assumptions!$F$30) -> 11.604702 | J17: =(J16*Assumptions!$F$30) -> 12.0355 | ... AL17: =(AL16*Assumptions!$F$30) -> 34.220445
A18: of which monthly plan | B18: new_monthly | C18: =(C17*Assumptions!$F$31) -> 3.5751467 | D18: =(D17*Assumptions!$F$31) -> 3.733847 | E18: =(E17*Assumptions!$F$31) -> 3.8724967 | F18: =(F17*Assumptions!$F$31) -> 4.1614629 | G18: =(G17*Assumptions!$F$31) -> 4.3162883 | H18: =(H17*Assumptions!$F$31) -> 4.4760015 | I18: =(I17*Assumptions!$F$31) -> 4.6418808 | J18: =(J17*Assumptions!$F$31) -> 4.8142 | ... AL18: =(AL17*Assumptions!$F$31) -> 13.688178
A19: of which annual plan | B19: new_annual | C19: =(C17*Assumptions!$F$32) -> 4.02204 | D19: =(D17*Assumptions!$F$32) -> 4.2005779 | E19: =(E17*Assumptions!$F$32) -> 4.3565587 | F19: =(F17*Assumptions!$F$32) -> 4.6816458 | G19: =(G17*Assumptions!$F$32) -> 4.8558243 | H19: =(H17*Assumptions!$F$32) -> 5.0355017 | I19: =(I17*Assumptions!$F$32) -> 5.2221159 | J19: =(J17*Assumptions!$F$32) -> 5.415975 | ... AL19: =(AL17*Assumptions!$F$32) -> 15.3992
A20: of which student plan | B20: new_student | C20: =(C17*Assumptions!$F$109) -> 1.34068 | D20: =(D17*Assumptions!$F$109) -> 1.4001926 | E20: =(E17*Assumptions!$F$109) -> 1.4521862 | F20: =(F17*Assumptions!$F$109) -> 1.5605486 | G20: =(G17*Assumptions!$F$109) -> 1.6186081 | H20: =(H17*Assumptions!$F$109) -> 1.6785006 | I20: =(I17*Assumptions!$F$109) -> 1.7407053 | J20: =(J17*Assumptions!$F$109) -> 1.805325 | ... AL20: =(AL17*Assumptions!$F$109) -> 5.1330667
A21: Recruiting Pass purchases (one-time) | B21: pass_sales | C21: =(C15*Assumptions!$F$33) -> 0.67711111 | D21: =(D15*Assumptions!$F$33) -> 0.707168 | E21: =(E15*Assumptions!$F$33) -> 0.7334274 | F21: =(F15*Assumptions!$F$33) -> 0.78815586 | G21: =(G15*Assumptions!$F$33) -> 0.81747884 | H21: =(H15*Assumptions!$F$33) -> 0.84772756 | I21: =(I15*Assumptions!$F$33) -> 0.87914409 | J21: =(J15*Assumptions!$F$33) -> 0.91178031 | ... AL21: =(AL15*Assumptions!$F$33) -> 2.5924579
A23: SUBSCRIBERS
A24: Monthly-plan subscribers (end of month) | B24: subs_monthly | C24: =((0*(1-Assumptions!$F$110))+C18) -> 3.5751467 | D24: =((C24*(1-Assumptions!$F$110))+D18) -> 6.6722014 | E24: =((D24*(1-Assumptions!$F$110))+E18) -> 9.3562694 | F24: =((E24*(1-Assumptions!$F$110))+F18) -> 11.851227 | G24: =((F24*(1-Assumptions!$F$110))+G18) -> 14.056617 | H24: =((G24*(1-Assumptions!$F$110))+H18) -> 16.028904 | I24: =((H24*(1-Assumptions!$F$110))+I18) -> 17.815774 | J24: =((I24*(1-Assumptions!$F$110))+J18) -> 19.456692 | K24: =((J24*(1-Assumptions!$F$110))+K18) -> 20.984369 | ... AL24: =((AK24*(1-Assumptions!$F$110))+AL18) -> 65.594024
A25: Annual plans billed (new + renewals) | B25: bill_annual | C25: =(C19+0) -> 4.02204 | D25: =(D19+0) -> 4.2005779 | E25: =(E19+0) -> 4.3565587 | F25: =(F19+0) -> 4.6816458 | G25: =(G19+0) -> 4.8558243 | H25: =(H19+0) -> 5.0355017 | I25: =(I19+0) -> 5.2221159 | J25: =(J19+0) -> 5.415975 | ... N25: =(N19+0) -> 6.2701889 | O25: =(O19+(Assumptions!$F$43*C25)) -> 7.7398769 | P25: =(P19+(Assumptions!$F$43*D25)) -> 8.0386693 | Q25: =(Q19+(Assumptions!$F$43*E25)) -> 8.3401619 | R25: =(R19+(Assumptions!$F$43*F25)) -> 8.7035891 | S25: =(S19+(Assumptions!$F$43*G25)) -> 9.0311044 | T25: =(T19+(Assumptions!$F$43*H25)) -> 9.3711537 | U25: =(U19+(Assumptions!$F$43*I25)) -> 9.7246156 | V25: =(V19+(Assumptions!$F$43*J25)) -> 10.092039 | ... AL25: =(AL19+(Assumptions!$F$43*Z25)) -> 18.995089
A26: Annual-plan subscribers (billed in last 12 months) | B26: subs_annual | C26: =SUM(C25:C25) -> 4.02204 | D26: =SUM(C25:D25) -> 8.2226179 | E26: =SUM(C25:E25) -> 12.579177 | F26: =SUM(C25:F25) -> 17.260822 | G26: =SUM(C25:G25) -> 22.116647 | H26: =SUM(C25:H25) -> 27.152148 | I26: =SUM(C25:I25) -> 32.374264 | J26: =SUM(C25:J25) -> 37.790239 | K26: =SUM(C25:K25) -> 43.407628 | L26: =SUM(C25:L25) -> 49.234301 | M26: =SUM(C25:M25) -> 55.278462 | N26: =SUM(C25:N25) -> 61.548651 | O26: =SUM(D25:O25) -> 65.266487 | P26: =SUM(E25:P25) -> 69.104579 | Q26: =SUM(F25:Q25) -> 73.088182 | R26: =SUM(G25:R25) -> 77.110125 | S26: =SUM(H25:S25) -> 81.285405 | T26: =SUM(I25:T25) -> 85.621057 | U26: =SUM(J25:U25) -> 90.123557 | ... AL26: =SUM(AA25:AL25) -> 186.75498
A27: Student plans billed (new + renewals) | B27: bill_student | C27: =(C20+0) -> 1.34068 | D27: =(D20+0) -> 1.4001926 | E27: =(E20+0) -> 1.4521862 | F27: =(F20+0) -> 1.5605486 | G27: =(G20+0) -> 1.6186081 | H27: =(H20+0) -> 1.6785006 | I27: =(I20+0) -> 1.7407053 | J27: =(J20+0) -> 1.805325 | ... N27: =(N20+0) -> 2.090063 | O27: =(O20+(Assumptions!$F$44*C27)) -> 2.5035402 | P27: =(P20+(Assumptions!$F$44*D27)) -> 2.5997455 | Q27: =(Q20+(Assumptions!$F$44*E27)) -> 2.6972793 | R27: =(R20+(Assumptions!$F$44*F27)) -> 2.8122451 | S27: =(S20+(Assumptions!$F$44*G27)) -> 2.9181075 | T27: =(T20+(Assumptions!$F$44*H27)) -> 3.0280434 | U27: =(U20+(Assumptions!$F$44*I27)) -> 3.1423183 | V27: =(V20+(Assumptions!$F$44*J27)) -> 3.2611094 | ... AL27: =(AL20+(Assumptions!$F$44*Z27)) -> 6.0793662
A28: Student-plan subscribers | B28: subs_student | C28: =SUM(C27:C27) -> 1.34068 | D28: =SUM(C27:D27) -> 2.7408726 | E28: =SUM(C27:E27) -> 4.1930589 | F28: =SUM(C27:F27) -> 5.7536075 | G28: =SUM(C27:G27) -> 7.3722156 | H28: =SUM(C27:H27) -> 9.0507162 | I28: =SUM(C27:I27) -> 10.791421 | J28: =SUM(C27:J27) -> 12.596746 | K28: =SUM(C27:K27) -> 14.469209 | L28: =SUM(C27:L27) -> 16.411434 | M28: =SUM(C27:M27) -> 18.426154 | N28: =SUM(C27:N27) -> 20.516217 | O28: =SUM(D27:O27) -> 21.679077 | P28: =SUM(E27:P27) -> 22.87863 | Q28: =SUM(F27:Q27) -> 24.123723 | R28: =SUM(G27:R27) -> 25.375419 | S28: =SUM(H27:S27) -> 26.674919 | T28: =SUM(I27:T27) -> 28.024462 | U28: =SUM(J27:U27) -> 29.426075 | ... AL28: =SUM(AA27:AL27) -> 59.767025
A29: Paid subscribers (end of month) | B29: subs_paid | C29: =((C24+C26)+C28) -> 8.9378667 | D29: =((D24+D26)+D28) -> 17.635692 | E29: =((E24+E26)+E28) -> 26.128505 | F29: =((F24+F26)+F28) -> 34.865657 | G29: =((G24+G26)+G28) -> 43.545479 | H29: =((H24+H26)+H28) -> 52.231769 | I29: =((I24+I26)+I28) -> 60.98146 | J29: =((J24+J26)+J28) -> 69.843678 | ... AL29: =((AL24+AL26)+AL28) -> 312.11603
A30: Gross in-app billings, cash basis (= RevenueCat MTR) | B30: bill_gross | C30: =((((C24*Assumptions!$F$35)+(C25*Assumptions!$F$36))+(C27*Assumptions!$F$37))+(C21*Assumptions!$F$38)) -> 363.79013 | D30: =((((D24*Assumptions!$F$35)+(D25*Assumptions!$F$36))+(D27*Assumptions!$F$37))+(D21*Assumptions!$F$38)) -> 409.2929 | E30: =((((E24*Assumptions!$F$35)+(E25*Assumptions!$F$36))+(E27*Assumptions!$F$37))+(E21*Assumptions!$F$38)) -> 448.82996 | F30: =((((F24*Assumptions!$F$35)+(F25*Assumptions!$F$36))+(F27*Assumptions!$F$37))+(F21*Assumptions!$F$38)) -> 500.27167 | G30: =((((G24*Assumptions!$F$35)+(G25*Assumptions!$F$36))+(G27*Assumptions!$F$37))+(G21*Assumptions!$F$38)) -> 536.5111 | H30: =((((H24*Assumptions!$F$35)+(H25*Assumptions!$F$36))+(H27*Assumptions!$F$37))+(H21*Assumptions!$F$38)) -> 570.87039 | I30: =((((I24*Assumptions!$F$35)+(I25*Assumptions!$F$36))+(I27*Assumptions!$F$37))+(I21*Assumptions!$F$38)) -> 603.94318 | J30: =((((J24*Assumptions!$F$35)+(J25*Assumptions!$F$36))+(J27*Assumptions!$F$37))+(J21*Assumptions!$F$38)) -> 636.14888 | ... AL30: =((((AL24*Assumptions!$F$35)+(AL25*Assumptions!$F$36))+(AL27*Assumptions!$F$37))+(AL21*Assumptions!$F$38)) -> 2164.944
A32: ACTIVE USERS
A33: New free users this month | B33: free_new | C33: =(C12-C17) -> 606.61769 | D33: =(D12-D17) -> 633.54538 | E33: =(E12-E17) -> 657.07094 | F33: =(F12-F17) -> 706.10167 | G33: =(G12-G17) -> 732.37186 | H33: =(H12-H17) -> 759.47142 | I33: =(I12-I17) -> 787.6172 | J33: =(J12-J17) -> 816.85569 | ... AL33: =(AL12-AL17) -> 2322.5595
A34: Retained free users from earlier months | B34: free_pool | C34: =((0*(1-Assumptions!$F$27))+(0*Assumptions!$F$26)) -> 0 | D34: =((C34*(1-Assumptions!$F$27))+(C33*Assumptions!$F$26)) -> 36.397061 | E34: =((D34*(1-Assumptions!$F$27))+(D33*Assumptions!$F$26)) -> 70.042137 | F34: =((E34*(1-Assumptions!$F$27))+(E33*Assumptions!$F$26)) -> 101.06134 | G34: =((F34*(1-Assumptions!$F$27))+(F33*Assumptions!$F$26)) -> 131.30008 | H34: =((G34*(1-Assumptions!$F$27))+(G33*Assumptions!$F$26)) -> 159.48638 | I34: =((H34*(1-Assumptions!$F$27))+(H33*Assumptions!$F$26)) -> 185.9163 | J34: =((I34*(1-Assumptions!$F$27))+(I33*Assumptions!$F$26)) -> 210.86337 | K34: =((J34*(1-Assumptions!$F$27))+(J33*Assumptions!$F$26)) -> 234.57111 | ... AL34: =((AK34*(1-Assumptions!$F$27))+(AK33*Assumptions!$F$26)) -> 876.55155
A35: Free MAU | B35: mau_free | C35: =(C33+C34) -> 606.61769 | D35: =(D33+D34) -> 669.94244 | E35: =(E33+E34) -> 727.11308 | F35: =(F33+F34) -> 807.16301 | G35: =(G33+G34) -> 863.67193 | H35: =(H33+H34) -> 918.9578 | I35: =(I33+I34) -> 973.53349 | J35: =(J33+J34) -> 1027.7191 | ... AL35: =(AL33+AL34) -> 3199.111
A36: Total MAU (free + paid) | B36: mau_total | C36: =(C35+C29) -> 615.55556 | D36: =(D35+D29) -> 687.57814 | E36: =(E35+E29) -> 753.24158 | F36: =(F35+F29) -> 842.02866 | G36: =(G35+G29) -> 907.21741 | H36: =(H35+H29) -> 971.18956 | I36: =(I35+I29) -> 1034.515 | J36: =(J35+J29) -> 1097.5627 | ... AL36: =(AL35+AL29) -> 3511.2271
A37: Paid subscribers / MAU | B37: paid_share | C37: =IF(C36=0,0,C29/C36) -> 0.01452 | D37: =IF(D36=0,0,D29/D36) -> 0.025649 | E37: =IF(E36=0,0,E29/E36) -> 0.034688081 | F37: =IF(F36=0,0,F29/F36) -> 0.041406734 | G37: =IF(G36=0,0,G29/G36) -> 0.047998946 | H37: =IF(H36=0,0,H29/H36) -> 0.05378123 | I37: =IF(I36=0,0,I29/I36) -> 0.05894691 | J37: =IF(J36=0,0,J29/J36) -> 0.063635248 | ... AL37: =IF(AL36=0,0,AL29/AL36) -> 0.08889087
A39: ADS, AFFILIATE, B2B AND LINKING VOLUMES
A40: Free MAU seeing ads | B40: ad_mau | C40: =IF(AND((Assumptions!$F$5=1),(C$2>=Assumptions!$F$46)),(C35*Assumptions!$F$47),0) -> 0 | D40: =IF(AND((Assumptions!$F$5=1),(D$2>=Assumptions!$F$46)),(D35*Assumptions!$F$47),0) -> 0 | E40: =IF(AND((Assumptions!$F$5=1),(E$2>=Assumptions!$F$46)),(E35*Assumptions!$F$47),0) -> 0 | F40: =IF(AND((Assumptions!$F$5=1),(F$2>=Assumptions!$F$46)),(F35*Assumptions!$F$47),0) -> 484.2978 | G40: =IF(AND((Assumptions!$F$5=1),(G$2>=Assumptions!$F$46)),(G35*Assumptions!$F$47),0) -> 518.20316 | H40: =IF(AND((Assumptions!$F$5=1),(H$2>=Assumptions!$F$46)),(H35*Assumptions!$F$47),0) -> 551.37468 | I40: =IF(AND((Assumptions!$F$5=1),(I$2>=Assumptions!$F$46)),(I35*Assumptions!$F$47),0) -> 584.1201 | J40: =IF(AND((Assumptions!$F$5=1),(J$2>=Assumptions!$F$46)),(J35*Assumptions!$F$47),0) -> 616.63144 | ... AL40: =IF(AND((Assumptions!$F$5=1),(AL$2>=Assumptions!$F$46)),(AL35*Assumptions!$F$47),0) -> 1919.4666
A41: Ad impressions: article / lesson end | B41: imps_article | C41: =(C40*Assumptions!$F$48) -> 0 | D41: =(D40*Assumptions!$F$48) -> 0 | E41: =(E40*Assumptions!$F$48) -> 0 | F41: =(F40*Assumptions!$F$48) -> 2421.489 | G41: =(G40*Assumptions!$F$48) -> 2591.0158 | H41: =(H40*Assumptions!$F$48) -> 2756.8734 | I41: =(I40*Assumptions!$F$48) -> 2920.6005 | J41: =(J40*Assumptions!$F$48) -> 3083.1572 | ... AL41: =(AL40*Assumptions!$F$48) -> 9597.3331
A42: Ad impressions: screener native | B42: imps_screener | C42: =(C40*Assumptions!$F$49) -> 0 | D42: =(D40*Assumptions!$F$49) -> 0 | E42: =(E40*Assumptions!$F$49) -> 0 | F42: =(F40*Assumptions!$F$49) -> 968.59561 | G42: =(G40*Assumptions!$F$49) -> 1036.4063 | H42: =(H40*Assumptions!$F$49) -> 1102.7494 | I42: =(I40*Assumptions!$F$49) -> 1168.2402 | J42: =(J40*Assumptions!$F$49) -> 1233.2629 | ... AL42: =(AL40*Assumptions!$F$49) -> 3838.9333
A43: Ad impressions: opt-in rewarded | B43: imps_rewarded | C43: =(C40*Assumptions!$F$50) -> 0 | D43: =(D40*Assumptions!$F$50) -> 0 | E43: =(E40*Assumptions!$F$50) -> 0 | F43: =(F40*Assumptions!$F$50) -> 242.1489 | G43: =(G40*Assumptions!$F$50) -> 259.10158 | H43: =(H40*Assumptions!$F$50) -> 275.68734 | I43: =(I40*Assumptions!$F$50) -> 292.06005 | J43: =(J40*Assumptions!$F$50) -> 308.31572 | ... AL43: =(AL40*Assumptions!$F$50) -> 959.73331
A44: Affiliate clicks | B44: aff_clicks | C44: =IF(AND((Assumptions!$F$6=1),(C$2>=Assumptions!$F$56)),((C36/1000)*Assumptions!$F$57),0) -> 0 | D44: =IF(AND((Assumptions!$F$6=1),(D$2>=Assumptions!$F$56)),((D36/1000)*Assumptions!$F$57),0) -> 0 | E44: =IF(AND((Assumptions!$F$6=1),(E$2>=Assumptions!$F$56)),((E36/1000)*Assumptions!$F$57),0) -> 0 | F44: =IF(AND((Assumptions!$F$6=1),(F$2>=Assumptions!$F$56)),((F36/1000)*Assumptions!$F$57),0) -> 0 | G44: =IF(AND((Assumptions!$F$6=1),(G$2>=Assumptions!$F$56)),((G36/1000)*Assumptions!$F$57),0) -> 0 | H44: =IF(AND((Assumptions!$F$6=1),(H$2>=Assumptions!$F$56)),((H36/1000)*Assumptions!$F$57),0) -> 0 | I44: =IF(AND((Assumptions!$F$6=1),(I$2>=Assumptions!$F$56)),((I36/1000)*Assumptions!$F$57),0) -> 3.1035449 | J44: =IF(AND((Assumptions!$F$6=1),(J$2>=Assumptions!$F$56)),((J36/1000)*Assumptions!$F$57),0) -> 3.2926882 | ... AL44: =IF(AND((Assumptions!$F$6=1),(AL$2>=Assumptions!$F$56)),((AL36/1000)*Assumptions!$F$57),0) -> 10.533681
A45: Affiliate funded accounts | B45: aff_funded | C45: =(C44*Assumptions!$F$58) -> 0 | D45: =(D44*Assumptions!$F$58) -> 0 | E45: =(E44*Assumptions!$F$58) -> 0 | F45: =(F44*Assumptions!$F$58) -> 0 | G45: =(G44*Assumptions!$F$58) -> 0 | H45: =(H44*Assumptions!$F$58) -> 0 | I45: =(I44*Assumptions!$F$58) -> 0.062070897 | J45: =(J44*Assumptions!$F$58) -> 0.065853765 | ... AL45: =(AL44*Assumptions!$F$58) -> 0.21067362
A46: Classroom Pro teachers | B46: teachers | C46: =IF(AND((Assumptions!$F$7=1),(C$2>=Assumptions!$F$61)),(Assumptions!$F$62+(Assumptions!$F$63*(C$2-Assumptions!$F$61))),0) -> 0 | D46: =IF(AND((Assumptions!$F$7=1),(D$2>=Assumptions!$F$61)),(Assumptions!$F$62+(Assumptions!$F$63*(D$2-Assumptions!$F$61))),0) -> 0 | E46: =IF(AND((Assumptions!$F$7=1),(E$2>=Assumptions!$F$61)),(Assumptions!$F$62+(Assumptions!$F$63*(E$2-Assumptions!$F$61))),0) -> 0 | F46: =IF(AND((Assumptions!$F$7=1),(F$2>=Assumptions!$F$61)),(Assumptions!$F$62+(Assumptions!$F$63*(F$2-Assumptions!$F$61))),0) -> 0 | G46: =IF(AND((Assumptions!$F$7=1),(G$2>=Assumptions!$F$61)),(Assumptions!$F$62+(Assumptions!$F$63*(G$2-Assumptions!$F$61))),0) -> 0 | H46: =IF(AND((Assumptions!$F$7=1),(H$2>=Assumptions!$F$61)),(Assumptions!$F$62+(Assumptions!$F$63*(H$2-Assumptions!$F$61))),0) -> 0 | I46: =IF(AND((Assumptions!$F$7=1),(I$2>=Assumptions!$F$61)),(Assumptions!$F$62+(Assumptions!$F$63*(I$2-Assumptions!$F$61))),0) -> 0 | J46: =IF(AND((Assumptions!$F$7=1),(J$2>=Assumptions!$F$61)),(Assumptions!$F$62+(Assumptions!$F$63*(J$2-Assumptions!$F$61))),0) -> 0 | ... AL46: =IF(AND((Assumptions!$F$7=1),(AL$2>=Assumptions!$F$61)),(Assumptions!$F$62+(Assumptions!$F$63*(AL$2-Assumptions!$F$61))),0) -> 0
A47: Campus / club licences | B47: campus | C47: =IF(AND((Assumptions!$F$7=1),(C$2>=Assumptions!$F$61)),(Assumptions!$F$65+(Assumptions!$F$66*(C$2-Assumptions!$F$61))),0) -> 0 | D47: =IF(AND((Assumptions!$F$7=1),(D$2>=Assumptions!$F$61)),(Assumptions!$F$65+(Assumptions!$F$66*(D$2-Assumptions!$F$61))),0) -> 0 | E47: =IF(AND((Assumptions!$F$7=1),(E$2>=Assumptions!$F$61)),(Assumptions!$F$65+(Assumptions!$F$66*(E$2-Assumptions!$F$61))),0) -> 0 | F47: =IF(AND((Assumptions!$F$7=1),(F$2>=Assumptions!$F$61)),(Assumptions!$F$65+(Assumptions!$F$66*(F$2-Assumptions!$F$61))),0) -> 0 | G47: =IF(AND((Assumptions!$F$7=1),(G$2>=Assumptions!$F$61)),(Assumptions!$F$65+(Assumptions!$F$66*(G$2-Assumptions!$F$61))),0) -> 0 | H47: =IF(AND((Assumptions!$F$7=1),(H$2>=Assumptions!$F$61)),(Assumptions!$F$65+(Assumptions!$F$66*(H$2-Assumptions!$F$61))),0) -> 0 | I47: =IF(AND((Assumptions!$F$7=1),(I$2>=Assumptions!$F$61)),(Assumptions!$F$65+(Assumptions!$F$66*(I$2-Assumptions!$F$61))),0) -> 0 | J47: =IF(AND((Assumptions!$F$7=1),(J$2>=Assumptions!$F$61)),(Assumptions!$F$65+(Assumptions!$F$66*(J$2-Assumptions!$F$61))),0) -> 0 | ... AL47: =IF(AND((Assumptions!$F$7=1),(AL$2>=Assumptions!$F$61)),(Assumptions!$F$65+(Assumptions!$F$66*(AL$2-Assumptions!$F$61))),0) -> 0
A48: Linking live (1 = yes) | B48: link_on | C48: =IF(AND((Assumptions!$F$9=1),(C$2>=Assumptions!$F$73)),1,0) -> 0 | D48: =IF(AND((Assumptions!$F$9=1),(D$2>=Assumptions!$F$73)),1,0) -> 0 | E48: =IF(AND((Assumptions!$F$9=1),(E$2>=Assumptions!$F$73)),1,0) -> 0 | F48: =IF(AND((Assumptions!$F$9=1),(F$2>=Assumptions!$F$73)),1,0) -> 0 | G48: =IF(AND((Assumptions!$F$9=1),(G$2>=Assumptions!$F$73)),1,0) -> 0 | H48: =IF(AND((Assumptions!$F$9=1),(H$2>=Assumptions!$F$73)),1,0) -> 0 | I48: =IF(AND((Assumptions!$F$9=1),(I$2>=Assumptions!$F$73)),1,0) -> 0 | J48: =IF(AND((Assumptions!$F$9=1),(J$2>=Assumptions!$F$73)),1,0) -> 0 | ... AL48: =IF(AND((Assumptions!$F$9=1),(AL$2>=Assumptions!$F$73)),1,0) -> 1
A49: Linked Items: free users (capped at 1 bank) | B49: items_free | C49: =((C48*C35)*Assumptions!$F$74) -> 0 | D49: =((D48*D35)*Assumptions!$F$74) -> 0 | E49: =((E48*E35)*Assumptions!$F$74) -> 0 | F49: =((F48*F35)*Assumptions!$F$74) -> 0 | G49: =((G48*G35)*Assumptions!$F$74) -> 0 | H49: =((H48*H35)*Assumptions!$F$74) -> 0 | I49: =((I48*I35)*Assumptions!$F$74) -> 0 | J49: =((J48*J35)*Assumptions!$F$74) -> 0 | ... AL49: =((AL48*AL35)*Assumptions!$F$74) -> 383.89333
A50: Linked Items: Pro users | B50: items_pro | C50: =(((C48*C29)*Assumptions!$F$76)*Assumptions!$F$77) -> 0 | D50: =(((D48*D29)*Assumptions!$F$76)*Assumptions!$F$77) -> 0 | E50: =(((E48*E29)*Assumptions!$F$76)*Assumptions!$F$77) -> 0 | F50: =(((F48*F29)*Assumptions!$F$76)*Assumptions!$F$77) -> 0 | G50: =(((G48*G29)*Assumptions!$F$76)*Assumptions!$F$77) -> 0 | H50: =(((H48*H29)*Assumptions!$F$76)*Assumptions!$F$77) -> 0 | I50: =(((I48*I29)*Assumptions!$F$76)*Assumptions!$F$77) -> 0 | J50: =(((J48*J29)*Assumptions!$F$76)*Assumptions!$F$77) -> 0 | ... AL50: =(((AL48*AL29)*Assumptions!$F$76)*Assumptions!$F$77) -> 273.10153
A52: REVENUE
A53: Gross: monthly plans | B53: rev_monthly | C53: =(C24*Assumptions!$F$35) -> 35.715715 | D53: =(D24*Assumptions!$F$35) -> 66.655292 | E53: =(E24*Assumptions!$F$35) -> 93.469131 | F53: =(F24*Assumptions!$F$35) -> 118.39376 | G53: =(G24*Assumptions!$F$35) -> 140.4256 | H53: =(H24*Assumptions!$F$35) -> 160.12875 | I53: =(I24*Assumptions!$F$35) -> 177.97958 | J53: =(J24*Assumptions!$F$35) -> 194.37235 | ... AL53: =(AL24*Assumptions!$F$35) -> 655.2843
A54: Gross: annual plans (recognised 1/12 a month) | B54: rev_annual | C54: =((C26*Assumptions!$F$36)/12) -> 20.106848 | D54: =((D26*Assumptions!$F$36)/12) -> 41.106237 | E54: =((E26*Assumptions!$F$36)/12) -> 62.885401 | F54: =((F26*Assumptions!$F$36)/12) -> 86.289728 | G54: =((G26*Assumptions!$F$36)/12) -> 110.5648 | H54: =((H26*Assumptions!$F$36)/12) -> 135.73812 | I54: =((I26*Assumptions!$F$36)/12) -> 161.84434 | J54: =((J26*Assumptions!$F$36)/12) -> 188.91971 | ... AL54: =((AL26*Assumptions!$F$36)/12) -> 933.61927
A55: Gross: student plans (recognised 1/12 a month) | B55: rev_student | C55: =((C28*Assumptions!$F$37)/12) -> 4.4678161 | D55: =((D28*Assumptions!$F$37)/12) -> 9.1339581 | E55: =((E28*Assumptions!$F$37)/12) -> 13.973369 | F55: =((F28*Assumptions!$F$37)/12) -> 19.173897 | G55: =((G28*Assumptions!$F$37)/12) -> 24.567908 | H55: =((H28*Assumptions!$F$37)/12) -> 30.161512 | I55: =((I28*Assumptions!$F$37)/12) -> 35.962412 | J55: =((J28*Assumptions!$F$37)/12) -> 41.978658 | ... AL55: =((AL28*Assumptions!$F$37)/12) -> 199.17361
A56: Gross: Recruiting Pass | B56: rev_pass | C56: =(C21*Assumptions!$F$38) -> 33.178444 | D56: =(D21*Assumptions!$F$38) -> 34.651232 | E56: =(E21*Assumptions!$F$38) -> 35.937943 | F56: =(F21*Assumptions!$F$38) -> 38.619637 | G56: =(G21*Assumptions!$F$38) -> 40.056463 | H56: =(H21*Assumptions!$F$38) -> 41.538651 | I56: =(I21*Assumptions!$F$38) -> 43.07806 | J56: =(J21*Assumptions!$F$38) -> 44.677235 | ... AL56: =(AL21*Assumptions!$F$38) -> 127.03044
A57: Gross in-app sales | B57: rev_iap_gross | C57: =(((C53+C54)+C55)+C56) -> 93.468824 | D57: =(((D53+D54)+D55)+D56) -> 151.54672 | E57: =(((E53+E54)+E55)+E56) -> 206.26584 | F57: =(((F53+F54)+F55)+F56) -> 262.47702 | G57: =(((G53+G54)+G55)+G56) -> 315.61478 | H57: =(((H53+H54)+H55)+H56) -> 367.56703 | I57: =(((I53+I54)+I55)+I56) -> 418.8644 | J57: =(((J53+J54)+J55)+J56) -> 469.94795 | ... AL57: =(((AL53+AL54)+AL55)+AL56) -> 1915.1076
A58: Less: refunds | B58: refunds | C58: =((-C57)*Assumptions!$F$40) -> -2.8040647 | D58: =((-D57)*Assumptions!$F$40) -> -4.5464016 | E58: =((-E57)*Assumptions!$F$40) -> -6.1879753 | F58: =((-F57)*Assumptions!$F$40) -> -7.8743106 | G58: =((-G57)*Assumptions!$F$40) -> -9.4684434 | H58: =((-H57)*Assumptions!$F$40) -> -11.027011 | I58: =((-I57)*Assumptions!$F$40) -> -12.565932 | J58: =((-J57)*Assumptions!$F$40) -> -14.098439 | ... AL58: =((-AL57)*Assumptions!$F$40) -> -57.453228
A59: Less: app store commission | B59: store_fee | C59: =((-(C57+C58))*Assumptions!$F$39) -> -13.599714 | D59: =((-(D57+D58))*Assumptions!$F$39) -> -22.050048 | E59: =((-(E57+E58))*Assumptions!$F$39) -> -30.01168 | F59: =((-(F57+F58))*Assumptions!$F$39) -> -38.190407 | G59: =((-(G57+G58))*Assumptions!$F$39) -> -45.92195 | H59: =((-(H57+H58))*Assumptions!$F$39) -> -53.481003 | I59: =((-(I57+I58))*Assumptions!$F$39) -> -60.94477 | J59: =((-(J57+J58))*Assumptions!$F$39) -> -68.377427 | ... AL59: =((-(AL57+AL58))*Assumptions!$F$39) -> -278.64816
A60: Subscriptions & in-app, net of store fee | B60: rev_subs_net | C60: =((C57+C58)+C59) -> 77.065045 | D60: =((D57+D58)+D59) -> 124.95027 | E60: =((E57+E58)+E59) -> 170.06619 | F60: =((F57+F58)+F59) -> 216.4123 | G60: =((G57+G58)+G59) -> 260.22439 | H60: =((H57+H58)+H59) -> 303.05902 | I60: =((I57+I58)+I59) -> 345.35369 | J60: =((J57+J58)+J59) -> 387.47208 | ... AL60: =((AL57+AL58)+AL59) -> 1579.0062
A61: Ads: article / lesson end | B61: rev_ads_article | C61: =(((C41/1000)*Assumptions!$F$51)*Assumptions!$F$54) -> 0 | D61: =(((D41/1000)*Assumptions!$F$51)*Assumptions!$F$54) -> 0 | E61: =(((E41/1000)*Assumptions!$F$51)*Assumptions!$F$54) -> 0 | F61: =(((F41/1000)*Assumptions!$F$51)*Assumptions!$F$54) -> 2.5425635 | G61: =(((G41/1000)*Assumptions!$F$51)*Assumptions!$F$54) -> 2.7205666 | H61: =(((H41/1000)*Assumptions!$F$51)*Assumptions!$F$54) -> 2.8947171 | I61: =(((I41/1000)*Assumptions!$F$51)*Assumptions!$F$54) -> 3.0666305 | J61: =(((J41/1000)*Assumptions!$F$51)*Assumptions!$F$54) -> 3.2373151 | ... AL61: =(((AL41/1000)*Assumptions!$F$51)*Assumptions!$F$54) -> 10.0772
A62: Ads: screener native | B62: rev_ads_screener | C62: =(((C42/1000)*Assumptions!$F$52)*Assumptions!$F$54) -> 0 | D62: =(((D42/1000)*Assumptions!$F$52)*Assumptions!$F$54) -> 0 | E62: =(((E42/1000)*Assumptions!$F$52)*Assumptions!$F$54) -> 0 | F62: =(((F42/1000)*Assumptions!$F$52)*Assumptions!$F$54) -> 1.3560339 | G62: =(((G42/1000)*Assumptions!$F$52)*Assumptions!$F$54) -> 1.4509688 | H62: =(((H42/1000)*Assumptions!$F$52)*Assumptions!$F$54) -> 1.5438491 | I62: =(((I42/1000)*Assumptions!$F$52)*Assumptions!$F$54) -> 1.6355363 | J62: =(((J42/1000)*Assumptions!$F$52)*Assumptions!$F$54) -> 1.726568 | ... AL62: =(((AL42/1000)*Assumptions!$F$52)*Assumptions!$F$54) -> 5.3745066
A63: Ads: opt-in rewarded | B63: rev_ads_rewarded | C63: =(((C43/1000)*Assumptions!$F$53)*Assumptions!$F$54) -> 0 | D63: =(((D43/1000)*Assumptions!$F$53)*Assumptions!$F$54) -> 0 | E63: =(((E43/1000)*Assumptions!$F$53)*Assumptions!$F$54) -> 0 | F63: =(((F43/1000)*Assumptions!$F$53)*Assumptions!$F$54) -> 1.3560339 | G63: =(((G43/1000)*Assumptions!$F$53)*Assumptions!$F$54) -> 1.4509688 | H63: =(((H43/1000)*Assumptions!$F$53)*Assumptions!$F$54) -> 1.5438491 | I63: =(((I43/1000)*Assumptions!$F$53)*Assumptions!$F$54) -> 1.6355363 | J63: =(((J43/1000)*Assumptions!$F$53)*Assumptions!$F$54) -> 1.726568 | ... AL63: =(((AL43/1000)*Assumptions!$F$53)*Assumptions!$F$54) -> 5.3745066
A64: Advertising revenue | B64: rev_ads | C64: =((C61+C62)+C63) -> 0 | D64: =((D61+D62)+D63) -> 0 | E64: =((E61+E62)+E63) -> 0 | F64: =((F61+F62)+F63) -> 5.2546312 | G64: =((G61+G62)+G63) -> 5.6225043 | H64: =((H61+H62)+H63) -> 5.9824152 | I64: =((I61+I62)+I63) -> 6.337703 | J64: =((J61+J62)+J63) -> 6.6904511 | ... AL64: =((AL61+AL62)+AL63) -> 20.826213
A65: Affiliate revenue | B65: rev_aff | C65: =(C45*Assumptions!$F$59) -> 0 | D65: =(D45*Assumptions!$F$59) -> 0 | E65: =(E45*Assumptions!$F$59) -> 0 | F65: =(F45*Assumptions!$F$59) -> 0 | G65: =(G45*Assumptions!$F$59) -> 0 | H65: =(H45*Assumptions!$F$59) -> 0 | I65: =(I45*Assumptions!$F$59) -> 1.8621269 | J65: =(J45*Assumptions!$F$59) -> 1.9756129 | ... AL65: =(AL45*Assumptions!$F$59) -> 6.3202087
A66: B2B / Edu licence revenue | B66: rev_b2b | C66: =(((C46*Assumptions!$F$64)/12)+((C47*Assumptions!$F$67)/12)) -> 0 | D66: =(((D46*Assumptions!$F$64)/12)+((D47*Assumptions!$F$67)/12)) -> 0 | E66: =(((E46*Assumptions!$F$64)/12)+((E47*Assumptions!$F$67)/12)) -> 0 | F66: =(((F46*Assumptions!$F$64)/12)+((F47*Assumptions!$F$67)/12)) -> 0 | G66: =(((G46*Assumptions!$F$64)/12)+((G47*Assumptions!$F$67)/12)) -> 0 | H66: =(((H46*Assumptions!$F$64)/12)+((H47*Assumptions!$F$67)/12)) -> 0 | I66: =(((I46*Assumptions!$F$64)/12)+((I47*Assumptions!$F$67)/12)) -> 0 | J66: =(((J46*Assumptions!$F$64)/12)+((J47*Assumptions!$F$67)/12)) -> 0 | ... AL66: =(((AL46*Assumptions!$F$64)/12)+((AL47*Assumptions!$F$67)/12)) -> 0
A67: TOTAL REVENUE | B67: rev_total | C67: =(((C60+C64)+C65)+C66) -> 77.065045 | D67: =(((D60+D64)+D65)+D66) -> 124.95027 | E67: =(((E60+E64)+E65)+E66) -> 170.06619 | F67: =(((F60+F64)+F65)+F66) -> 221.66693 | G67: =(((G60+G64)+G65)+G66) -> 265.84689 | H67: =(((H60+H64)+H65)+H66) -> 309.04143 | I67: =(((I60+I64)+I65)+I66) -> 353.55352 | J67: =(((J60+J64)+J65)+J66) -> 396.13815 | ... AL67: =(((AL60+AL64)+AL65)+AL66) -> 1606.1527
A69: COST OF REVENUE (COGS)
A70: Data licensing (beta, or scale phase above MAU threshold) | B70: cogs_data | C70: =IF((C36>=Assumptions!$F$72),Assumptions!$F$71,Assumptions!$F$70) -> 450 | D70: =IF((D36>=Assumptions!$F$72),Assumptions!$F$71,Assumptions!$F$70) -> 450 | E70: =IF((E36>=Assumptions!$F$72),Assumptions!$F$71,Assumptions!$F$70) -> 450 | F70: =IF((F36>=Assumptions!$F$72),Assumptions!$F$71,Assumptions!$F$70) -> 450 | G70: =IF((G36>=Assumptions!$F$72),Assumptions!$F$71,Assumptions!$F$70) -> 450 | H70: =IF((H36>=Assumptions!$F$72),Assumptions!$F$71,Assumptions!$F$70) -> 450 | I70: =IF((I36>=Assumptions!$F$72),Assumptions!$F$71,Assumptions!$F$70) -> 450 | J70: =IF((J36>=Assumptions!$F$72),Assumptions!$F$71,Assumptions!$F$70) -> 450 | ... AL70: =IF((AL36>=Assumptions!$F$72),Assumptions!$F$71,Assumptions!$F$70) -> 450
A71: Plaid / aggregation | B71: cogs_plaid | C71: =(((C49*Assumptions!$F$75)+(C50*Assumptions!$F$78))+(C48*Assumptions!$F$79)) -> 0 | D71: =(((D49*Assumptions!$F$75)+(D50*Assumptions!$F$78))+(D48*Assumptions!$F$79)) -> 0 | E71: =(((E49*Assumptions!$F$75)+(E50*Assumptions!$F$78))+(E48*Assumptions!$F$79)) -> 0 | F71: =(((F49*Assumptions!$F$75)+(F50*Assumptions!$F$78))+(F48*Assumptions!$F$79)) -> 0 | G71: =(((G49*Assumptions!$F$75)+(G50*Assumptions!$F$78))+(G48*Assumptions!$F$79)) -> 0 | H71: =(((H49*Assumptions!$F$75)+(H50*Assumptions!$F$78))+(H48*Assumptions!$F$79)) -> 0 | I71: =(((I49*Assumptions!$F$75)+(I50*Assumptions!$F$78))+(I48*Assumptions!$F$79)) -> 0 | J71: =(((J49*Assumptions!$F$75)+(J50*Assumptions!$F$78))+(J48*Assumptions!$F$79)) -> 0 | ... AL71: =(((AL49*Assumptions!$F$75)+(AL50*Assumptions!$F$78))+(AL48*Assumptions!$F$79)) -> 576.12737
A72: Hosting / Supabase / Expo | B72: cogs_hosting | C72: =(Assumptions!$F$80+(Assumptions!$F$81*C36)) -> 56.155556 | D72: =(Assumptions!$F$80+(Assumptions!$F$81*D36)) -> 56.875781 | E72: =(Assumptions!$F$80+(Assumptions!$F$81*E36)) -> 57.532416 | F72: =(Assumptions!$F$80+(Assumptions!$F$81*F36)) -> 58.420287 | G72: =(Assumptions!$F$80+(Assumptions!$F$81*G36)) -> 59.072174 | H72: =(Assumptions!$F$80+(Assumptions!$F$81*H36)) -> 59.711896 | I72: =(Assumptions!$F$80+(Assumptions!$F$81*I36)) -> 60.34515 | J72: =(Assumptions!$F$80+(Assumptions!$F$81*J36)) -> 60.975627 | ... AL72: =(Assumptions!$F$80+(Assumptions!$F$81*AL36)) -> 85.112271
A73: LLM tutor tokens | B73: cogs_llm | C73: =IF(AND((Assumptions!$F$8=1),(C$2>=Assumptions!$F$82)),((C29*Assumptions!$F$83)+(C35*Assumptions!$F$84)),0) -> 0 | D73: =IF(AND((Assumptions!$F$8=1),(D$2>=Assumptions!$F$82)),((D29*Assumptions!$F$83)+(D35*Assumptions!$F$84)),0) -> 0 | E73: =IF(AND((Assumptions!$F$8=1),(E$2>=Assumptions!$F$82)),((E29*Assumptions!$F$83)+(E35*Assumptions!$F$84)),0) -> 0 | F73: =IF(AND((Assumptions!$F$8=1),(F$2>=Assumptions!$F$82)),((F29*Assumptions!$F$83)+(F35*Assumptions!$F$84)),0) -> 0 | G73: =IF(AND((Assumptions!$F$8=1),(G$2>=Assumptions!$F$82)),((G29*Assumptions!$F$83)+(G35*Assumptions!$F$84)),0) -> 0 | H73: =IF(AND((Assumptions!$F$8=1),(H$2>=Assumptions!$F$82)),((H29*Assumptions!$F$83)+(H35*Assumptions!$F$84)),0) -> 0 | I73: =IF(AND((Assumptions!$F$8=1),(I$2>=Assumptions!$F$82)),((I29*Assumptions!$F$83)+(I35*Assumptions!$F$84)),0) -> 49.373284 | J73: =IF(AND((Assumptions!$F$8=1),(J$2>=Assumptions!$F$82)),((J29*Assumptions!$F$83)+(J35*Assumptions!$F$84)),0) -> 55.675581 | ... AL73: =IF(AND((Assumptions!$F$8=1),(AL$2>=Assumptions!$F$82)),((AL29*Assumptions!$F$83)+(AL35*Assumptions!$F$84)),0) -> 234.86653
A74: RevenueCat (1% of MTR above $2.5k) | B74: cogs_rc | C74: =(MAX(0,(C30-Assumptions!$F$85))*Assumptions!$F$86) -> 0 | D74: =(MAX(0,(D30-Assumptions!$F$85))*Assumptions!$F$86) -> 0 | E74: =(MAX(0,(E30-Assumptions!$F$85))*Assumptions!$F$86) -> 0 | F74: =(MAX(0,(F30-Assumptions!$F$85))*Assumptions!$F$86) -> 0 | G74: =(MAX(0,(G30-Assumptions!$F$85))*Assumptions!$F$86) -> 0 | H74: =(MAX(0,(H30-Assumptions!$F$85))*Assumptions!$F$86) -> 0 | I74: =(MAX(0,(I30-Assumptions!$F$85))*Assumptions!$F$86) -> 0 | J74: =(MAX(0,(J30-Assumptions!$F$85))*Assumptions!$F$86) -> 0 | ... AL74: =(MAX(0,(AL30-Assumptions!$F$85))*Assumptions!$F$86) -> 0
A75: B2B card processing | B75: cogs_b2b | C75: =(C66*Assumptions!$F$68) -> 0 | D75: =(D66*Assumptions!$F$68) -> 0 | E75: =(E66*Assumptions!$F$68) -> 0 | F75: =(F66*Assumptions!$F$68) -> 0 | G75: =(G66*Assumptions!$F$68) -> 0 | H75: =(H66*Assumptions!$F$68) -> 0 | I75: =(I66*Assumptions!$F$68) -> 0 | J75: =(J66*Assumptions!$F$68) -> 0 | ... AL75: =(AL66*Assumptions!$F$68) -> 0
A76: Total COGS | B76: cogs_total | C76: =(((((C70+C71)+C72)+C73)+C74)+C75) -> 506.15556 | D76: =(((((D70+D71)+D72)+D73)+D74)+D75) -> 506.87578 | E76: =(((((E70+E71)+E72)+E73)+E74)+E75) -> 507.53242 | F76: =(((((F70+F71)+F72)+F73)+F74)+F75) -> 508.42029 | G76: =(((((G70+G71)+G72)+G73)+G74)+G75) -> 509.07217 | H76: =(((((H70+H71)+H72)+H73)+H74)+H75) -> 509.7119 | I76: =(((((I70+I71)+I72)+I73)+I74)+I75) -> 559.71843 | J76: =(((((J70+J71)+J72)+J73)+J74)+J75) -> 566.65121 | ... AL76: =(((((AL70+AL71)+AL72)+AL73)+AL74)+AL75) -> 1346.1062
A77: GROSS PROFIT | B77: gross_profit | C77: =(C67-C76) -> -429.09051 | D77: =(D67-D76) -> -381.92551 | E77: =(E67-E76) -> -337.46623 | F77: =(F67-F76) -> -286.75335 | G77: =(G67-G76) -> -243.22528 | H77: =(H67-H76) -> -200.67046 | I77: =(I67-I76) -> -206.16491 | J77: =(J67-J76) -> -170.51306 | ... AL77: =(AL67-AL76) -> 260.04648
A78: Gross margin | B78: gross_margin | C78: =IF(C67=0,0,C77/C67) -> -5.5679006 | D78: =IF(D67=0,0,D77/D67) -> -3.0566201 | E78: =IF(E67=0,0,E77/E67) -> -1.9843229 | F78: =IF(F67=0,0,F77/F67) -> -1.2936226 | G78: =IF(G67=0,0,G77/G67) -> -0.91490739 | H78: =IF(H67=0,0,H77/H67) -> -0.64933191 | I78: =IF(I67=0,0,I77/I67) -> -0.5831222 | J78: =IF(J67=0,0,J77/J67) -> -0.43043837 | ... AL78: =IF(AL67=0,0,AL77/AL67) -> 0.16190646
A80: OPERATING EXPENSES
A81: Founder salary | B81: opex_founder | C81: =(Assumptions!$F$10*Assumptions!$F$88) -> 0 | D81: =(Assumptions!$F$10*Assumptions!$F$88) -> 0 | E81: =(Assumptions!$F$10*Assumptions!$F$88) -> 0 | F81: =(Assumptions!$F$10*Assumptions!$F$88) -> 0 | G81: =(Assumptions!$F$10*Assumptions!$F$88) -> 0 | H81: =(Assumptions!$F$10*Assumptions!$F$88) -> 0 | I81: =(Assumptions!$F$10*Assumptions!$F$88) -> 0 | J81: =(Assumptions!$F$10*Assumptions!$F$88) -> 0 | ... AL81: =(Assumptions!$F$10*Assumptions!$F$88) -> 0
A82: Contractors | B82: opex_contractors | C82: =CHOOSE(C$3,Assumptions!$F$89,Assumptions!$F$90,Assumptions!$F$91) -> 300 | D82: =CHOOSE(D$3,Assumptions!$F$89,Assumptions!$F$90,Assumptions!$F$91) -> 300 | E82: =CHOOSE(E$3,Assumptions!$F$89,Assumptions!$F$90,Assumptions!$F$91) -> 300 | F82: =CHOOSE(F$3,Assumptions!$F$89,Assumptions!$F$90,Assumptions!$F$91) -> 300 | G82: =CHOOSE(G$3,Assumptions!$F$89,Assumptions!$F$90,Assumptions!$F$91) -> 300 | H82: =CHOOSE(H$3,Assumptions!$F$89,Assumptions!$F$90,Assumptions!$F$91) -> 300 | I82: =CHOOSE(I$3,Assumptions!$F$89,Assumptions!$F$90,Assumptions!$F$91) -> 300 | J82: =CHOOSE(J$3,Assumptions!$F$89,Assumptions!$F$90,Assumptions!$F$91) -> 300 | ... AL82: =CHOOSE(AL$3,Assumptions!$F$89,Assumptions!$F$90,Assumptions!$F$91) -> 1500
A83: Marketing: Apple Search Ads | B83: opex_asa | C83: =C10 -> 500 | D83: =D10 -> 500 | E83: =E10 -> 500 | F83: =F10 -> 500 | G83: =G10 -> 500 | H83: =H10 -> 500 | I83: =I10 -> 500 | J83: =J10 -> 500 | ... AL83: =AL10 -> 500
A84: Marketing: creators | B84: opex_creators | C84: =C8 -> 0 | D84: =D8 -> 0 | E84: =E8 -> 0 | F84: =F8 -> 300 | G84: =G8 -> 309 | H84: =H8 -> 318.27 | I84: =I8 -> 327.8181 | J84: =J8 -> 337.65264 | ... AL84: =AL8 -> 772.52483
A85: Marketing: other | B85: opex_mkt_other | C85: =Assumptions!$F$92 -> 150 | D85: =Assumptions!$F$92 -> 150 | E85: =Assumptions!$F$92 -> 150 | F85: =Assumptions!$F$92 -> 150 | G85: =Assumptions!$F$92 -> 150 | H85: =Assumptions!$F$92 -> 150 | I85: =Assumptions!$F$92 -> 150 | J85: =Assumptions!$F$92 -> 150 | ... AL85: =Assumptions!$F$92 -> 150
A86: Legal & compliance | B86: opex_legal | C86: =(((IF((C$2=1),(((Assumptions!$F$93+Assumptions!$F$94)+Assumptions!$F$95)+Assumptions!$F$96),0)+Assumptions!$F$97)+IF(AND((C$2>1),(MOD((C$2-1),12)=0)),Assumptions!$F$98,0))+IF(AND((Assumptions!$F$11=1),(C$2>=Assumptions!$F$99)),Assumptions!$F$100,0)) -> 3800 | D86: =(((IF((D$2=1),(((Assumptions!$F$93+Assumptions!$F$94)+Assumptions!$F$95)+Assumptions!$F$96),0)+Assumptions!$F$97)+IF(AND((D$2>1),(MOD((D$2-1),12)=0)),Assumptions!$F$98,0))+IF(AND((Assumptions!$F$11=1),(D$2>=Assumptions!$F$99)),Assumptions!$F$100,0)) -> 100 | E86: =(((IF((E$2=1),(((Assumptions!$F$93+Assumptions!$F$94)+Assumptions!$F$95)+Assumptions!$F$96),0)+Assumptions!$F$97)+IF(AND((E$2>1),(MOD((E$2-1),12)=0)),Assumptions!$F$98,0))+IF(AND((Assumptions!$F$11=1),(E$2>=Assumptions!$F$99)),Assumptions!$F$100,0)) -> 100 | F86: =(((IF((F$2=1),(((Assumptions!$F$93+Assumptions!$F$94)+Assumptions!$F$95)+Assumptions!$F$96),0)+Assumptions!$F$97)+IF(AND((F$2>1),(MOD((F$2-1),12)=0)),Assumptions!$F$98,0))+IF(AND((Assumptions!$F$11=1),(F$2>=Assumptions!$F$99)),Assumptions!$F$100,0)) -> 100 | G86: =(((IF((G$2=1),(((Assumptions!$F$93+Assumptions!$F$94)+Assumptions!$F$95)+Assumptions!$F$96),0)+Assumptions!$F$97)+IF(AND((G$2>1),(MOD((G$2-1),12)=0)),Assumptions!$F$98,0))+IF(AND((Assumptions!$F$11=1),(G$2>=Assumptions!$F$99)),Assumptions!$F$100,0)) -> 100 | H86: =(((IF((H$2=1),(((Assumptions!$F$93+Assumptions!$F$94)+Assumptions!$F$95)+Assumptions!$F$96),0)+Assumptions!$F$97)+IF(AND((H$2>1),(MOD((H$2-1),12)=0)),Assumptions!$F$98,0))+IF(AND((Assumptions!$F$11=1),(H$2>=Assumptions!$F$99)),Assumptions!$F$100,0)) -> 100 | I86: =(((IF((I$2=1),(((Assumptions!$F$93+Assumptions!$F$94)+Assumptions!$F$95)+Assumptions!$F$96),0)+Assumptions!$F$97)+IF(AND((I$2>1),(MOD((I$2-1),12)=0)),Assumptions!$F$98,0))+IF(AND((Assumptions!$F$11=1),(I$2>=Assumptions!$F$99)),Assumptions!$F$100,0)) -> 100 | J86: =(((IF((J$2=1),(((Assumptions!$F$93+Assumptions!$F$94)+Assumptions!$F$95)+Assumptions!$F$96),0)+Assumptions!$F$97)+IF(AND((J$2>1),(MOD((J$2-1),12)=0)),Assumptions!$F$98,0))+IF(AND((Assumptions!$F$11=1),(J$2>=Assumptions!$F$99)),Assumptions!$F$100,0)) -> 100 | ... AL86: =(((IF((AL$2=1),(((Assumptions!$F$93+Assumptions!$F$94)+Assumptions!$F$95)+Assumptions!$F$96),0)+Assumptions!$F$97)+IF(AND((AL$2>1),(MOD((AL$2-1),12)=0)),Assumptions!$F$98,0))+IF(AND((Assumptions!$F$11=1),(AL$2>=Assumptions!$F$99)),Assumptions!$F$100,0)) -> 100
A87: Software / tools | B87: opex_tools | C87: =CHOOSE(C$3,Assumptions!$F$101,Assumptions!$F$102,Assumptions!$F$103) -> 150 | D87: =CHOOSE(D$3,Assumptions!$F$101,Assumptions!$F$102,Assumptions!$F$103) -> 150 | E87: =CHOOSE(E$3,Assumptions!$F$101,Assumptions!$F$102,Assumptions!$F$103) -> 150 | F87: =CHOOSE(F$3,Assumptions!$F$101,Assumptions!$F$102,Assumptions!$F$103) -> 150 | G87: =CHOOSE(G$3,Assumptions!$F$101,Assumptions!$F$102,Assumptions!$F$103) -> 150 | H87: =CHOOSE(H$3,Assumptions!$F$101,Assumptions!$F$102,Assumptions!$F$103) -> 150 | I87: =CHOOSE(I$3,Assumptions!$F$101,Assumptions!$F$102,Assumptions!$F$103) -> 150 | J87: =CHOOSE(J$3,Assumptions!$F$101,Assumptions!$F$102,Assumptions!$F$103) -> 150 | ... AL87: =CHOOSE(AL$3,Assumptions!$F$101,Assumptions!$F$102,Assumptions!$F$103) -> 400
A88: Apple / Google developer fees | B88: opex_stores | C88: =(IF((MOD((C$2-1),12)=0),Assumptions!$F$104,0)+IF((C$2=1),Assumptions!$F$105,0)) -> 124 | D88: =(IF((MOD((D$2-1),12)=0),Assumptions!$F$104,0)+IF((D$2=1),Assumptions!$F$105,0)) -> 0 | E88: =(IF((MOD((E$2-1),12)=0),Assumptions!$F$104,0)+IF((E$2=1),Assumptions!$F$105,0)) -> 0 | F88: =(IF((MOD((F$2-1),12)=0),Assumptions!$F$104,0)+IF((F$2=1),Assumptions!$F$105,0)) -> 0 | G88: =(IF((MOD((G$2-1),12)=0),Assumptions!$F$104,0)+IF((G$2=1),Assumptions!$F$105,0)) -> 0 | H88: =(IF((MOD((H$2-1),12)=0),Assumptions!$F$104,0)+IF((H$2=1),Assumptions!$F$105,0)) -> 0 | I88: =(IF((MOD((I$2-1),12)=0),Assumptions!$F$104,0)+IF((I$2=1),Assumptions!$F$105,0)) -> 0 | J88: =(IF((MOD((J$2-1),12)=0),Assumptions!$F$104,0)+IF((J$2=1),Assumptions!$F$105,0)) -> 0 | ... AL88: =(IF((MOD((AL$2-1),12)=0),Assumptions!$F$104,0)+IF((AL$2=1),Assumptions!$F$105,0)) -> 0
A89: Insurance | B89: opex_insurance | C89: =Assumptions!$F$106 -> 100 | D89: =Assumptions!$F$106 -> 100 | E89: =Assumptions!$F$106 -> 100 | F89: =Assumptions!$F$106 -> 100 | G89: =Assumptions!$F$106 -> 100 | H89: =Assumptions!$F$106 -> 100 | I89: =Assumptions!$F$106 -> 100 | J89: =Assumptions!$F$106 -> 100 | ... AL89: =Assumptions!$F$106 -> 100
A90: Total operating expenses | B90: opex_total | C90: =((((((((C81+C82)+C83)+C84)+C85)+C86)+C87)+C88)+C89) -> 5124 | D90: =((((((((D81+D82)+D83)+D84)+D85)+D86)+D87)+D88)+D89) -> 1300 | E90: =((((((((E81+E82)+E83)+E84)+E85)+E86)+E87)+E88)+E89) -> 1300 | F90: =((((((((F81+F82)+F83)+F84)+F85)+F86)+F87)+F88)+F89) -> 1600 | G90: =((((((((G81+G82)+G83)+G84)+G85)+G86)+G87)+G88)+G89) -> 1609 | H90: =((((((((H81+H82)+H83)+H84)+H85)+H86)+H87)+H88)+H89) -> 1618.27 | I90: =((((((((I81+I82)+I83)+I84)+I85)+I86)+I87)+I88)+I89) -> 1627.8181 | J90: =((((((((J81+J82)+J83)+J84)+J85)+J86)+J87)+J88)+J89) -> 1637.6526 | ... AL90: =((((((((AL81+AL82)+AL83)+AL84)+AL85)+AL86)+AL87)+AL88)+AL89) -> 3522.5248
A91: OPERATING INCOME (EBIT) | B91: ebit | C91: =(C77-C90) -> -5553.0905 | D91: =(D77-D90) -> -1681.9255 | E91: =(E77-E90) -> -1637.4662 | F91: =(F77-F90) -> -1886.7534 | G91: =(G77-G90) -> -1852.2253 | H91: =(H77-H90) -> -1818.9405 | I91: =(I77-I90) -> -1833.983 | J91: =(J77-J90) -> -1808.1657 | ... AL91: =(AL77-AL90) -> -3262.4783
A92: Operating margin | B92: ebit_margin | C92: =IF(C67=0,0,C91/C67) -> -72.057189 | D92: =IF(D67=0,0,D91/D67) -> -13.460759 | E92: =IF(E67=0,0,E91/E67) -> -9.6284056 | F92: =IF(F67=0,0,F91/F67) -> -8.511659 | G92: =IF(G67=0,0,G91/G67) -> -6.9672633 | H92: =IF(H67=0,0,H91/H67) -> -5.8857495 | I92: =IF(I67=0,0,I91/I67) -> -5.1872853 | J92: =IF(J67=0,0,J91/J67) -> -4.5644826 | ... AL92: =IF(AL67=0,0,AL91/AL67) -> -2.031238
A94: CASH
A95: In-app billings net of refunds & store fee | B95: bill_net | C95: =(C30*Assumptions!$F$112) -> 299.94496 | D95: =(D30*Assumptions!$F$112) -> 337.46199 | E95: =(E30*Assumptions!$F$112) -> 370.0603 | F95: =(F30*Assumptions!$F$112) -> 412.47399 | G95: =(G30*Assumptions!$F$112) -> 442.35341 | H95: =(H30*Assumptions!$F$112) -> 470.68264 | I95: =(I30*Assumptions!$F$112) -> 497.95115 | J95: =(J30*Assumptions!$F$112) -> 524.50475 | ... AL95: =(AL30*Assumptions!$F$112) -> 1784.9963
A96: Change in deferred revenue (annual plans paid upfront) | B96: deferred_chg | C96: =(C95-C60) -> 222.87992 | D96: =(D95-D60) -> 212.51172 | E96: =(E95-E60) -> 199.99412 | F96: =(F95-F60) -> 196.06169 | G96: =(G95-G60) -> 182.12902 | H96: =(H95-H60) -> 167.62362 | I96: =(I95-I60) -> 152.59745 | J96: =(J95-J60) -> 137.03266 | ... AL96: =(AL95-AL60) -> 205.99009
A97: Operating cash flow | B97: cash_flow | C97: =(C91+C96) -> -5330.2106 | D97: =(D91+D96) -> -1469.4138 | E97: =(E91+E96) -> -1437.4721 | F97: =(F91+F96) -> -1690.6917 | G97: =(G91+G96) -> -1670.0963 | H97: =(H91+H96) -> -1651.3168 | I97: =(I91+I96) -> -1681.3856 | J97: =(J91+J96) -> -1671.133 | ... AL97: =(AL91+AL96) -> -3056.4882
A98: Cumulative cash (from $0 at launch) | B98: cash_cum | C98: =(0+C97) -> -5330.2106 | D98: =(C98+D97) -> -6799.6244 | E98: =(D98+E97) -> -8237.0965 | F98: =(E98+F97) -> -9927.7882 | G98: =(F98+G97) -> -11597.884 | H98: =(G98+H97) -> -13249.201 | I98: =(H98+I97) -> -14930.587 | J98: =(I98+J97) -> -16601.72 | K98: =(J98+K97) -> -18263.421 | ... AL98: =(AK98+AL97) -> -91904.652
A99: Cumulative operating income | B99: ebit_cum | C99: =(0+C91) -> -5553.0905 | D99: =(C99+D91) -> -7235.016 | E99: =(D99+E91) -> -8872.4822 | F99: =(E99+F91) -> -10759.236 | G99: =(F99+G91) -> -12611.461 | H99: =(G99+H91) -> -14430.401 | I99: =(H99+I91) -> -16264.384 | J99: =(I99+J91) -> -18072.55 | K99: =(J99+K91) -> -19855.161 | ... AL99: =(AK99+AL91) -> -97460.374
A101: KPIs
A102: ARPU: total revenue / MAU | B102: arpu | C102: =IF(C36=0,0,C67/C36) -> 0.12519592 | D102: =IF(D36=0,0,D67/D36) -> 0.18172519 | E102: =IF(E36=0,0,E67/E36) -> 0.22577908 | F102: =IF(F36=0,0,F67/F36) -> 0.26325343 | G102: =IF(G36=0,0,G67/G36) -> 0.29303548 | H102: =IF(H36=0,0,H67/H36) -> 0.31820918 | I102: =IF(I36=0,0,I67/I36) -> 0.34175777 | J102: =IF(J36=0,0,J67/J36) -> 0.36092529 | ... AL102: =IF(AL36=0,0,AL67/AL36) -> 0.45743343
A103: ARPPU: net subscription revenue / paid subscriber | B103: arppu | C103: =IF(C29=0,0,C60/C29) -> 8.6223087 | D103: =IF(D29=0,0,D60/D29) -> 7.085079 | E103: =IF(E29=0,0,E60/E29) -> 6.5088373 | F103: =IF(F29=0,0,F60/F29) -> 6.2070336 | G103: =IF(G29=0,0,G60/G29) -> 5.9759219 | H103: =IF(H29=0,0,H60/H29) -> 5.8021971 | I103: =IF(I29=0,0,I60/I29) -> 5.6632573 | J103: =IF(J29=0,0,J60/J29) -> 5.5477045 | ... AL103: =IF(AL29=0,0,AL60/AL29) -> 5.059036
A104: CAC: paid channels (ASA + creators) per payer they bring | B104: cac_paid | C104: =IF(((C11+C9)*Assumptions!$F$111)=0,0,(C10+C8)/((C11+C9)*Assumptions!$F$111)) -> 619.83471 | D104: =IF(((D11+D9)*Assumptions!$F$111)=0,0,(D10+D8)/((D11+D9)*Assumptions!$F$111)) -> 619.83471 | E104: =IF(((E11+E9)*Assumptions!$F$111)=0,0,(E10+E8)/((E11+E9)*Assumptions!$F$111)) -> 619.83471 | F104: =IF(((F11+F9)*Assumptions!$F$111)=0,0,(F10+F8)/((F11+F9)*Assumptions!$F$111)) -> 683.95554 | G104: =IF(((G11+G9)*Assumptions!$F$111)=0,0,(G10+G8)/((G11+G9)*Assumptions!$F$111)) -> 685.26994 | H104: =IF(((H11+H9)*Assumptions!$F$111)=0,0,(H10+H8)/((H11+H9)*Assumptions!$F$111)) -> 686.59866 | I104: =IF(((I11+I9)*Assumptions!$F$111)=0,0,(I10+I8)/((I11+I9)*Assumptions!$F$111)) -> 687.94135 | J104: =IF(((J11+J9)*Assumptions!$F$111)=0,0,(J10+J8)/((J11+J9)*Assumptions!$F$111)) -> 689.29762 | ... AL104: =IF(((AL11+AL9)*Assumptions!$F$111)=0,0,(AL10+AL8)/((AL11+AL9)*Assumptions!$F$111)) -> 730.73904
A105: EBIT >= 0 this month (1 = yes) | B105: flag_be | C105: =IF((C91>=0),1,0) -> 0 | D105: =IF((D91>=0),1,0) -> 0 | E105: =IF((E91>=0),1,0) -> 0 | F105: =IF((F91>=0),1,0) -> 0 | G105: =IF((G91>=0),1,0) -> 0 | H105: =IF((H91>=0),1,0) -> 0 | I105: =IF((I91>=0),1,0) -> 0 | J105: =IF((J91>=0),1,0) -> 0 | ... AL105: =IF((AL91>=0),1,0) -> 0
A106: EBIT >= 0 this month and every month after | B106: flag_be_sus | C106: =IF(AND((C91>=0),(D106=1)),1,0) -> 0 | D106: =IF(AND((D91>=0),(E106=1)),1,0) -> 0 | E106: =IF(AND((E91>=0),(F106=1)),1,0) -> 0 | F106: =IF(AND((F91>=0),(G106=1)),1,0) -> 0 | G106: =IF(AND((G91>=0),(H106=1)),1,0) -> 0 | H106: =IF(AND((H91>=0),(I106=1)),1,0) -> 0 | I106: =IF(AND((I91>=0),(J106=1)),1,0) -> 0 | J106: =IF(AND((J91>=0),(K106=1)),1,0) -> 0 | ... AK106: =IF(AND((AK91>=0),(AL106=1)),1,0) -> 0 | AL106: =IF((AL91>=0),1,0) -> 0
A107: Cumulative cash >= 0 this month and every month after | B107: flag_cash_sus | C107: =IF(AND((C98>=0),(D107=1)),1,0) -> 0 | D107: =IF(AND((D98>=0),(E107=1)),1,0) -> 0 | E107: =IF(AND((E98>=0),(F107=1)),1,0) -> 0 | F107: =IF(AND((F98>=0),(G107=1)),1,0) -> 0 | G107: =IF(AND((G98>=0),(H107=1)),1,0) -> 0 | H107: =IF(AND((H98>=0),(I107=1)),1,0) -> 0 | I107: =IF(AND((I98>=0),(J107=1)),1,0) -> 0 | J107: =IF(AND((J98>=0),(K107=1)),1,0) -> 0 | ... AK107: =IF(AND((AK98>=0),(AL107=1)),1,0) -> 0 | AL107: =IF((AL98>=0),1,0) -> 0

Sheet Monthly_Bull
A1: Tenbagger: Bull case, monthly (USD). All cells are formulas driven by the Assumptions sheet.
A2: Month | C2: 1 | D2: 2 | E2: 3 | F2: 4 | G2: 5 | H2: 6 | I2: 7 | J2: 8 | K2: 9 | L2: 10 | M2: 11 | N2: 12 | O2: 13 | P2: 14 | Q2: 15 | R2: 16 | S2: 17 | T2: 18 | U2: 19 | V2: 20 | W2: 21 | X2: 22 | Y2: 23 | Z2: 24 | AA2: 25 | AB2: 26 | AC2: 27 | AD2: 28 | AE2: 29 | AF2: 30 | AG2: 31 | AH2: 32 | AI2: 33 | AJ2: 34 | AK2: 35 | AL2: 36
A3: Fiscal year | C3: 1 | D3: 1 | E3: 1 | F3: 1 | G3: 1 | H3: 1 | I3: 1 | J3: 1 | K3: 1 | L3: 1 | M3: 1 | N3: 1 | O3: 2 | P3: 2 | Q3: 2 | R3: 2 | S3: 2 | T3: 2 | U3: 2 | V3: 2 | W3: 2 | X3: 2 | Y3: 2 | Z3: 2 | AA3: 3 | AB3: 3 | AC3: 3 | AD3: 3 | AE3: 3 | AF3: 3 | AG3: 3 | AH3: 3 | AI3: 3 | AJ3: 3 | AK3: 3 | AL3: 3
A4: Calendar month | C4: Jan-27 | D4: Feb-27 | E4: Mar-27 | F4: Apr-27 | G4: May-27 | H4: Jun-27 | I4: Jul-27 | J4: Aug-27 | K4: Sep-27 | L4: Oct-27 | M4: Nov-27 | N4: Dec-27 | O4: Jan-28 | P4: Feb-28 | Q4: Mar-28 | R4: Apr-28 | S4: May-28 | T4: Jun-28 | U4: Jul-28 | V4: Aug-28 | W4: Sep-28 | X4: Oct-28 | Y4: Nov-28 | Z4: Dec-28 | AA4: Jan-29 | AB4: Feb-29 | AC4: Mar-29 | AD4: Apr-29 | AE4: May-29 | AF4: Jun-29 | AG4: Jul-29 | AH4: Aug-29 | AI4: Sep-29 | AJ4: Oct-29 | AK4: Nov-29 | AL4: Dec-29
A5: ACQUISITION
A6: Installs: organic / SEO / ASO | B6: inst_org | C6: =(Assumptions!$G$13*((1+Assumptions!$G$14)^(C$2-1))) -> 2100 | D6: =(Assumptions!$G$13*((1+Assumptions!$G$14)^(D$2-1))) -> 2289 | E6: =(Assumptions!$G$13*((1+Assumptions!$G$14)^(E$2-1))) -> 2495.01 | F6: =(Assumptions!$G$13*((1+Assumptions!$G$14)^(F$2-1))) -> 2719.5609 | G6: =(Assumptions!$G$13*((1+Assumptions!$G$14)^(G$2-1))) -> 2964.3214 | H6: =(Assumptions!$G$13*((1+Assumptions!$G$14)^(H$2-1))) -> 3231.1103 | I6: =(Assumptions!$G$13*((1+Assumptions!$G$14)^(I$2-1))) -> 3521.9102 | J6: =(Assumptions!$G$13*((1+Assumptions!$G$14)^(J$2-1))) -> 3838.8822 | ... AL6: =(Assumptions!$G$13*((1+Assumptions!$G$14)^(AL$2-1))) -> 42869.333
A7: Installs: referral (x prior-month MAU) | B7: inst_ref | C7: =(Assumptions!$G$15*0) -> 0 | D7: =(Assumptions!$G$15*C36) -> 70.5 | E7: =(Assumptions!$G$15*D36) -> 95.106885 | F7: =(Assumptions!$G$15*E36) -> 119.88984 | G7: =(Assumptions!$G$15*F36) -> 152.03684 | H7: =(Assumptions!$G$15*G36) -> 181.73249 | I7: =(Assumptions!$G$15*H36) -> 213.13639 | J7: =(Assumptions!$G$15*I36) -> 246.53979 | K7: =(Assumptions!$G$15*J36) -> 282.16184 | ... AL7: =(Assumptions!$G$15*AK36) -> 3589.0952
A8: Creator spend | B8: spend_creators | C8: =IF((C$2>=Assumptions!$G$16),(Assumptions!$G$17*((1+Assumptions!$G$18)^(C$2-Assumptions!$G$16))),0) -> 0 | D8: =IF((D$2>=Assumptions!$G$16),(Assumptions!$G$17*((1+Assumptions!$G$18)^(D$2-Assumptions!$G$16))),0) -> 0 | E8: =IF((E$2>=Assumptions!$G$16),(Assumptions!$G$17*((1+Assumptions!$G$18)^(E$2-Assumptions!$G$16))),0) -> 0 | F8: =IF((F$2>=Assumptions!$G$16),(Assumptions!$G$17*((1+Assumptions!$G$18)^(F$2-Assumptions!$G$16))),0) -> 1000 | G8: =IF((G$2>=Assumptions!$G$16),(Assumptions!$G$17*((1+Assumptions!$G$18)^(G$2-Assumptions!$G$16))),0) -> 1070 | H8: =IF((H$2>=Assumptions!$G$16),(Assumptions!$G$17*((1+Assumptions!$G$18)^(H$2-Assumptions!$G$16))),0) -> 1144.9 | I8: =IF((I$2>=Assumptions!$G$16),(Assumptions!$G$17*((1+Assumptions!$G$18)^(I$2-Assumptions!$G$16))),0) -> 1225.043 | J8: =IF((J$2>=Assumptions!$G$16),(Assumptions!$G$17*((1+Assumptions!$G$18)^(J$2-Assumptions!$G$16))),0) -> 1310.796 | ... AL8: =IF((AL$2>=Assumptions!$G$16),(Assumptions!$G$17*((1+Assumptions!$G$18)^(AL$2-Assumptions!$G$16))),0) -> 8715.2708
A9: Installs: creators | B9: inst_creators | C9: =IF(Assumptions!$G$19=0,0,C8/Assumptions!$G$19) -> 0 | D9: =IF(Assumptions!$G$19=0,0,D8/Assumptions!$G$19) -> 0 | E9: =IF(Assumptions!$G$19=0,0,E8/Assumptions!$G$19) -> 0 | F9: =IF(Assumptions!$G$19=0,0,F8/Assumptions!$G$19) -> 200 | G9: =IF(Assumptions!$G$19=0,0,G8/Assumptions!$G$19) -> 214 | H9: =IF(Assumptions!$G$19=0,0,H8/Assumptions!$G$19) -> 228.98 | I9: =IF(Assumptions!$G$19=0,0,I8/Assumptions!$G$19) -> 245.0086 | J9: =IF(Assumptions!$G$19=0,0,J8/Assumptions!$G$19) -> 262.1592 | ... AL9: =IF(Assumptions!$G$19=0,0,AL8/Assumptions!$G$19) -> 1743.0542
A10: Apple Search Ads spend | B10: spend_asa | C10: =IF((C$2>=Assumptions!$G$20),(Assumptions!$G$21*((1+Assumptions!$G$22)^(C$2-Assumptions!$G$20))),0) -> 1000 | D10: =IF((D$2>=Assumptions!$G$20),(Assumptions!$G$21*((1+Assumptions!$G$22)^(D$2-Assumptions!$G$20))),0) -> 1060 | E10: =IF((E$2>=Assumptions!$G$20),(Assumptions!$G$21*((1+Assumptions!$G$22)^(E$2-Assumptions!$G$20))),0) -> 1123.6 | F10: =IF((F$2>=Assumptions!$G$20),(Assumptions!$G$21*((1+Assumptions!$G$22)^(F$2-Assumptions!$G$20))),0) -> 1191.016 | G10: =IF((G$2>=Assumptions!$G$20),(Assumptions!$G$21*((1+Assumptions!$G$22)^(G$2-Assumptions!$G$20))),0) -> 1262.477 | H10: =IF((H$2>=Assumptions!$G$20),(Assumptions!$G$21*((1+Assumptions!$G$22)^(H$2-Assumptions!$G$20))),0) -> 1338.2256 | I10: =IF((I$2>=Assumptions!$G$20),(Assumptions!$G$21*((1+Assumptions!$G$22)^(I$2-Assumptions!$G$20))),0) -> 1418.5191 | J10: =IF((J$2>=Assumptions!$G$20),(Assumptions!$G$21*((1+Assumptions!$G$22)^(J$2-Assumptions!$G$20))),0) -> 1503.6303 | ... AL10: =IF((AL$2>=Assumptions!$G$20),(Assumptions!$G$21*((1+Assumptions!$G$22)^(AL$2-Assumptions!$G$20))),0) -> 7686.0868
A11: Installs: paid Apple Search Ads | B11: inst_asa | C11: =IF(Assumptions!$G$23=0,0,C10/Assumptions!$G$23) -> 250 | D11: =IF(Assumptions!$G$23=0,0,D10/Assumptions!$G$23) -> 265 | E11: =IF(Assumptions!$G$23=0,0,E10/Assumptions!$G$23) -> 280.9 | F11: =IF(Assumptions!$G$23=0,0,F10/Assumptions!$G$23) -> 297.754 | G11: =IF(Assumptions!$G$23=0,0,G10/Assumptions!$G$23) -> 315.61924 | H11: =IF(Assumptions!$G$23=0,0,H10/Assumptions!$G$23) -> 334.55639 | I11: =IF(Assumptions!$G$23=0,0,I10/Assumptions!$G$23) -> 354.62978 | J11: =IF(Assumptions!$G$23=0,0,J10/Assumptions!$G$23) -> 375.90756 | ... AL11: =IF(Assumptions!$G$23=0,0,AL10/Assumptions!$G$23) -> 1921.5217
A12: Total installs | B12: inst_total | C12: =(((C6+C7)+C9)+C11) -> 2350 | D12: =(((D6+D7)+D9)+D11) -> 2624.5 | E12: =(((E6+E7)+E9)+E11) -> 2871.0169 | F12: =(((F6+F7)+F9)+F11) -> 3337.2047 | G12: =(((G6+G7)+G9)+G11) -> 3645.9775 | H12: =(((H6+H7)+H9)+H11) -> 3976.3792 | I12: =(((I6+I7)+I9)+I11) -> 4334.685 | J12: =(((J6+J7)+J9)+J11) -> 4723.4887 | ... AL12: =(((AL6+AL7)+AL9)+AL11) -> 50123.004
A14: FUNNEL (free -> trial -> paid)
A15: Activated users | B15: activated | C15: =(C12*Assumptions!$G$25) -> 1762.5 | D15: =(D12*Assumptions!$G$25) -> 1968.375 | E15: =(E12*Assumptions!$G$25) -> 2153.2627 | F15: =(F12*Assumptions!$G$25) -> 2502.9036 | G15: =(G12*Assumptions!$G$25) -> 2734.4831 | H15: =(H12*Assumptions!$G$25) -> 2982.2844 | I15: =(I12*Assumptions!$G$25) -> 3251.0138 | J15: =(J12*Assumptions!$G$25) -> 3542.6165 | ... AL15: =(AL12*Assumptions!$G$25) -> 37592.253
A16: Trial / paywall starts | B16: trial_starts | C16: =(C15*Assumptions!$G$29) -> 246.75 | D16: =(D15*Assumptions!$G$29) -> 275.5725 | E16: =(E15*Assumptions!$G$29) -> 301.45677 | F16: =(F15*Assumptions!$G$29) -> 350.4065 | G16: =(G15*Assumptions!$G$29) -> 382.82763 | H16: =(H15*Assumptions!$G$29) -> 417.51981 | I16: =(I15*Assumptions!$G$29) -> 455.14193 | J16: =(J15*Assumptions!$G$29) -> 495.96631 | ... AL16: =(AL15*Assumptions!$G$29) -> 5262.9154
A17: New paid subscribers | B17: new_paid | C17: =(C16*Assumptions!$G$30) -> 98.7 | D17: =(D16*Assumptions!$G$30) -> 110.229 | E17: =(E16*Assumptions!$G$30) -> 120.58271 | F17: =(F16*Assumptions!$G$30) -> 140.1626 | G17: =(G16*Assumptions!$G$30) -> 153.13105 | H17: =(H16*Assumptions!$G$30) -> 167.00793 | I17: =(I16*Assumptions!$G$30) -> 182.05677 | J17: =(J16*Assumptions!$G$30) -> 198.38653 | ... AL17: =(AL16*Assumptions!$G$30) -> 2105.1662
A18: of which monthly plan | B18: new_monthly | C18: =(C17*Assumptions!$G$31) -> 29.61 | D18: =(D17*Assumptions!$G$31) -> 33.0687 | E18: =(E17*Assumptions!$G$31) -> 36.174813 | F18: =(F17*Assumptions!$G$31) -> 42.04878 | G18: =(G17*Assumptions!$G$31) -> 45.939316 | H18: =(H17*Assumptions!$G$31) -> 50.102378 | I18: =(I17*Assumptions!$G$31) -> 54.617031 | J18: =(J17*Assumptions!$G$31) -> 59.515958 | ... AL18: =(AL17*Assumptions!$G$31) -> 631.54985
A19: of which annual plan | B19: new_annual | C19: =(C17*Assumptions!$G$32) -> 54.285 | D19: =(D17*Assumptions!$G$32) -> 60.62595 | E19: =(E17*Assumptions!$G$32) -> 66.32049 | F19: =(F17*Assumptions!$G$32) -> 77.08943 | G19: =(G17*Assumptions!$G$32) -> 84.222079 | H19: =(H17*Assumptions!$G$32) -> 91.854359 | I19: =(I17*Assumptions!$G$32) -> 100.13122 | J19: =(J17*Assumptions!$G$32) -> 109.11259 | ... AL19: =(AL17*Assumptions!$G$32) -> 1157.8414
A20: of which student plan | B20: new_student | C20: =(C17*Assumptions!$G$109) -> 14.805 | D20: =(D17*Assumptions!$G$109) -> 16.53435 | E20: =(E17*Assumptions!$G$109) -> 18.087406 | F20: =(F17*Assumptions!$G$109) -> 21.02439 | G20: =(G17*Assumptions!$G$109) -> 22.969658 | H20: =(H17*Assumptions!$G$109) -> 25.051189 | I20: =(I17*Assumptions!$G$109) -> 27.308516 | J20: =(J17*Assumptions!$G$109) -> 29.757979 | ... AL20: =(AL17*Assumptions!$G$109) -> 315.77492
A21: Recruiting Pass purchases (one-time) | B21: pass_sales | C21: =(C15*Assumptions!$G$33) -> 14.1 | D21: =(D15*Assumptions!$G$33) -> 15.747 | E21: =(E15*Assumptions!$G$33) -> 17.226101 | F21: =(F15*Assumptions!$G$33) -> 20.023228 | G21: =(G15*Assumptions!$G$33) -> 21.875865 | H21: =(H15*Assumptions!$G$33) -> 23.858275 | I21: =(I15*Assumptions!$G$33) -> 26.00811 | J21: =(J15*Assumptions!$G$33) -> 28.340932 | ... AL21: =(AL15*Assumptions!$G$33) -> 300.73802
A23: SUBSCRIBERS
A24: Monthly-plan subscribers (end of month) | B24: subs_monthly | C24: =((0*(1-Assumptions!$G$110))+C18) -> 29.61 | D24: =((C24*(1-Assumptions!$G$110))+D18) -> 59.448211 | E24: =((D24*(1-Assumptions!$G$110))+E18) -> 89.137148 | F24: =((E24*(1-Assumptions!$G$110))+F18) -> 121.46095 | G24: =((F24*(1-Assumptions!$G$110))+G18) -> 154.14872 | H24: =((G24*(1-Assumptions!$G$110))+H18) -> 187.43328 | I24: =((H24*(1-Assumptions!$G$110))+I18) -> 221.6011 | J24: =((I24*(1-Assumptions!$G$110))+J18) -> 256.94009 | K24: =((J24*(1-Assumptions!$G$110))+K18) -> 293.7411 | ... AL24: =((AK24*(1-Assumptions!$G$110))+AL18) -> 3484.7364
A25: Annual plans billed (new + renewals) | B25: bill_annual | C25: =(C19+0) -> 54.285 | D25: =(D19+0) -> 60.62595 | E25: =(E19+0) -> 66.32049 | F25: =(F19+0) -> 77.08943 | G25: =(G19+0) -> 84.222079 | H25: =(H19+0) -> 91.854359 | I25: =(I19+0) -> 100.13122 | J25: =(J19+0) -> 109.11259 | ... N25: =(N19+0) -> 153.42739 | O25: =(O19+(Assumptions!$G$43*C25)) -> 196.30689 | P25: =(P19+(Assumptions!$G$43*D25)) -> 214.44885 | Q25: =(Q19+(Assumptions!$G$43*E25)) -> 233.51786 | R25: =(R19+(Assumptions!$G$43*F25)) -> 256.71736 | S25: =(S19+(Assumptions!$G$43*G25)) -> 279.46499 | T25: =(T19+(Assumptions!$G$43*H25)) -> 304.13006 | U25: =(U19+(Assumptions!$G$43*I25)) -> 330.93704 | V25: =(V19+(Assumptions!$G$43*J25)) -> 360.07733 | ... AL25: =(AL19+(Assumptions!$G$43*Z25)) -> 1430.2168
A26: Annual-plan subscribers (billed in last 12 months) | B26: subs_annual | C26: =SUM(C25:C25) -> 54.285 | D26: =SUM(C25:D25) -> 114.91095 | E26: =SUM(C25:E25) -> 181.23144 | F26: =SUM(C25:F25) -> 258.32087 | G26: =SUM(C25:G25) -> 342.54295 | H26: =SUM(C25:H25) -> 434.39731 | I26: =SUM(C25:I25) -> 534.52853 | J26: =SUM(C25:J25) -> 643.64112 | K26: =SUM(C25:K25) -> 762.50253 | L26: =SUM(C25:L25) -> 891.94865 | M26: =SUM(C25:M25) -> 1032.8898 | N26: =SUM(C25:N25) -> 1186.3172 | O26: =SUM(D25:O25) -> 1328.3391 | P26: =SUM(E25:P25) -> 1482.162 | Q26: =SUM(F25:Q25) -> 1649.3593 | R26: =SUM(G25:R25) -> 1828.9873 | S26: =SUM(H25:S25) -> 2024.2302 | T26: =SUM(I25:T25) -> 2236.5059 | U26: =SUM(J25:U25) -> 2467.3117 | ... AL26: =SUM(AA25:AL25) -> 11254.576
A27: Student plans billed (new + renewals) | B27: bill_student | C27: =(C20+0) -> 14.805 | D27: =(D20+0) -> 16.53435 | E27: =(E20+0) -> 18.087406 | F27: =(F20+0) -> 21.02439 | G27: =(G20+0) -> 22.969658 | H27: =(H20+0) -> 25.051189 | I27: =(I20+0) -> 27.308516 | J27: =(J20+0) -> 29.757979 | ... N27: =(N20+0) -> 41.843833 | O27: =(O20+(Assumptions!$G$44*C27)) -> 52.205794 | P27: =(P20+(Assumptions!$G$44*D27)) -> 56.997959 | Q27: =(Q20+(Assumptions!$G$44*E27)) -> 62.058822 | R27: =(R20+(Assumptions!$G$44*F27)) -> 68.121631 | S27: =(S20+(Assumptions!$G$44*G27)) -> 74.150455 | T27: =(T20+(Assumptions!$G$44*H27)) -> 80.689956 | U27: =(U20+(Assumptions!$G$44*I27)) -> 87.797791 | V27: =(V20+(Assumptions!$G$44*J27)) -> 95.524689 | ... AL27: =(AL20+(Assumptions!$G$44*Z27)) -> 375.98375
A28: Student-plan subscribers | B28: subs_student | C28: =SUM(C27:C27) -> 14.805 | D28: =SUM(C27:D27) -> 31.33935 | E28: =SUM(C27:E27) -> 49.426756 | F28: =SUM(C27:F27) -> 70.451146 | G28: =SUM(C27:G27) -> 93.420804 | H28: =SUM(C27:H27) -> 118.47199 | I28: =SUM(C27:I27) -> 145.78051 | J28: =SUM(C27:J27) -> 175.53849 | K28: =SUM(C27:K27) -> 207.95524 | L28: =SUM(C27:L27) -> 243.25872 | M28: =SUM(C27:M27) -> 281.69721 | N28: =SUM(C27:N27) -> 323.54104 | O28: =SUM(D27:O27) -> 360.94184 | P28: =SUM(E27:P27) -> 401.40545 | Q28: =SUM(F27:Q27) -> 445.37686 | R28: =SUM(G27:R27) -> 492.4741 | S28: =SUM(H27:S27) -> 543.6549 | T28: =SUM(I27:T27) -> 599.29367 | U28: =SUM(J27:U27) -> 659.78294 | ... AL28: =SUM(AA27:AL27) -> 2959.0865
A29: Paid subscribers (end of month) | B29: subs_paid | C29: =((C24+C26)+C28) -> 98.7 | D29: =((D24+D26)+D28) -> 205.69851 | E29: =((E24+E26)+E28) -> 319.79534 | F29: =((F24+F26)+F28) -> 450.23297 | G29: =((G24+G26)+G28) -> 590.11247 | H29: =((H24+H26)+H28) -> 740.30258 | I29: =((I24+I26)+I28) -> 901.91014 | J29: =((J24+J26)+J28) -> 1076.1197 | ... AL29: =((AL24+AL26)+AL28) -> 17698.399
A30: Gross in-app billings, cash basis (= RevenueCat MTR) | B30: bill_gross | C30: =((((C24*Assumptions!$G$35)+(C25*Assumptions!$G$36))+(C27*Assumptions!$G$37))+(C21*Assumptions!$G$38)) -> 7154.763 | D30: =((((D24*Assumptions!$G$35)+(D25*Assumptions!$G$36))+(D27*Assumptions!$G$37))+(D21*Assumptions!$G$38)) -> 8385.9291 | E30: =((((E24*Assumptions!$G$35)+(E25*Assumptions!$G$36))+(E27*Assumptions!$G$37))+(E21*Assumptions!$G$38)) -> 9534.946 | F30: =((((F24*Assumptions!$G$35)+(F25*Assumptions!$G$36))+(F27*Assumptions!$G$37))+(F21*Assumptions!$G$38)) -> 11350.775 | G30: =((((G24*Assumptions!$G$35)+(G25*Assumptions!$G$36))+(G27*Assumptions!$G$37))+(G21*Assumptions!$G$38)) -> 12722.529 | H30: =((((H24*Assumptions!$G$35)+(H25*Assumptions!$G$36))+(H27*Assumptions!$G$37))+(H21*Assumptions!$G$38)) -> 14164.995 | I30: =((((I24*Assumptions!$G$35)+(I25*Assumptions!$G$36))+(I27*Assumptions!$G$37))+(I21*Assumptions!$G$38)) -> 15700.386 | J30: =((((J24*Assumptions!$G$35)+(J25*Assumptions!$G$36))+(J27*Assumptions!$G$37))+(J21*Assumptions!$G$38)) -> 17340.427 | ... AL30: =((((AL24*Assumptions!$G$35)+(AL25*Assumptions!$G$36))+(AL27*Assumptions!$G$37))+(AL21*Assumptions!$G$38)) -> 225015.33
A32: ACTIVE USERS
A33: New free users this month | B33: free_new | C33: =(C12-C17) -> 2251.3 | D33: =(D12-D17) -> 2514.271 | E33: =(E12-E17) -> 2750.4342 | F33: =(F12-F17) -> 3197.0421 | G33: =(G12-G17) -> 3492.8464 | H33: =(H12-H17) -> 3809.3713 | I33: =(I12-I17) -> 4152.6282 | J33: =(J12-J17) -> 4525.1022 | ... AL33: =(AL12-AL17) -> 48017.838
A34: Retained free users from earlier months | B34: free_pool | C34: =((0*(1-Assumptions!$G$27))+(0*Assumptions!$G$26)) -> 0 | D34: =((C34*(1-Assumptions!$G$27))+(C33*Assumptions!$G$26)) -> 450.26 | E34: =((D34*(1-Assumptions!$G$27))+(D33*Assumptions!$G$26)) -> 926.0986 | F34: =((E34*(1-Assumptions!$G$27))+(E33*Assumptions!$G$26)) -> 1420.6195 | G34: =((F34*(1-Assumptions!$G$27))+(F33*Assumptions!$G$26)) -> 1974.7908 | H34: =((G34*(1-Assumptions!$G$27))+(G33*Assumptions!$G$26)) -> 2554.8726 | I34: =((H34*(1-Assumptions!$G$27))+(H33*Assumptions!$G$26)) -> 3163.4545 | J34: =((I34*(1-Assumptions!$G$27))+(I33*Assumptions!$G$26)) -> 3804.1729 | K34: =((J34*(1-Assumptions!$G$27))+(J33*Assumptions!$G$26)) -> 4480.9429 | ... AL34: =((AK34*(1-Assumptions!$G$27))+(AK33*Assumptions!$G$26)) -> 64526.413
A35: Free MAU | B35: mau_free | C35: =(C33+C34) -> 2251.3 | D35: =(D33+D34) -> 2964.531 | E35: =(E33+E34) -> 3676.5328 | F35: =(F33+F34) -> 4617.6617 | G35: =(G33+G34) -> 5467.6372 | H35: =(H33+H34) -> 6364.2439 | I35: =(I33+I34) -> 7316.0827 | J35: =(J33+J34) -> 8329.2751 | ... AL35: =(AL33+AL34) -> 112544.25
A36: Total MAU (free + paid) | B36: mau_total | C36: =(C35+C29) -> 2350 | D36: =(D35+D29) -> 3170.2295 | E36: =(E35+E29) -> 3996.3281 | F36: =(F35+F29) -> 5067.8946 | G36: =(G35+G29) -> 6057.7497 | H36: =(H35+H29) -> 7104.5465 | I36: =(I35+I29) -> 8217.9929 | J36: =(J35+J29) -> 9405.3948 | ... AL36: =(AL35+AL29) -> 130242.65
A37: Paid subscribers / MAU | B37: paid_share | C37: =IF(C36=0,0,C29/C36) -> 0.042 | D37: =IF(D36=0,0,D29/D36) -> 0.064884423 | E37: =IF(E36=0,0,E29/E36) -> 0.080022294 | F37: =IF(F36=0,0,F29/F36) -> 0.088840238 | G37: =IF(G36=0,0,G29/G36) -> 0.09741447 | H37: =IF(H36=0,0,H29/H36) -> 0.10420124 | I37: =IF(I36=0,0,I29/I36) -> 0.10974823 | J37: =IF(J36=0,0,J29/J36) -> 0.11441515 | ... AL37: =IF(AL36=0,0,AL29/AL36) -> 0.13588789
A39: ADS, AFFILIATE, B2B AND LINKING VOLUMES
A40: Free MAU seeing ads | B40: ad_mau | C40: =IF(AND((Assumptions!$G$5=1),(C$2>=Assumptions!$G$46)),(C35*Assumptions!$G$47),0) -> 0 | D40: =IF(AND((Assumptions!$G$5=1),(D$2>=Assumptions!$G$46)),(D35*Assumptions!$G$47),0) -> 0 | E40: =IF(AND((Assumptions!$G$5=1),(E$2>=Assumptions!$G$46)),(E35*Assumptions!$G$47),0) -> 0 | F40: =IF(AND((Assumptions!$G$5=1),(F$2>=Assumptions!$G$46)),(F35*Assumptions!$G$47),0) -> 3694.1293 | G40: =IF(AND((Assumptions!$G$5=1),(G$2>=Assumptions!$G$46)),(G35*Assumptions!$G$47),0) -> 4374.1097 | H40: =IF(AND((Assumptions!$G$5=1),(H$2>=Assumptions!$G$46)),(H35*Assumptions!$G$47),0) -> 5091.3951 | I40: =IF(AND((Assumptions!$G$5=1),(I$2>=Assumptions!$G$46)),(I35*Assumptions!$G$47),0) -> 5852.8662 | J40: =IF(AND((Assumptions!$G$5=1),(J$2>=Assumptions!$G$46)),(J35*Assumptions!$G$47),0) -> 6663.4201 | ... AL40: =IF(AND((Assumptions!$G$5=1),(AL$2>=Assumptions!$G$46)),(AL35*Assumptions!$G$47),0) -> 90035.4
A41: Ad impressions: article / lesson end | B41: imps_article | C41: =(C40*Assumptions!$G$48) -> 0 | D41: =(D40*Assumptions!$G$48) -> 0 | E41: =(E40*Assumptions!$G$48) -> 0 | F41: =(F40*Assumptions!$G$48) -> 44329.552 | G41: =(G40*Assumptions!$G$48) -> 52489.317 | H41: =(H40*Assumptions!$G$48) -> 61096.741 | I41: =(I40*Assumptions!$G$48) -> 70234.394 | J41: =(J40*Assumptions!$G$48) -> 79961.041 | ... AL41: =(AL40*Assumptions!$G$48) -> 1080424.8
A42: Ad impressions: screener native | B42: imps_screener | C42: =(C40*Assumptions!$G$49) -> 0 | D42: =(D40*Assumptions!$G$49) -> 0 | E42: =(E40*Assumptions!$G$49) -> 0 | F42: =(F40*Assumptions!$G$49) -> 22164.776 | G42: =(G40*Assumptions!$G$49) -> 26244.658 | H42: =(H40*Assumptions!$G$49) -> 30548.371 | I42: =(I40*Assumptions!$G$49) -> 35117.197 | J42: =(J40*Assumptions!$G$49) -> 39980.52 | ... AL42: =(AL40*Assumptions!$G$49) -> 540212.4
A43: Ad impressions: opt-in rewarded | B43: imps_rewarded | C43: =(C40*Assumptions!$G$50) -> 0 | D43: =(D40*Assumptions!$G$50) -> 0 | E43: =(E40*Assumptions!$G$50) -> 0 | F43: =(F40*Assumptions!$G$50) -> 7388.2587 | G43: =(G40*Assumptions!$G$50) -> 8748.2195 | H43: =(H40*Assumptions!$G$50) -> 10182.79 | I43: =(I40*Assumptions!$G$50) -> 11705.732 | J43: =(J40*Assumptions!$G$50) -> 13326.84 | ... AL43: =(AL40*Assumptions!$G$50) -> 180070.8
A44: Affiliate clicks | B44: aff_clicks | C44: =IF(AND((Assumptions!$G$6=1),(C$2>=Assumptions!$G$56)),((C36/1000)*Assumptions!$G$57),0) -> 0 | D44: =IF(AND((Assumptions!$G$6=1),(D$2>=Assumptions!$G$56)),((D36/1000)*Assumptions!$G$57),0) -> 0 | E44: =IF(AND((Assumptions!$G$6=1),(E$2>=Assumptions!$G$56)),((E36/1000)*Assumptions!$G$57),0) -> 0 | F44: =IF(AND((Assumptions!$G$6=1),(F$2>=Assumptions!$G$56)),((F36/1000)*Assumptions!$G$57),0) -> 0 | G44: =IF(AND((Assumptions!$G$6=1),(G$2>=Assumptions!$G$56)),((G36/1000)*Assumptions!$G$57),0) -> 0 | H44: =IF(AND((Assumptions!$G$6=1),(H$2>=Assumptions!$G$56)),((H36/1000)*Assumptions!$G$57),0) -> 0 | I44: =IF(AND((Assumptions!$G$6=1),(I$2>=Assumptions!$G$56)),((I36/1000)*Assumptions!$G$57),0) -> 82.179929 | J44: =IF(AND((Assumptions!$G$6=1),(J$2>=Assumptions!$G$56)),((J36/1000)*Assumptions!$G$57),0) -> 94.053948 | ... AL44: =IF(AND((Assumptions!$G$6=1),(AL$2>=Assumptions!$G$56)),((AL36/1000)*Assumptions!$G$57),0) -> 1302.4265
A45: Affiliate funded accounts | B45: aff_funded | C45: =(C44*Assumptions!$G$58) -> 0 | D45: =(D44*Assumptions!$G$58) -> 0 | E45: =(E44*Assumptions!$G$58) -> 0 | F45: =(F44*Assumptions!$G$58) -> 0 | G45: =(G44*Assumptions!$G$58) -> 0 | H45: =(H44*Assumptions!$G$58) -> 0 | I45: =(I44*Assumptions!$G$58) -> 4.9307957 | J45: =(J44*Assumptions!$G$58) -> 5.6432369 | ... AL45: =(AL44*Assumptions!$G$58) -> 78.14559
A46: Classroom Pro teachers | B46: teachers | C46: =IF(AND((Assumptions!$G$7=1),(C$2>=Assumptions!$G$61)),(Assumptions!$G$62+(Assumptions!$G$63*(C$2-Assumptions!$G$61))),0) -> 0 | D46: =IF(AND((Assumptions!$G$7=1),(D$2>=Assumptions!$G$61)),(Assumptions!$G$62+(Assumptions!$G$63*(D$2-Assumptions!$G$61))),0) -> 0 | E46: =IF(AND((Assumptions!$G$7=1),(E$2>=Assumptions!$G$61)),(Assumptions!$G$62+(Assumptions!$G$63*(E$2-Assumptions!$G$61))),0) -> 0 | F46: =IF(AND((Assumptions!$G$7=1),(F$2>=Assumptions!$G$61)),(Assumptions!$G$62+(Assumptions!$G$63*(F$2-Assumptions!$G$61))),0) -> 0 | G46: =IF(AND((Assumptions!$G$7=1),(G$2>=Assumptions!$G$61)),(Assumptions!$G$62+(Assumptions!$G$63*(G$2-Assumptions!$G$61))),0) -> 0 | H46: =IF(AND((Assumptions!$G$7=1),(H$2>=Assumptions!$G$61)),(Assumptions!$G$62+(Assumptions!$G$63*(H$2-Assumptions!$G$61))),0) -> 0 | I46: =IF(AND((Assumptions!$G$7=1),(I$2>=Assumptions!$G$61)),(Assumptions!$G$62+(Assumptions!$G$63*(I$2-Assumptions!$G$61))),0) -> 0 | J46: =IF(AND((Assumptions!$G$7=1),(J$2>=Assumptions!$G$61)),(Assumptions!$G$62+(Assumptions!$G$63*(J$2-Assumptions!$G$61))),0) -> 0 | ... AL46: =IF(AND((Assumptions!$G$7=1),(AL$2>=Assumptions!$G$61)),(Assumptions!$G$62+(Assumptions!$G$63*(AL$2-Assumptions!$G$61))),0) -> 0
A47: Campus / club licences | B47: campus | C47: =IF(AND((Assumptions!$G$7=1),(C$2>=Assumptions!$G$61)),(Assumptions!$G$65+(Assumptions!$G$66*(C$2-Assumptions!$G$61))),0) -> 0 | D47: =IF(AND((Assumptions!$G$7=1),(D$2>=Assumptions!$G$61)),(Assumptions!$G$65+(Assumptions!$G$66*(D$2-Assumptions!$G$61))),0) -> 0 | E47: =IF(AND((Assumptions!$G$7=1),(E$2>=Assumptions!$G$61)),(Assumptions!$G$65+(Assumptions!$G$66*(E$2-Assumptions!$G$61))),0) -> 0 | F47: =IF(AND((Assumptions!$G$7=1),(F$2>=Assumptions!$G$61)),(Assumptions!$G$65+(Assumptions!$G$66*(F$2-Assumptions!$G$61))),0) -> 0 | G47: =IF(AND((Assumptions!$G$7=1),(G$2>=Assumptions!$G$61)),(Assumptions!$G$65+(Assumptions!$G$66*(G$2-Assumptions!$G$61))),0) -> 0 | H47: =IF(AND((Assumptions!$G$7=1),(H$2>=Assumptions!$G$61)),(Assumptions!$G$65+(Assumptions!$G$66*(H$2-Assumptions!$G$61))),0) -> 0 | I47: =IF(AND((Assumptions!$G$7=1),(I$2>=Assumptions!$G$61)),(Assumptions!$G$65+(Assumptions!$G$66*(I$2-Assumptions!$G$61))),0) -> 0 | J47: =IF(AND((Assumptions!$G$7=1),(J$2>=Assumptions!$G$61)),(Assumptions!$G$65+(Assumptions!$G$66*(J$2-Assumptions!$G$61))),0) -> 0 | ... AL47: =IF(AND((Assumptions!$G$7=1),(AL$2>=Assumptions!$G$61)),(Assumptions!$G$65+(Assumptions!$G$66*(AL$2-Assumptions!$G$61))),0) -> 0
A48: Linking live (1 = yes) | B48: link_on | C48: =IF(AND((Assumptions!$G$9=1),(C$2>=Assumptions!$G$73)),1,0) -> 0 | D48: =IF(AND((Assumptions!$G$9=1),(D$2>=Assumptions!$G$73)),1,0) -> 0 | E48: =IF(AND((Assumptions!$G$9=1),(E$2>=Assumptions!$G$73)),1,0) -> 0 | F48: =IF(AND((Assumptions!$G$9=1),(F$2>=Assumptions!$G$73)),1,0) -> 0 | G48: =IF(AND((Assumptions!$G$9=1),(G$2>=Assumptions!$G$73)),1,0) -> 0 | H48: =IF(AND((Assumptions!$G$9=1),(H$2>=Assumptions!$G$73)),1,0) -> 0 | I48: =IF(AND((Assumptions!$G$9=1),(I$2>=Assumptions!$G$73)),1,0) -> 0 | J48: =IF(AND((Assumptions!$G$9=1),(J$2>=Assumptions!$G$73)),1,0) -> 0 | ... AL48: =IF(AND((Assumptions!$G$9=1),(AL$2>=Assumptions!$G$73)),1,0) -> 1
A49: Linked Items: free users (capped at 1 bank) | B49: items_free | C49: =((C48*C35)*Assumptions!$G$74) -> 0 | D49: =((D48*D35)*Assumptions!$G$74) -> 0 | E49: =((E48*E35)*Assumptions!$G$74) -> 0 | F49: =((F48*F35)*Assumptions!$G$74) -> 0 | G49: =((G48*G35)*Assumptions!$G$74) -> 0 | H49: =((H48*H35)*Assumptions!$G$74) -> 0 | I49: =((I48*I35)*Assumptions!$G$74) -> 0 | J49: =((J48*J35)*Assumptions!$G$74) -> 0 | ... AL49: =((AL48*AL35)*Assumptions!$G$74) -> 9003.54
A50: Linked Items: Pro users | B50: items_pro | C50: =(((C48*C29)*Assumptions!$G$76)*Assumptions!$G$77) -> 0 | D50: =(((D48*D29)*Assumptions!$G$76)*Assumptions!$G$77) -> 0 | E50: =(((E48*E29)*Assumptions!$G$76)*Assumptions!$G$77) -> 0 | F50: =(((F48*F29)*Assumptions!$G$76)*Assumptions!$G$77) -> 0 | G50: =(((G48*G29)*Assumptions!$G$76)*Assumptions!$G$77) -> 0 | H50: =(((H48*H29)*Assumptions!$G$76)*Assumptions!$G$77) -> 0 | I50: =(((I48*I29)*Assumptions!$G$76)*Assumptions!$G$77) -> 0 | J50: =(((J48*J29)*Assumptions!$G$76)*Assumptions!$G$77) -> 0 | ... AL50: =(((AL48*AL29)*Assumptions!$G$76)*Assumptions!$G$77) -> 26547.598
A52: REVENUE
A53: Gross: monthly plans | B53: rev_monthly | C53: =(C24*Assumptions!$G$35) -> 443.8539 | D53: =(D24*Assumptions!$G$35) -> 891.12868 | E53: =(E24*Assumptions!$G$35) -> 1336.1658 | F53: =(F24*Assumptions!$G$35) -> 1820.6996 | G53: =(G24*Assumptions!$G$35) -> 2310.6893 | H53: =(H24*Assumptions!$G$35) -> 2809.6248 | I53: =(I24*Assumptions!$G$35) -> 3321.8004 | J53: =(J24*Assumptions!$G$35) -> 3851.532 | ... AL53: =(AL24*Assumptions!$G$35) -> 52236.198
A54: Gross: annual plans (recognised 1/12 a month) | B54: rev_annual | C54: =((C26*Assumptions!$G$36)/12) -> 452.32976 | D54: =((D26*Assumptions!$G$36)/12) -> 957.49549 | E54: =((E26*Assumptions!$G$36)/12) -> 1510.111 | F54: =((F26*Assumptions!$G$36)/12) -> 2152.4586 | G54: =((G26*Assumptions!$G$36)/12) -> 2854.2391 | H54: =((H26*Assumptions!$G$36)/12) -> 3619.6156 | I54: =((I26*Assumptions!$G$36)/12) -> 4453.959 | J54: =((J26*Assumptions!$G$36)/12) -> 5363.1396 | ... AL54: =((AL26*Assumptions!$G$36)/12) -> 93778.753
A55: Gross: student plans (recognised 1/12 a month) | B55: rev_student | C55: =((C28*Assumptions!$G$37)/12) -> 49.337663 | D55: =((D28*Assumptions!$G$37)/12) -> 104.43838 | E55: =((E28*Assumptions!$G$37)/12) -> 164.71467 | F55: =((F28*Assumptions!$G$37)/12) -> 234.77844 | G55: =((G28*Assumptions!$G$37)/12) -> 311.32483 | H55: =((H28*Assumptions!$G$37)/12) -> 394.80792 | I55: =((I28*Assumptions!$G$37)/12) -> 485.81355 | J55: =((J28*Assumptions!$G$37)/12) -> 584.98201 | ... AL55: =((AL28*Assumptions!$G$37)/12) -> 9861.1557
A56: Gross: Recruiting Pass | B56: rev_pass | C56: =(C21*Assumptions!$G$38) -> 690.9 | D56: =(D21*Assumptions!$G$38) -> 771.603 | E56: =(E21*Assumptions!$G$38) -> 844.07896 | F56: =(F21*Assumptions!$G$38) -> 981.13819 | G56: =(G21*Assumptions!$G$38) -> 1071.9174 | H56: =(H21*Assumptions!$G$38) -> 1169.0555 | I56: =(I21*Assumptions!$G$38) -> 1274.3974 | J56: =(J21*Assumptions!$G$38) -> 1388.7057 | ... AL56: =(AL21*Assumptions!$G$38) -> 14736.163
A57: Gross in-app sales | B57: rev_iap_gross | C57: =(((C53+C54)+C55)+C56) -> 1636.4213 | D57: =(((D53+D54)+D55)+D56) -> 2724.6656 | E57: =(((E53+E54)+E55)+E56) -> 3855.0704 | F57: =(((F53+F54)+F55)+F56) -> 5189.0749 | G57: =(((G53+G54)+G55)+G56) -> 6548.1707 | H57: =(((H53+H54)+H55)+H56) -> 7993.1038 | I57: =(((I53+I54)+I55)+I56) -> 9535.9704 | J57: =(((J53+J54)+J55)+J56) -> 11188.359 | ... AL57: =(((AL53+AL54)+AL55)+AL56) -> 170612.27
A58: Less: refunds | B58: refunds | C58: =((-C57)*Assumptions!$G$40) -> -24.54632 | D58: =((-D57)*Assumptions!$G$40) -> -40.869983 | E58: =((-E57)*Assumptions!$G$40) -> -57.826057 | F58: =((-F57)*Assumptions!$G$40) -> -77.836124 | G58: =((-G57)*Assumptions!$G$40) -> -98.22256 | H58: =((-H57)*Assumptions!$G$40) -> -119.89656 | I58: =((-I57)*Assumptions!$G$40) -> -143.03956 | J58: =((-J57)*Assumptions!$G$40) -> -167.82539 | ... AL58: =((-AL57)*Assumptions!$G$40) -> -2559.1841
A59: Less: app store commission | B59: store_fee | C59: =((-(C57+C58))*Assumptions!$G$39) -> -241.78125 | D59: =((-(D57+D58))*Assumptions!$G$39) -> -402.56934 | E59: =((-(E57+E58))*Assumptions!$G$39) -> -569.58666 | F59: =((-(F57+F58))*Assumptions!$G$39) -> -766.68582 | G59: =((-(G57+G58))*Assumptions!$G$39) -> -967.49221 | H59: =((-(H57+H58))*Assumptions!$G$39) -> -1180.9811 | I59: =((-(I57+I58))*Assumptions!$G$39) -> -1408.9396 | J59: =((-(J57+J58))*Assumptions!$G$39) -> -1653.0801 | ... AL59: =((-(AL57+AL58))*Assumptions!$G$39) -> -25207.963
A60: Subscriptions & in-app, net of store fee | B60: rev_subs_net | C60: =((C57+C58)+C59) -> 1370.0938 | D60: =((D57+D58)+D59) -> 2281.2262 | E60: =((E57+E58)+E59) -> 3227.6577 | F60: =((F57+F58)+F59) -> 4344.553 | G60: =((G57+G58)+G59) -> 5482.4559 | H60: =((H57+H58)+H59) -> 6692.2261 | I60: =((I57+I58)+I59) -> 7983.9912 | J60: =((J57+J58)+J59) -> 9367.4538 | ... AL60: =((AL57+AL58)+AL59) -> 142845.12
A61: Ads: article / lesson end | B61: rev_ads_article | C61: =(((C41/1000)*Assumptions!$G$51)*Assumptions!$G$54) -> 0 | D61: =(((D41/1000)*Assumptions!$G$51)*Assumptions!$G$54) -> 0 | E61: =(((E41/1000)*Assumptions!$G$51)*Assumptions!$G$54) -> 0 | F61: =(((F41/1000)*Assumptions!$G$51)*Assumptions!$G$54) -> 168.4523 | G61: =(((G41/1000)*Assumptions!$G$51)*Assumptions!$G$54) -> 199.4594 | H61: =(((H41/1000)*Assumptions!$G$51)*Assumptions!$G$54) -> 232.16762 | I61: =(((I41/1000)*Assumptions!$G$51)*Assumptions!$G$54) -> 266.8907 | J61: =(((J41/1000)*Assumptions!$G$51)*Assumptions!$G$54) -> 303.85195 | ... AL61: =(((AL41/1000)*Assumptions!$G$51)*Assumptions!$G$54) -> 4105.6143
A62: Ads: screener native | B62: rev_ads_screener | C62: =(((C42/1000)*Assumptions!$G$52)*Assumptions!$G$54) -> 0 | D62: =(((D42/1000)*Assumptions!$G$52)*Assumptions!$G$54) -> 0 | E62: =(((E42/1000)*Assumptions!$G$52)*Assumptions!$G$54) -> 0 | F62: =(((F42/1000)*Assumptions!$G$52)*Assumptions!$G$54) -> 105.28269 | G62: =(((G42/1000)*Assumptions!$G$52)*Assumptions!$G$54) -> 124.66213 | H62: =(((H42/1000)*Assumptions!$G$52)*Assumptions!$G$54) -> 145.10476 | I62: =(((I42/1000)*Assumptions!$G$52)*Assumptions!$G$54) -> 166.80669 | J62: =(((J42/1000)*Assumptions!$G$52)*Assumptions!$G$54) -> 189.90747 | ... AL62: =(((AL42/1000)*Assumptions!$G$52)*Assumptions!$G$54) -> 2566.0089
A63: Ads: opt-in rewarded | B63: rev_ads_rewarded | C63: =(((C43/1000)*Assumptions!$G$53)*Assumptions!$G$54) -> 0 | D63: =(((D43/1000)*Assumptions!$G$53)*Assumptions!$G$54) -> 0 | E63: =(((E43/1000)*Assumptions!$G$53)*Assumptions!$G$54) -> 0 | F63: =(((F43/1000)*Assumptions!$G$53)*Assumptions!$G$54) -> 126.33922 | G63: =(((G43/1000)*Assumptions!$G$53)*Assumptions!$G$54) -> 149.59455 | H63: =(((H43/1000)*Assumptions!$G$53)*Assumptions!$G$54) -> 174.12571 | I63: =(((I43/1000)*Assumptions!$G$53)*Assumptions!$G$54) -> 200.16802 | J63: =(((J43/1000)*Assumptions!$G$53)*Assumptions!$G$54) -> 227.88897 | ... AL63: =(((AL43/1000)*Assumptions!$G$53)*Assumptions!$G$54) -> 3079.2107
A64: Advertising revenue | B64: rev_ads | C64: =((C61+C62)+C63) -> 0 | D64: =((D61+D62)+D63) -> 0 | E64: =((E61+E62)+E63) -> 0 | F64: =((F61+F62)+F63) -> 400.07421 | G64: =((G61+G62)+G63) -> 473.71609 | H64: =((H61+H62)+H63) -> 551.39809 | I64: =((I61+I62)+I63) -> 633.86541 | J64: =((J61+J62)+J63) -> 721.64839 | ... AL64: =((AL61+AL62)+AL63) -> 9750.8339
A65: Affiliate revenue | B65: rev_aff | C65: =(C45*Assumptions!$G$59) -> 0 | D65: =(D45*Assumptions!$G$59) -> 0 | E65: =(E45*Assumptions!$G$59) -> 0 | F65: =(F45*Assumptions!$G$59) -> 0 | G65: =(G45*Assumptions!$G$59) -> 0 | H65: =(H45*Assumptions!$G$59) -> 0 | I65: =(I45*Assumptions!$G$59) -> 369.80968 | J65: =(J45*Assumptions!$G$59) -> 423.24276 | ... AL65: =(AL45*Assumptions!$G$59) -> 5860.9192
A66: B2B / Edu licence revenue | B66: rev_b2b | C66: =(((C46*Assumptions!$G$64)/12)+((C47*Assumptions!$G$67)/12)) -> 0 | D66: =(((D46*Assumptions!$G$64)/12)+((D47*Assumptions!$G$67)/12)) -> 0 | E66: =(((E46*Assumptions!$G$64)/12)+((E47*Assumptions!$G$67)/12)) -> 0 | F66: =(((F46*Assumptions!$G$64)/12)+((F47*Assumptions!$G$67)/12)) -> 0 | G66: =(((G46*Assumptions!$G$64)/12)+((G47*Assumptions!$G$67)/12)) -> 0 | H66: =(((H46*Assumptions!$G$64)/12)+((H47*Assumptions!$G$67)/12)) -> 0 | I66: =(((I46*Assumptions!$G$64)/12)+((I47*Assumptions!$G$67)/12)) -> 0 | J66: =(((J46*Assumptions!$G$64)/12)+((J47*Assumptions!$G$67)/12)) -> 0 | ... AL66: =(((AL46*Assumptions!$G$64)/12)+((AL47*Assumptions!$G$67)/12)) -> 0
A67: TOTAL REVENUE | B67: rev_total | C67: =(((C60+C64)+C65)+C66) -> 1370.0938 | D67: =(((D60+D64)+D65)+D66) -> 2281.2262 | E67: =(((E60+E64)+E65)+E66) -> 3227.6577 | F67: =(((F60+F64)+F65)+F66) -> 4744.6272 | G67: =(((G60+G64)+G65)+G66) -> 5956.172 | H67: =(((H60+H64)+H65)+H66) -> 7243.6242 | I67: =(((I60+I64)+I65)+I66) -> 8987.6663 | J67: =(((J60+J64)+J65)+J66) -> 10512.345 | ... AL67: =(((AL60+AL64)+AL65)+AL66) -> 158456.88
A69: COST OF REVENUE (COGS)
A70: Data licensing (beta, or scale phase above MAU threshold) | B70: cogs_data | C70: =IF((C36>=Assumptions!$G$72),Assumptions!$G$71,Assumptions!$G$70) -> 350 | D70: =IF((D36>=Assumptions!$G$72),Assumptions!$G$71,Assumptions!$G$70) -> 350 | E70: =IF((E36>=Assumptions!$G$72),Assumptions!$G$71,Assumptions!$G$70) -> 350 | F70: =IF((F36>=Assumptions!$G$72),Assumptions!$G$71,Assumptions!$G$70) -> 350 | G70: =IF((G36>=Assumptions!$G$72),Assumptions!$G$71,Assumptions!$G$70) -> 350 | H70: =IF((H36>=Assumptions!$G$72),Assumptions!$G$71,Assumptions!$G$70) -> 350 | I70: =IF((I36>=Assumptions!$G$72),Assumptions!$G$71,Assumptions!$G$70) -> 350 | J70: =IF((J36>=Assumptions!$G$72),Assumptions!$G$71,Assumptions!$G$70) -> 350 | ... AL70: =IF((AL36>=Assumptions!$G$72),Assumptions!$G$71,Assumptions!$G$70) -> 2500
A71: Plaid / aggregation | B71: cogs_plaid | C71: =(((C49*Assumptions!$G$75)+(C50*Assumptions!$G$78))+(C48*Assumptions!$G$79)) -> 0 | D71: =(((D49*Assumptions!$G$75)+(D50*Assumptions!$G$78))+(D48*Assumptions!$G$79)) -> 0 | E71: =(((E49*Assumptions!$G$75)+(E50*Assumptions!$G$78))+(E48*Assumptions!$G$79)) -> 0 | F71: =(((F49*Assumptions!$G$75)+(F50*Assumptions!$G$78))+(F48*Assumptions!$G$79)) -> 0 | G71: =(((G49*Assumptions!$G$75)+(G50*Assumptions!$G$78))+(G48*Assumptions!$G$79)) -> 0 | H71: =(((H49*Assumptions!$G$75)+(H50*Assumptions!$G$78))+(H48*Assumptions!$G$79)) -> 0 | I71: =(((I49*Assumptions!$G$75)+(I50*Assumptions!$G$78))+(I48*Assumptions!$G$79)) -> 0 | J71: =(((J49*Assumptions!$G$75)+(J50*Assumptions!$G$78))+(J48*Assumptions!$G$79)) -> 0 | ... AL71: =(((AL49*Assumptions!$G$75)+(AL50*Assumptions!$G$78))+(AL48*Assumptions!$G$79)) -> 17402.241
A72: Hosting / Supabase / Expo | B72: cogs_hosting | C72: =(Assumptions!$G$80+(Assumptions!$G$81*C36)) -> 73.5 | D72: =(Assumptions!$G$80+(Assumptions!$G$81*D36)) -> 81.702295 | E72: =(Assumptions!$G$80+(Assumptions!$G$81*E36)) -> 89.963281 | F72: =(Assumptions!$G$80+(Assumptions!$G$81*F36)) -> 100.67895 | G72: =(Assumptions!$G$80+(Assumptions!$G$81*G36)) -> 110.5775 | H72: =(Assumptions!$G$80+(Assumptions!$G$81*H36)) -> 121.04546 | I72: =(Assumptions!$G$80+(Assumptions!$G$81*I36)) -> 132.17993 | J72: =(Assumptions!$G$80+(Assumptions!$G$81*J36)) -> 144.05395 | ... AL72: =(Assumptions!$G$80+(Assumptions!$G$81*AL36)) -> 1352.4265
A73: LLM tutor tokens | B73: cogs_llm | C73: =IF(AND((Assumptions!$G$8=1),(C$2>=Assumptions!$G$82)),((C29*Assumptions!$G$83)+(C35*Assumptions!$G$84)),0) -> 0 | D73: =IF(AND((Assumptions!$G$8=1),(D$2>=Assumptions!$G$82)),((D29*Assumptions!$G$83)+(D35*Assumptions!$G$84)),0) -> 0 | E73: =IF(AND((Assumptions!$G$8=1),(E$2>=Assumptions!$G$82)),((E29*Assumptions!$G$83)+(E35*Assumptions!$G$84)),0) -> 0 | F73: =IF(AND((Assumptions!$G$8=1),(F$2>=Assumptions!$G$82)),((F29*Assumptions!$G$83)+(F35*Assumptions!$G$84)),0) -> 0 | G73: =IF(AND((Assumptions!$G$8=1),(G$2>=Assumptions!$G$82)),((G29*Assumptions!$G$83)+(G35*Assumptions!$G$84)),0) -> 0 | H73: =IF(AND((Assumptions!$G$8=1),(H$2>=Assumptions!$G$82)),((H29*Assumptions!$G$83)+(H35*Assumptions!$G$84)),0) -> 0 | I73: =IF(AND((Assumptions!$G$8=1),(I$2>=Assumptions!$G$82)),((I29*Assumptions!$G$83)+(I35*Assumptions!$G$84)),0) -> 343.73387 | J73: =IF(AND((Assumptions!$G$8=1),(J$2>=Assumptions!$G$82)),((J29*Assumptions!$G$83)+(J35*Assumptions!$G$84)),0) -> 406.12866 | ... AL73: =IF(AND((Assumptions!$G$8=1),(AL$2>=Assumptions!$G$82)),((AL29*Assumptions!$G$83)+(AL35*Assumptions!$G$84)),0) -> 6434.9621
A74: RevenueCat (1% of MTR above $2.5k) | B74: cogs_rc | C74: =(MAX(0,(C30-Assumptions!$G$85))*Assumptions!$G$86) -> 46.54763 | D74: =(MAX(0,(D30-Assumptions!$G$85))*Assumptions!$G$86) -> 58.859291 | E74: =(MAX(0,(E30-Assumptions!$G$85))*Assumptions!$G$86) -> 70.34946 | F74: =(MAX(0,(F30-Assumptions!$G$85))*Assumptions!$G$86) -> 88.507753 | G74: =(MAX(0,(G30-Assumptions!$G$85))*Assumptions!$G$86) -> 102.22529 | H74: =(MAX(0,(H30-Assumptions!$G$85))*Assumptions!$G$86) -> 116.64995 | I74: =(MAX(0,(I30-Assumptions!$G$85))*Assumptions!$G$86) -> 132.00386 | J74: =(MAX(0,(J30-Assumptions!$G$85))*Assumptions!$G$86) -> 148.40427 | ... AL74: =(MAX(0,(AL30-Assumptions!$G$85))*Assumptions!$G$86) -> 2225.1533
A75: B2B card processing | B75: cogs_b2b | C75: =(C66*Assumptions!$G$68) -> 0 | D75: =(D66*Assumptions!$G$68) -> 0 | E75: =(E66*Assumptions!$G$68) -> 0 | F75: =(F66*Assumptions!$G$68) -> 0 | G75: =(G66*Assumptions!$G$68) -> 0 | H75: =(H66*Assumptions!$G$68) -> 0 | I75: =(I66*Assumptions!$G$68) -> 0 | J75: =(J66*Assumptions!$G$68) -> 0 | ... AL75: =(AL66*Assumptions!$G$68) -> 0
A76: Total COGS | B76: cogs_total | C76: =(((((C70+C71)+C72)+C73)+C74)+C75) -> 470.04763 | D76: =(((((D70+D71)+D72)+D73)+D74)+D75) -> 490.56159 | E76: =(((((E70+E71)+E72)+E73)+E74)+E75) -> 510.31274 | F76: =(((((F70+F71)+F72)+F73)+F74)+F75) -> 539.1867 | G76: =(((((G70+G71)+G72)+G73)+G74)+G75) -> 562.80279 | H76: =(((((H70+H71)+H72)+H73)+H74)+H75) -> 587.69541 | I76: =(((((I70+I71)+I72)+I73)+I74)+I75) -> 957.91766 | J76: =(((((J70+J71)+J72)+J73)+J74)+J75) -> 1048.5869 | ... AL76: =(((((AL70+AL71)+AL72)+AL73)+AL74)+AL75) -> 29914.783
A77: GROSS PROFIT | B77: gross_profit | C77: =(C67-C76) -> 900.04612 | D77: =(D67-D76) -> 1790.6647 | E77: =(E67-E76) -> 2717.345 | F77: =(F67-F76) -> 4205.4405 | G77: =(G67-G76) -> 5393.3692 | H77: =(H67-H76) -> 6655.9288 | I77: =(I67-I76) -> 8029.7486 | J77: =(J67-J76) -> 9463.7581 | ... AL77: =(AL67-AL76) -> 128542.09
A78: Gross margin | B78: gross_margin | C78: =IF(C67=0,0,C77/C67) -> 0.65692302 | D78: =IF(D67=0,0,D77/D67) -> 0.78495706 | E78: =IF(E67=0,0,E77/E67) -> 0.84189379 | F78: =IF(F67=0,0,F77/F67) -> 0.88635847 | G78: =IF(G67=0,0,G77/G67) -> 0.90550931 | H78: =IF(H67=0,0,H77/H67) -> 0.91886721 | I78: =IF(I67=0,0,I77/I67) -> 0.89341864 | J78: =IF(J67=0,0,J77/J67) -> 0.90025186 | ... AL78: =IF(AL67=0,0,AL77/AL67) -> 0.81121184
A80: OPERATING EXPENSES
A81: Founder salary | B81: opex_founder | C81: =(Assumptions!$G$10*Assumptions!$G$88) -> 0 | D81: =(Assumptions!$G$10*Assumptions!$G$88) -> 0 | E81: =(Assumptions!$G$10*Assumptions!$G$88) -> 0 | F81: =(Assumptions!$G$10*Assumptions!$G$88) -> 0 | G81: =(Assumptions!$G$10*Assumptions!$G$88) -> 0 | H81: =(Assumptions!$G$10*Assumptions!$G$88) -> 0 | I81: =(Assumptions!$G$10*Assumptions!$G$88) -> 0 | J81: =(Assumptions!$G$10*Assumptions!$G$88) -> 0 | ... AL81: =(Assumptions!$G$10*Assumptions!$G$88) -> 0
A82: Contractors | B82: opex_contractors | C82: =CHOOSE(C$3,Assumptions!$G$89,Assumptions!$G$90,Assumptions!$G$91) -> 1000 | D82: =CHOOSE(D$3,Assumptions!$G$89,Assumptions!$G$90,Assumptions!$G$91) -> 1000 | E82: =CHOOSE(E$3,Assumptions!$G$89,Assumptions!$G$90,Assumptions!$G$91) -> 1000 | F82: =CHOOSE(F$3,Assumptions!$G$89,Assumptions!$G$90,Assumptions!$G$91) -> 1000 | G82: =CHOOSE(G$3,Assumptions!$G$89,Assumptions!$G$90,Assumptions!$G$91) -> 1000 | H82: =CHOOSE(H$3,Assumptions!$G$89,Assumptions!$G$90,Assumptions!$G$91) -> 1000 | I82: =CHOOSE(I$3,Assumptions!$G$89,Assumptions!$G$90,Assumptions!$G$91) -> 1000 | J82: =CHOOSE(J$3,Assumptions!$G$89,Assumptions!$G$90,Assumptions!$G$91) -> 1000 | ... AL82: =CHOOSE(AL$3,Assumptions!$G$89,Assumptions!$G$90,Assumptions!$G$91) -> 6000
A83: Marketing: Apple Search Ads | B83: opex_asa | C83: =C10 -> 1000 | D83: =D10 -> 1060 | E83: =E10 -> 1123.6 | F83: =F10 -> 1191.016 | G83: =G10 -> 1262.477 | H83: =H10 -> 1338.2256 | I83: =I10 -> 1418.5191 | J83: =J10 -> 1503.6303 | ... AL83: =AL10 -> 7686.0868
A84: Marketing: creators | B84: opex_creators | C84: =C8 -> 0 | D84: =D8 -> 0 | E84: =E8 -> 0 | F84: =F8 -> 1000 | G84: =G8 -> 1070 | H84: =H8 -> 1144.9 | I84: =I8 -> 1225.043 | J84: =J8 -> 1310.796 | ... AL84: =AL8 -> 8715.2708
A85: Marketing: other | B85: opex_mkt_other | C85: =Assumptions!$G$92 -> 150 | D85: =Assumptions!$G$92 -> 150 | E85: =Assumptions!$G$92 -> 150 | F85: =Assumptions!$G$92 -> 150 | G85: =Assumptions!$G$92 -> 150 | H85: =Assumptions!$G$92 -> 150 | I85: =Assumptions!$G$92 -> 150 | J85: =Assumptions!$G$92 -> 150 | ... AL85: =Assumptions!$G$92 -> 150
A86: Legal & compliance | B86: opex_legal | C86: =(((IF((C$2=1),(((Assumptions!$G$93+Assumptions!$G$94)+Assumptions!$G$95)+Assumptions!$G$96),0)+Assumptions!$G$97)+IF(AND((C$2>1),(MOD((C$2-1),12)=0)),Assumptions!$G$98,0))+IF(AND((Assumptions!$G$11=1),(C$2>=Assumptions!$G$99)),Assumptions!$G$100,0)) -> 3800 | D86: =(((IF((D$2=1),(((Assumptions!$G$93+Assumptions!$G$94)+Assumptions!$G$95)+Assumptions!$G$96),0)+Assumptions!$G$97)+IF(AND((D$2>1),(MOD((D$2-1),12)=0)),Assumptions!$G$98,0))+IF(AND((Assumptions!$G$11=1),(D$2>=Assumptions!$G$99)),Assumptions!$G$100,0)) -> 100 | E86: =(((IF((E$2=1),(((Assumptions!$G$93+Assumptions!$G$94)+Assumptions!$G$95)+Assumptions!$G$96),0)+Assumptions!$G$97)+IF(AND((E$2>1),(MOD((E$2-1),12)=0)),Assumptions!$G$98,0))+IF(AND((Assumptions!$G$11=1),(E$2>=Assumptions!$G$99)),Assumptions!$G$100,0)) -> 100 | F86: =(((IF((F$2=1),(((Assumptions!$G$93+Assumptions!$G$94)+Assumptions!$G$95)+Assumptions!$G$96),0)+Assumptions!$G$97)+IF(AND((F$2>1),(MOD((F$2-1),12)=0)),Assumptions!$G$98,0))+IF(AND((Assumptions!$G$11=1),(F$2>=Assumptions!$G$99)),Assumptions!$G$100,0)) -> 100 | G86: =(((IF((G$2=1),(((Assumptions!$G$93+Assumptions!$G$94)+Assumptions!$G$95)+Assumptions!$G$96),0)+Assumptions!$G$97)+IF(AND((G$2>1),(MOD((G$2-1),12)=0)),Assumptions!$G$98,0))+IF(AND((Assumptions!$G$11=1),(G$2>=Assumptions!$G$99)),Assumptions!$G$100,0)) -> 100 | H86: =(((IF((H$2=1),(((Assumptions!$G$93+Assumptions!$G$94)+Assumptions!$G$95)+Assumptions!$G$96),0)+Assumptions!$G$97)+IF(AND((H$2>1),(MOD((H$2-1),12)=0)),Assumptions!$G$98,0))+IF(AND((Assumptions!$G$11=1),(H$2>=Assumptions!$G$99)),Assumptions!$G$100,0)) -> 100 | I86: =(((IF((I$2=1),(((Assumptions!$G$93+Assumptions!$G$94)+Assumptions!$G$95)+Assumptions!$G$96),0)+Assumptions!$G$97)+IF(AND((I$2>1),(MOD((I$2-1),12)=0)),Assumptions!$G$98,0))+IF(AND((Assumptions!$G$11=1),(I$2>=Assumptions!$G$99)),Assumptions!$G$100,0)) -> 100 | J86: =(((IF((J$2=1),(((Assumptions!$G$93+Assumptions!$G$94)+Assumptions!$G$95)+Assumptions!$G$96),0)+Assumptions!$G$97)+IF(AND((J$2>1),(MOD((J$2-1),12)=0)),Assumptions!$G$98,0))+IF(AND((Assumptions!$G$11=1),(J$2>=Assumptions!$G$99)),Assumptions!$G$100,0)) -> 100 | ... AL86: =(((IF((AL$2=1),(((Assumptions!$G$93+Assumptions!$G$94)+Assumptions!$G$95)+Assumptions!$G$96),0)+Assumptions!$G$97)+IF(AND((AL$2>1),(MOD((AL$2-1),12)=0)),Assumptions!$G$98,0))+IF(AND((Assumptions!$G$11=1),(AL$2>=Assumptions!$G$99)),Assumptions!$G$100,0)) -> 100
A87: Software / tools | B87: opex_tools | C87: =CHOOSE(C$3,Assumptions!$G$101,Assumptions!$G$102,Assumptions!$G$103) -> 150 | D87: =CHOOSE(D$3,Assumptions!$G$101,Assumptions!$G$102,Assumptions!$G$103) -> 150 | E87: =CHOOSE(E$3,Assumptions!$G$101,Assumptions!$G$102,Assumptions!$G$103) -> 150 | F87: =CHOOSE(F$3,Assumptions!$G$101,Assumptions!$G$102,Assumptions!$G$103) -> 150 | G87: =CHOOSE(G$3,Assumptions!$G$101,Assumptions!$G$102,Assumptions!$G$103) -> 150 | H87: =CHOOSE(H$3,Assumptions!$G$101,Assumptions!$G$102,Assumptions!$G$103) -> 150 | I87: =CHOOSE(I$3,Assumptions!$G$101,Assumptions!$G$102,Assumptions!$G$103) -> 150 | J87: =CHOOSE(J$3,Assumptions!$G$101,Assumptions!$G$102,Assumptions!$G$103) -> 150 | ... AL87: =CHOOSE(AL$3,Assumptions!$G$101,Assumptions!$G$102,Assumptions!$G$103) -> 400
A88: Apple / Google developer fees | B88: opex_stores | C88: =(IF((MOD((C$2-1),12)=0),Assumptions!$G$104,0)+IF((C$2=1),Assumptions!$G$105,0)) -> 124 | D88: =(IF((MOD((D$2-1),12)=0),Assumptions!$G$104,0)+IF((D$2=1),Assumptions!$G$105,0)) -> 0 | E88: =(IF((MOD((E$2-1),12)=0),Assumptions!$G$104,0)+IF((E$2=1),Assumptions!$G$105,0)) -> 0 | F88: =(IF((MOD((F$2-1),12)=0),Assumptions!$G$104,0)+IF((F$2=1),Assumptions!$G$105,0)) -> 0 | G88: =(IF((MOD((G$2-1),12)=0),Assumptions!$G$104,0)+IF((G$2=1),Assumptions!$G$105,0)) -> 0 | H88: =(IF((MOD((H$2-1),12)=0),Assumptions!$G$104,0)+IF((H$2=1),Assumptions!$G$105,0)) -> 0 | I88: =(IF((MOD((I$2-1),12)=0),Assumptions!$G$104,0)+IF((I$2=1),Assumptions!$G$105,0)) -> 0 | J88: =(IF((MOD((J$2-1),12)=0),Assumptions!$G$104,0)+IF((J$2=1),Assumptions!$G$105,0)) -> 0 | ... AL88: =(IF((MOD((AL$2-1),12)=0),Assumptions!$G$104,0)+IF((AL$2=1),Assumptions!$G$105,0)) -> 0
A89: Insurance | B89: opex_insurance | C89: =Assumptions!$G$106 -> 100 | D89: =Assumptions!$G$106 -> 100 | E89: =Assumptions!$G$106 -> 100 | F89: =Assumptions!$G$106 -> 100 | G89: =Assumptions!$G$106 -> 100 | H89: =Assumptions!$G$106 -> 100 | I89: =Assumptions!$G$106 -> 100 | J89: =Assumptions!$G$106 -> 100 | ... AL89: =Assumptions!$G$106 -> 100
A90: Total operating expenses | B90: opex_total | C90: =((((((((C81+C82)+C83)+C84)+C85)+C86)+C87)+C88)+C89) -> 6324 | D90: =((((((((D81+D82)+D83)+D84)+D85)+D86)+D87)+D88)+D89) -> 2560 | E90: =((((((((E81+E82)+E83)+E84)+E85)+E86)+E87)+E88)+E89) -> 2623.6 | F90: =((((((((F81+F82)+F83)+F84)+F85)+F86)+F87)+F88)+F89) -> 3691.016 | G90: =((((((((G81+G82)+G83)+G84)+G85)+G86)+G87)+G88)+G89) -> 3832.477 | H90: =((((((((H81+H82)+H83)+H84)+H85)+H86)+H87)+H88)+H89) -> 3983.1256 | I90: =((((((((I81+I82)+I83)+I84)+I85)+I86)+I87)+I88)+I89) -> 4143.5621 | J90: =((((((((J81+J82)+J83)+J84)+J85)+J86)+J87)+J88)+J89) -> 4314.4263 | ... AL90: =((((((((AL81+AL82)+AL83)+AL84)+AL85)+AL86)+AL87)+AL88)+AL89) -> 23151.358
A91: OPERATING INCOME (EBIT) | B91: ebit | C91: =(C77-C90) -> -5423.9539 | D91: =(D77-D90) -> -769.33535 | E91: =(E77-E90) -> 93.744992 | F91: =(F77-F90) -> 514.4245 | G91: =(G77-G90) -> 1560.8922 | H91: =(H77-H90) -> 2672.8032 | I91: =(I77-I90) -> 3886.1865 | J91: =(J77-J90) -> 5149.3318 | ... AL91: =(AL77-AL90) -> 105390.74
A92: Operating margin | B92: ebit_margin | C92: =IF(C67=0,0,C91/C67) -> -3.9588195 | D92: =IF(D67=0,0,D91/D67) -> -0.3372464 | E92: =IF(E67=0,0,E91/E67) -> 0.029044279 | F92: =IF(F67=0,0,F91/F67) -> 0.10842253 | G92: =IF(G67=0,0,G91/G67) -> 0.26206299 | H92: =IF(H67=0,0,H91/H67) -> 0.36898701 | I92: =IF(I67=0,0,I91/I67) -> 0.43239105 | J92: =IF(J67=0,0,J91/J67) -> 0.48983665 | ... AL92: =IF(AL67=0,0,AL91/AL67) -> 0.66510674
A94: CASH
A95: In-app billings net of refunds & store fee | B95: bill_net | C95: =(C30*Assumptions!$G$112) -> 5990.3253 | D95: =(D30*Assumptions!$G$112) -> 7021.1191 | E95: =(E30*Assumptions!$G$112) -> 7983.1335 | F95: =(F30*Assumptions!$G$112) -> 9503.4366 | G95: =(G30*Assumptions!$G$112) -> 10651.937 | H95: =(H30*Assumptions!$G$112) -> 11859.642 | I95: =(I30*Assumptions!$G$112) -> 13145.149 | J95: =(J30*Assumptions!$G$112) -> 14518.273 | ... AL95: =(AL30*Assumptions!$G$112) -> 188394.08
A96: Change in deferred revenue (annual plans paid upfront) | B96: deferred_chg | C96: =(C95-C60) -> 4620.2316 | D96: =(D95-D60) -> 4739.8929 | E96: =(E95-E60) -> 4755.4758 | F96: =(F95-F60) -> 5158.8836 | G96: =(G95-G60) -> 5169.4816 | H96: =(H95-H60) -> 5167.4157 | I96: =(I95-I60) -> 5161.1573 | J96: =(J95-J60) -> 5150.8187 | ... AL96: =(AL95-AL60) -> 45548.96
A97: Operating cash flow | B97: cash_flow | C97: =(C91+C96) -> -803.72231 | D97: =(D91+D96) -> 3970.5575 | E97: =(E91+E96) -> 4849.2208 | F97: =(F91+F96) -> 5673.3081 | G97: =(G91+G96) -> 6730.3738 | H97: =(H91+H96) -> 7840.2189 | I97: =(I91+I96) -> 9047.3438 | J97: =(J91+J96) -> 10300.151 | ... AL97: =(AL91+AL96) -> 150939.7
A98: Cumulative cash (from $0 at launch) | B98: cash_cum | C98: =(0+C97) -> -803.72231 | D98: =(C98+D97) -> 3166.8352 | E98: =(D98+E97) -> 8016.056 | F98: =(E98+F97) -> 13689.364 | G98: =(F98+G97) -> 20419.738 | H98: =(G98+H97) -> 28259.957 | I98: =(H98+I97) -> 37307.301 | J98: =(I98+J97) -> 47607.451 | K98: =(J98+K97) -> 59249.817 | ... AL98: =(AK98+AL97) -> 1632362.9
A99: Cumulative operating income | B99: ebit_cum | C99: =(0+C91) -> -5423.9539 | D99: =(C99+D91) -> -6193.2892 | E99: =(D99+E91) -> -6099.5442 | F99: =(E99+F91) -> -5585.1197 | G99: =(F99+G91) -> -4024.2275 | H99: =(G99+H91) -> -1351.4243 | I99: =(H99+I91) -> 2534.7622 | J99: =(I99+J91) -> 7684.094 | K99: =(J99+K91) -> 14190.153 | ... AL99: =(AK99+AL91) -> 1069272.8
A101: KPIs
A102: ARPU: total revenue / MAU | B102: arpu | C102: =IF(C36=0,0,C67/C36) -> 0.58301862 | D102: =IF(D36=0,0,D67/D36) -> 0.71957763 | E102: =IF(E36=0,0,E67/E36) -> 0.80765584 | F102: =IF(F36=0,0,F67/F36) -> 0.93621268 | G102: =IF(G36=0,0,G67/G36) -> 0.98323178 | H102: =IF(H36=0,0,H67/H36) -> 1.0195759 | I102: =IF(I36=0,0,I67/I36) -> 1.0936571 | J102: =IF(J36=0,0,J67/J36) -> 1.1176931 | ... AL102: =IF(AL36=0,0,AL67/AL36) -> 1.2166282
A103: ARPPU: net subscription revenue / paid subscriber | B103: arppu | C103: =IF(C29=0,0,C60/C29) -> 13.881396 | D103: =IF(D29=0,0,D60/D29) -> 11.090145 | E103: =IF(E29=0,0,E60/E29) -> 10.092885 | F103: =IF(F29=0,0,F60/F29) -> 9.6495666 | G103: =IF(G29=0,0,G60/G29) -> 9.290527 | H103: =IF(H29=0,0,H60/H29) -> 9.0398525 | I103: =IF(I29=0,0,I60/I29) -> 8.8523134 | J103: =IF(J29=0,0,J60/J29) -> 8.7048437 | ... AL103: =IF(AL29=0,0,AL60/AL29) -> 8.0710761
A104: CAC: paid channels (ASA + creators) per payer they bring | B104: cac_paid | C104: =IF(((C11+C9)*Assumptions!$G$111)=0,0,(C10+C8)/((C11+C9)*Assumptions!$G$111)) -> 95.238095 | D104: =IF(((D11+D9)*Assumptions!$G$111)=0,0,(D10+D8)/((D11+D9)*Assumptions!$G$111)) -> 95.238095 | E104: =IF(((E11+E9)*Assumptions!$G$111)=0,0,(E10+E8)/((E11+E9)*Assumptions!$G$111)) -> 95.238095 | F104: =IF(((F11+F9)*Assumptions!$G$111)=0,0,(F10+F8)/((F11+F9)*Assumptions!$G$111)) -> 104.80488 | G104: =IF(((G11+G9)*Assumptions!$G$111)=0,0,(G10+G8)/((G11+G9)*Assumptions!$G$111)) -> 104.85866 | H104: =IF(((H11+H9)*Assumptions!$G$111)=0,0,(H10+H8)/((H11+H9)*Assumptions!$G$111)) -> 104.91255 | I104: =IF(((I11+I9)*Assumptions!$G$111)=0,0,(I10+I8)/((I11+I9)*Assumptions!$G$111)) -> 104.96652 | J104: =IF(((J11+J9)*Assumptions!$G$111)=0,0,(J10+J8)/((J11+J9)*Assumptions!$G$111)) -> 105.02059 | ... AL104: =IF(((AL11+AL9)*Assumptions!$G$111)=0,0,(AL10+AL8)/((AL11+AL9)*Assumptions!$G$111)) -> 106.56309
A105: EBIT >= 0 this month (1 = yes) | B105: flag_be | C105: =IF((C91>=0),1,0) -> 0 | D105: =IF((D91>=0),1,0) -> 0 | E105: =IF((E91>=0),1,0) -> 1 | F105: =IF((F91>=0),1,0) -> 1 | G105: =IF((G91>=0),1,0) -> 1 | H105: =IF((H91>=0),1,0) -> 1 | I105: =IF((I91>=0),1,0) -> 1 | J105: =IF((J91>=0),1,0) -> 1 | ... AL105: =IF((AL91>=0),1,0) -> 1
A106: EBIT >= 0 this month and every month after | B106: flag_be_sus | C106: =IF(AND((C91>=0),(D106=1)),1,0) -> 0 | D106: =IF(AND((D91>=0),(E106=1)),1,0) -> 0 | E106: =IF(AND((E91>=0),(F106=1)),1,0) -> 1 | F106: =IF(AND((F91>=0),(G106=1)),1,0) -> 1 | G106: =IF(AND((G91>=0),(H106=1)),1,0) -> 1 | H106: =IF(AND((H91>=0),(I106=1)),1,0) -> 1 | I106: =IF(AND((I91>=0),(J106=1)),1,0) -> 1 | J106: =IF(AND((J91>=0),(K106=1)),1,0) -> 1 | ... AK106: =IF(AND((AK91>=0),(AL106=1)),1,0) -> 1 | AL106: =IF((AL91>=0),1,0) -> 1
A107: Cumulative cash >= 0 this month and every month after | B107: flag_cash_sus | C107: =IF(AND((C98>=0),(D107=1)),1,0) -> 0 | D107: =IF(AND((D98>=0),(E107=1)),1,0) -> 1 | E107: =IF(AND((E98>=0),(F107=1)),1,0) -> 1 | F107: =IF(AND((F98>=0),(G107=1)),1,0) -> 1 | G107: =IF(AND((G98>=0),(H107=1)),1,0) -> 1 | H107: =IF(AND((H98>=0),(I107=1)),1,0) -> 1 | I107: =IF(AND((I98>=0),(J107=1)),1,0) -> 1 | J107: =IF(AND((J98>=0),(K107=1)),1,0) -> 1 | ... AK107: =IF(AND((AK98>=0),(AL107=1)),1,0) -> 1 | AL107: =IF((AL98>=0),1,0) -> 1

Sheet Annual_PnL
A1: Tenbagger: annual income statement by scenario (USD). FY1 = months 1-12. Live formulas.
A3: BASE CASE | B3: FY1 | C3: FY2 | D3: FY3 | E3: 3-year total
A4: REVENUE
A5: Gross in-app sales | B5: =SUM(Monthly_Base!$C$57:$N$57) -> 22877.071 | C5: =SUM(Monthly_Base!$O$57:$Z$57) -> 75508.965 | D5: =SUM(Monthly_Base!$AA$57:$AL$57) -> 175438.99 | E5: =SUM(Monthly_Base!$C$57:$AL$57) -> 273825.03
A6: Less: refunds | B6: =SUM(Monthly_Base!$C$58:$N$58) -> -457.54143 | C6: =SUM(Monthly_Base!$O$58:$Z$58) -> -1510.1793 | D6: =SUM(Monthly_Base!$AA$58:$AL$58) -> -3508.7799 | E6: =SUM(Monthly_Base!$C$58:$AL$58) -> -5476.5006
A7: Less: app store commission | B7: =SUM(Monthly_Base!$C$59:$N$59) -> -3362.9295 | C7: =SUM(Monthly_Base!$O$59:$Z$59) -> -11099.818 | D7: =SUM(Monthly_Base!$AA$59:$AL$59) -> -25789.532 | E7: =SUM(Monthly_Base!$C$59:$AL$59) -> -40252.28
A8: Subscriptions & in-app, net | B8: =SUM(Monthly_Base!$C$60:$N$60) -> 19056.6 | C8: =SUM(Monthly_Base!$O$60:$Z$60) -> 62898.968 | D8: =SUM(Monthly_Base!$AA$60:$AL$60) -> 146140.68 | E8: =SUM(Monthly_Base!$C$60:$AL$60) -> 228096.25
A9: Advertising | B9: =SUM(Monthly_Base!$C$64:$N$64) -> 673.20698 | C9: =SUM(Monthly_Base!$O$64:$Z$64) -> 2088.7976 | D9: =SUM(Monthly_Base!$AA$64:$AL$64) -> 4745.0809 | E9: =SUM(Monthly_Base!$C$64:$AL$64) -> 7507.0855
A10: Affiliate | B10: =SUM(Monthly_Base!$C$65:$N$65) -> 214.89402 | C10: =SUM(Monthly_Base!$O$65:$Z$65) -> 890.88235 | D10: =SUM(Monthly_Base!$AA$65:$AL$65) -> 2031.238 | E10: =SUM(Monthly_Base!$C$65:$AL$65) -> 3137.0144
A11: B2B / Edu licences | B11: =SUM(Monthly_Base!$C$66:$N$66) -> 0 | C11: =SUM(Monthly_Base!$O$66:$Z$66) -> 0 | D11: =SUM(Monthly_Base!$AA$66:$AL$66) -> 0 | E11: =SUM(Monthly_Base!$C$66:$AL$66) -> 0
A12: TOTAL REVENUE | B12: =SUM(Monthly_Base!$C$67:$N$67) -> 19944.701 | C12: =SUM(Monthly_Base!$O$67:$Z$67) -> 65878.648 | D12: =SUM(Monthly_Base!$AA$67:$AL$67) -> 152917 | E12: =SUM(Monthly_Base!$C$67:$AL$67) -> 238740.35
A13: COST OF REVENUE
A14: Data licensing | B14: =SUM(Monthly_Base!$C$70:$N$70) -> 4800 | C14: =SUM(Monthly_Base!$O$70:$Z$70) -> 4800 | D14: =SUM(Monthly_Base!$AA$70:$AL$70) -> 4800 | E14: =SUM(Monthly_Base!$C$70:$AL$70) -> 14400
A15: Plaid / aggregation | B15: =SUM(Monthly_Base!$C$71:$N$71) -> 0 | C15: =SUM(Monthly_Base!$O$71:$Z$71) -> 11301.933 | D15: =SUM(Monthly_Base!$AA$71:$AL$71) -> 24669.012 | E15: =SUM(Monthly_Base!$C$71:$AL$71) -> 35970.945
A16: Hosting | B16: =SUM(Monthly_Base!$C$72:$N$72) -> 922.96334 | C16: =SUM(Monthly_Base!$O$72:$Z$72) -> 1490.8824 | D16: =SUM(Monthly_Base!$AA$72:$AL$72) -> 2631.238 | E16: =SUM(Monthly_Base!$C$72:$AL$72) -> 5045.0837
A17: LLM tutor | B17: =SUM(Monthly_Base!$C$73:$N$73) -> 1082.6009 | C17: =SUM(Monthly_Base!$O$73:$Z$73) -> 4983.8646 | D17: =SUM(Monthly_Base!$AA$73:$AL$73) -> 11656.45 | E17: =SUM(Monthly_Base!$C$73:$AL$73) -> 17722.916
A18: RevenueCat | B18: =SUM(Monthly_Base!$C$74:$N$74) -> 77.917608 | C18: =SUM(Monthly_Base!$O$74:$Z$74) -> 660.98249 | D18: =SUM(Monthly_Base!$AA$74:$AL$74) -> 1879.2021 | E18: =SUM(Monthly_Base!$C$74:$AL$74) -> 2618.1022
A19: B2B processing | B19: =SUM(Monthly_Base!$C$75:$N$75) -> 0 | C19: =SUM(Monthly_Base!$O$75:$Z$75) -> 0 | D19: =SUM(Monthly_Base!$AA$75:$AL$75) -> 0 | E19: =SUM(Monthly_Base!$C$75:$AL$75) -> 0
A20: Total COGS | B20: =SUM(Monthly_Base!$C$76:$N$76) -> 6883.4819 | C20: =SUM(Monthly_Base!$O$76:$Z$76) -> 23237.662 | D20: =SUM(Monthly_Base!$AA$76:$AL$76) -> 45635.902 | E20: =SUM(Monthly_Base!$C$76:$AL$76) -> 75757.046
A21: GROSS PROFIT | B21: =SUM(Monthly_Base!$C$77:$N$77) -> 13061.22 | C21: =SUM(Monthly_Base!$O$77:$Z$77) -> 42640.985 | D21: =SUM(Monthly_Base!$AA$77:$AL$77) -> 107281.1 | E21: =SUM(Monthly_Base!$C$77:$AL$77) -> 162983.3
A22: Gross margin | B22: =IF(SUM(Monthly_Base!$C$67:$N$67)=0,0,SUM(Monthly_Base!$C$77:$N$77)/SUM(Monthly_Base!$C$67:$N$67)) -> 0.65487165 | C22: =IF(SUM(Monthly_Base!$O$67:$Z$67)=0,0,SUM(Monthly_Base!$O$77:$Z$77)/SUM(Monthly_Base!$O$67:$Z$67)) -> 0.64726564 | D22: =IF(SUM(Monthly_Base!$AA$67:$AL$67)=0,0,SUM(Monthly_Base!$AA$77:$AL$77)/SUM(Monthly_Base!$AA$67:$AL$67)) -> 0.70156424 | E22: =IF(SUM(Monthly_Base!$C$67:$AL$67)=0,0,SUM(Monthly_Base!$C$77:$AL$77)/SUM(Monthly_Base!$C$67:$AL$67)) -> 0.68268018
A23: OPERATING EXPENSES
A24: Founder salary | B24: =SUM(Monthly_Base!$C$81:$N$81) -> 0 | C24: =SUM(Monthly_Base!$O$81:$Z$81) -> 0 | D24: =SUM(Monthly_Base!$AA$81:$AL$81) -> 0 | E24: =SUM(Monthly_Base!$C$81:$AL$81) -> 0
A25: Contractors | B25: =SUM(Monthly_Base!$C$82:$N$82) -> 6000 | C25: =SUM(Monthly_Base!$O$82:$Z$82) -> 18000 | D25: =SUM(Monthly_Base!$AA$82:$AL$82) -> 36000 | E25: =SUM(Monthly_Base!$C$82:$AL$82) -> 60000
A26: Marketing: Apple Search Ads | B26: =SUM(Monthly_Base!$C$83:$N$83) -> 7096.0148 | C26: =SUM(Monthly_Base!$O$83:$Z$83) -> 10117.22 | D26: =SUM(Monthly_Base!$AA$83:$AL$83) -> 14424.737 | E26: =SUM(Monthly_Base!$C$83:$AL$83) -> 31637.972
A27: Marketing: creators | B27: =SUM(Monthly_Base!$C$84:$N$84) -> 5513.2822 | C27: =SUM(Monthly_Base!$O$84:$Z$84) -> 12346.344 | D27: =SUM(Monthly_Base!$AA$84:$AL$84) -> 22172.26 | E27: =SUM(Monthly_Base!$C$84:$AL$84) -> 40031.885
A28: Marketing: other | B28: =SUM(Monthly_Base!$C$85:$N$85) -> 1800 | C28: =SUM(Monthly_Base!$O$85:$Z$85) -> 1800 | D28: =SUM(Monthly_Base!$AA$85:$AL$85) -> 1800 | E28: =SUM(Monthly_Base!$C$85:$AL$85) -> 5400
A29: Legal & compliance | B29: =SUM(Monthly_Base!$C$86:$N$86) -> 4900 | C29: =SUM(Monthly_Base!$O$86:$Z$86) -> 2200 | D29: =SUM(Monthly_Base!$AA$86:$AL$86) -> 2200 | E29: =SUM(Monthly_Base!$C$86:$AL$86) -> 9300
A30: Software / tools | B30: =SUM(Monthly_Base!$C$87:$N$87) -> 1800 | C30: =SUM(Monthly_Base!$O$87:$Z$87) -> 3000 | D30: =SUM(Monthly_Base!$AA$87:$AL$87) -> 4800 | E30: =SUM(Monthly_Base!$C$87:$AL$87) -> 9600
A31: Apple / Google developer fees | B31: =SUM(Monthly_Base!$C$88:$N$88) -> 124 | C31: =SUM(Monthly_Base!$O$88:$Z$88) -> 99 | D31: =SUM(Monthly_Base!$AA$88:$AL$88) -> 99 | E31: =SUM(Monthly_Base!$C$88:$AL$88) -> 322
A32: Insurance | B32: =SUM(Monthly_Base!$C$89:$N$89) -> 1200 | C32: =SUM(Monthly_Base!$O$89:$Z$89) -> 1200 | D32: =SUM(Monthly_Base!$AA$89:$AL$89) -> 1200 | E32: =SUM(Monthly_Base!$C$89:$AL$89) -> 3600
A33: Total operating expenses | B33: =SUM(Monthly_Base!$C$90:$N$90) -> 28433.297 | C33: =SUM(Monthly_Base!$O$90:$Z$90) -> 48762.564 | D33: =SUM(Monthly_Base!$AA$90:$AL$90) -> 82695.997 | E33: =SUM(Monthly_Base!$C$90:$AL$90) -> 159891.86
A34: OPERATING INCOME (EBIT) | B34: =SUM(Monthly_Base!$C$91:$N$91) -> -15372.077 | C34: =SUM(Monthly_Base!$O$91:$Z$91) -> -6121.5788 | D34: =SUM(Monthly_Base!$AA$91:$AL$91) -> 24585.103 | E34: =SUM(Monthly_Base!$C$91:$AL$91) -> 3091.4471
A35: Operating margin | B35: =IF(SUM(Monthly_Base!$C$67:$N$67)=0,0,SUM(Monthly_Base!$C$91:$N$91)/SUM(Monthly_Base!$C$67:$N$67)) -> -0.7707349 | C35: =IF(SUM(Monthly_Base!$O$67:$Z$67)=0,0,SUM(Monthly_Base!$O$91:$Z$91)/SUM(Monthly_Base!$O$67:$Z$67)) -> -0.092922047 | D35: =IF(SUM(Monthly_Base!$AA$67:$AL$67)=0,0,SUM(Monthly_Base!$AA$91:$AL$91)/SUM(Monthly_Base!$AA$67:$AL$67)) -> 0.16077417 | E35: =IF(SUM(Monthly_Base!$C$67:$AL$67)=0,0,SUM(Monthly_Base!$C$91:$AL$91)/SUM(Monthly_Base!$C$67:$AL$67)) -> 0.012948993
A36: MEMO
A37: Ads as share of revenue | B37: =IF(SUM(Monthly_Base!$C$67:$N$67)=0,0,SUM(Monthly_Base!$C$64:$N$64)/SUM(Monthly_Base!$C$67:$N$67)) -> 0.033753675 | C37: =IF(SUM(Monthly_Base!$O$67:$Z$67)=0,0,SUM(Monthly_Base!$O$64:$Z$64)/SUM(Monthly_Base!$O$67:$Z$67)) -> 0.031706746 | D37: =IF(SUM(Monthly_Base!$AA$67:$AL$67)=0,0,SUM(Monthly_Base!$AA$64:$AL$64)/SUM(Monthly_Base!$AA$67:$AL$67)) -> 0.031030434 | E37: =IF(SUM(Monthly_Base!$C$67:$AL$67)=0,0,SUM(Monthly_Base!$C$64:$AL$64)/SUM(Monthly_Base!$C$67:$AL$67)) -> 0.031444561
A38: EBIT if ads were switched off (no other change) | B38: =(SUM(Monthly_Base!$C$91:$N$91)-SUM(Monthly_Base!$C$64:$N$64)) -> -16045.284 | C38: =(SUM(Monthly_Base!$O$91:$Z$91)-SUM(Monthly_Base!$O$64:$Z$64)) -> -8210.3763 | D38: =(SUM(Monthly_Base!$AA$91:$AL$91)-SUM(Monthly_Base!$AA$64:$AL$64)) -> 19840.022 | E38: =(SUM(Monthly_Base!$C$91:$AL$91)-SUM(Monthly_Base!$C$64:$AL$64)) -> -4415.6383
A39: Operating cash flow | B39: =SUM(Monthly_Base!$C$97:$N$97) -> -4864.4809 | C39: =SUM(Monthly_Base!$O$97:$Z$97) -> 11029.295 | D39: =SUM(Monthly_Base!$AA$97:$AL$97) -> 59971.955 | E39: =SUM(Monthly_Base!$C$97:$AL$97) -> 66136.769
A40: Cumulative cash, end of period | B40: =Monthly_Base!N98 -> -4864.4809 | C40: =Monthly_Base!Z98 -> 6164.8137 | D40: =Monthly_Base!AL98 -> 66136.769 | E40: =Monthly_Base!AL98 -> 66136.769
A41: Installs | B41: =SUM(Monthly_Base!$C$12:$N$12) -> 21072.714 | C41: =SUM(Monthly_Base!$O$12:$Z$12) -> 46775.434 | D41: =SUM(Monthly_Base!$AA$12:$AL$12) -> 103298.23 | E41: =SUM(Monthly_Base!$C$12:$AL$12) -> 171146.37
A42: New paid subscribers | B42: =SUM(Monthly_Base!$C$17:$N$17) -> 520.49602 | C42: =SUM(Monthly_Base!$O$17:$Z$17) -> 1155.3532 | D42: =SUM(Monthly_Base!$AA$17:$AL$17) -> 2551.4662 | E42: =SUM(Monthly_Base!$C$17:$AL$17) -> 4227.3154
A43: MAU, end of period | B43: =Monthly_Base!N36 -> 4428.9808 | C43: =Monthly_Base!Z36 -> 10630.054 | D43: =Monthly_Base!AL36 -> 23824.344 | E43: =Monthly_Base!AL36 -> 23824.344
A44: Paid subscribers, end of period | B44: =Monthly_Base!N29 -> 440.86506 | C44: =Monthly_Base!Z29 -> 1136.9393 | D44: =Monthly_Base!AL29 -> 2575.9028 | E44: =Monthly_Base!AL29 -> 2575.9028
A46: BEAR CASE | B46: FY1 | C46: FY2 | D46: FY3 | E46: 3-year total
A47: REVENUE
A48: Gross in-app sales | B48: =SUM(Monthly_Bear!$C$57:$N$57) -> 4684.1937 | C48: =SUM(Monthly_Bear!$O$57:$Z$57) -> 11336 | D48: =SUM(Monthly_Bear!$AA$57:$AL$57) -> 18712.834 | E48: =SUM(Monthly_Bear!$C$57:$AL$57) -> 34733.027
A49: Less: refunds | B49: =SUM(Monthly_Bear!$C$58:$N$58) -> -140.52581 | C49: =SUM(Monthly_Bear!$O$58:$Z$58) -> -340.07999 | D49: =SUM(Monthly_Bear!$AA$58:$AL$58) -> -561.38501 | E49: =SUM(Monthly_Bear!$C$58:$AL$58) -> -1041.9908
A50: Less: app store commission | B50: =SUM(Monthly_Bear!$C$59:$N$59) -> -681.55018 | C50: =SUM(Monthly_Bear!$O$59:$Z$59) -> -1649.3879 | D50: =SUM(Monthly_Bear!$AA$59:$AL$59) -> -2722.7173 | E50: =SUM(Monthly_Bear!$C$59:$AL$59) -> -5053.6554
A51: Subscriptions & in-app, net | B51: =SUM(Monthly_Bear!$C$60:$N$60) -> 3862.1177 | C51: =SUM(Monthly_Bear!$O$60:$Z$60) -> 9346.5317 | D51: =SUM(Monthly_Bear!$AA$60:$AL$60) -> 15428.731 | E51: =SUM(Monthly_Bear!$C$60:$AL$60) -> 28637.381
A52: Advertising | B52: =SUM(Monthly_Bear!$C$64:$N$64) -> 60.189031 | C52: =SUM(Monthly_Bear!$O$64:$Z$64) -> 128.54792 | D52: =SUM(Monthly_Bear!$AA$64:$AL$64) -> 204.44784 | E52: =SUM(Monthly_Bear!$C$64:$AL$64) -> 393.18479
A53: Affiliate | B53: =SUM(Monthly_Bear!$C$65:$N$65) -> 12.884946 | C53: =SUM(Monthly_Bear!$O$65:$Z$65) -> 38.8188 | D53: =SUM(Monthly_Bear!$AA$65:$AL$65) -> 62.009227 | E53: =SUM(Monthly_Bear!$C$65:$AL$65) -> 113.71297
A54: B2B / Edu licences | B54: =SUM(Monthly_Bear!$C$66:$N$66) -> 0 | C54: =SUM(Monthly_Bear!$O$66:$Z$66) -> 0 | D54: =SUM(Monthly_Bear!$AA$66:$AL$66) -> 0 | E54: =SUM(Monthly_Bear!$C$66:$AL$66) -> 0
A55: TOTAL REVENUE | B55: =SUM(Monthly_Bear!$C$67:$N$67) -> 3935.1917 | C55: =SUM(Monthly_Bear!$O$67:$Z$67) -> 9513.8984 | D55: =SUM(Monthly_Bear!$AA$67:$AL$67) -> 15695.189 | E55: =SUM(Monthly_Bear!$C$67:$AL$67) -> 29144.279
A56: COST OF REVENUE
A57: Data licensing | B57: =SUM(Monthly_Bear!$C$70:$N$70) -> 5400 | C57: =SUM(Monthly_Bear!$O$70:$Z$70) -> 5400 | D57: =SUM(Monthly_Bear!$AA$70:$AL$70) -> 5400 | E57: =SUM(Monthly_Bear!$C$70:$AL$70) -> 16200
A58: Plaid / aggregation | B58: =SUM(Monthly_Bear!$C$71:$N$71) -> 0 | C58: =SUM(Monthly_Bear!$O$71:$Z$71) -> 4054.8017 | D58: =SUM(Monthly_Bear!$AA$71:$AL$71) -> 5858.6174 | E58: =SUM(Monthly_Bear!$C$71:$AL$71) -> 9913.4191
A59: Hosting | B59: =SUM(Monthly_Bear!$C$72:$N$72) -> 719.35114 | C59: =SUM(Monthly_Bear!$O$72:$Z$72) -> 815.66 | D59: =SUM(Monthly_Bear!$AA$72:$AL$72) -> 944.49571 | E59: =SUM(Monthly_Bear!$C$72:$AL$72) -> 2479.5069
A60: LLM tutor | B60: =SUM(Monthly_Bear!$C$73:$N$73) -> 393.16344 | C60: =SUM(Monthly_Bear!$O$73:$Z$73) -> 1380.3166 | D60: =SUM(Monthly_Bear!$AA$73:$AL$73) -> 2292.8939 | E60: =SUM(Monthly_Bear!$C$73:$AL$73) -> 4066.374
A61: RevenueCat | B61: =SUM(Monthly_Bear!$C$74:$N$74) -> 0 | C61: =SUM(Monthly_Bear!$O$74:$Z$74) -> 0 | D61: =SUM(Monthly_Bear!$AA$74:$AL$74) -> 0 | E61: =SUM(Monthly_Bear!$C$74:$AL$74) -> 0
A62: B2B processing | B62: =SUM(Monthly_Bear!$C$75:$N$75) -> 0 | C62: =SUM(Monthly_Bear!$O$75:$Z$75) -> 0 | D62: =SUM(Monthly_Bear!$AA$75:$AL$75) -> 0 | E62: =SUM(Monthly_Bear!$C$75:$AL$75) -> 0
A63: Total COGS | B63: =SUM(Monthly_Bear!$C$76:$N$76) -> 6512.5146 | C63: =SUM(Monthly_Bear!$O$76:$Z$76) -> 11650.778 | D63: =SUM(Monthly_Bear!$AA$76:$AL$76) -> 14496.007 | E63: =SUM(Monthly_Bear!$C$76:$AL$76) -> 32659.3
A64: GROSS PROFIT | B64: =SUM(Monthly_Bear!$C$77:$N$77) -> -2577.3229 | C64: =SUM(Monthly_Bear!$O$77:$Z$77) -> -2136.8799 | D64: =SUM(Monthly_Bear!$AA$77:$AL$77) -> 1199.1815 | E64: =SUM(Monthly_Bear!$C$77:$AL$77) -> -3515.0213
A65: Gross margin | B65: =IF(SUM(Monthly_Bear!$C$67:$N$67)=0,0,SUM(Monthly_Bear!$C$77:$N$77)/SUM(Monthly_Bear!$C$67:$N$67)) -> -0.65494215 | C65: =IF(SUM(Monthly_Bear!$O$67:$Z$67)=0,0,SUM(Monthly_Bear!$O$77:$Z$77)/SUM(Monthly_Bear!$O$67:$Z$67)) -> -0.22460613 | D65: =IF(SUM(Monthly_Bear!$AA$67:$AL$67)=0,0,SUM(Monthly_Bear!$AA$77:$AL$77)/SUM(Monthly_Bear!$AA$67:$AL$67)) -> 0.076404403 | E65: =IF(SUM(Monthly_Bear!$C$67:$AL$67)=0,0,SUM(Monthly_Bear!$C$77:$AL$77)/SUM(Monthly_Bear!$C$67:$AL$67)) -> -0.12060759
A66: OPERATING EXPENSES
A67: Founder salary | B67: =SUM(Monthly_Bear!$C$81:$N$81) -> 0 | C67: =SUM(Monthly_Bear!$O$81:$Z$81) -> 0 | D67: =SUM(Monthly_Bear!$AA$81:$AL$81) -> 0 | E67: =SUM(Monthly_Bear!$C$81:$AL$81) -> 0
A68: Contractors | B68: =SUM(Monthly_Bear!$C$82:$N$82) -> 3600 | C68: =SUM(Monthly_Bear!$O$82:$Z$82) -> 9600 | D68: =SUM(Monthly_Bear!$AA$82:$AL$82) -> 18000 | E68: =SUM(Monthly_Bear!$C$82:$AL$82) -> 31200
A69: Marketing: Apple Search Ads | B69: =SUM(Monthly_Bear!$C$83:$N$83) -> 6000 | C69: =SUM(Monthly_Bear!$O$83:$Z$83) -> 6000 | D69: =SUM(Monthly_Bear!$AA$83:$AL$83) -> 6000 | E69: =SUM(Monthly_Bear!$C$83:$AL$83) -> 18000
A70: Marketing: creators | B70: =SUM(Monthly_Bear!$C$84:$N$84) -> 3047.7318 | C70: =SUM(Monthly_Bear!$O$84:$Z$84) -> 5555.2139 | D70: =SUM(Monthly_Bear!$AA$84:$AL$84) -> 7920.4067 | E70: =SUM(Monthly_Bear!$C$84:$AL$84) -> 16523.352
A71: Marketing: other | B71: =SUM(Monthly_Bear!$C$85:$N$85) -> 1800 | C71: =SUM(Monthly_Bear!$O$85:$Z$85) -> 1800 | D71: =SUM(Monthly_Bear!$AA$85:$AL$85) -> 1800 | E71: =SUM(Monthly_Bear!$C$85:$AL$85) -> 5400
A72: Legal & compliance | B72: =SUM(Monthly_Bear!$C$86:$N$86) -> 4900 | C72: =SUM(Monthly_Bear!$O$86:$Z$86) -> 2200 | D72: =SUM(Monthly_Bear!$AA$86:$AL$86) -> 2200 | E72: =SUM(Monthly_Bear!$C$86:$AL$86) -> 9300
A73: Software / tools | B73: =SUM(Monthly_Bear!$C$87:$N$87) -> 1800 | C73: =SUM(Monthly_Bear!$O$87:$Z$87) -> 3000 | D73: =SUM(Monthly_Bear!$AA$87:$AL$87) -> 4800 | E73: =SUM(Monthly_Bear!$C$87:$AL$87) -> 9600
A74: Apple / Google developer fees | B74: =SUM(Monthly_Bear!$C$88:$N$88) -> 124 | C74: =SUM(Monthly_Bear!$O$88:$Z$88) -> 99 | D74: =SUM(Monthly_Bear!$AA$88:$AL$88) -> 99 | E74: =SUM(Monthly_Bear!$C$88:$AL$88) -> 322
A75: Insurance | B75: =SUM(Monthly_Bear!$C$89:$N$89) -> 1200 | C75: =SUM(Monthly_Bear!$O$89:$Z$89) -> 1200 | D75: =SUM(Monthly_Bear!$AA$89:$AL$89) -> 1200 | E75: =SUM(Monthly_Bear!$C$89:$AL$89) -> 3600
A76: Total operating expenses | B76: =SUM(Monthly_Bear!$C$90:$N$90) -> 22471.732 | C76: =SUM(Monthly_Bear!$O$90:$Z$90) -> 29454.214 | D76: =SUM(Monthly_Bear!$AA$90:$AL$90) -> 42019.407 | E76: =SUM(Monthly_Bear!$C$90:$AL$90) -> 93945.352
A77: OPERATING INCOME (EBIT) | B77: =SUM(Monthly_Bear!$C$91:$N$91) -> -25049.055 | C77: =SUM(Monthly_Bear!$O$91:$Z$91) -> -31591.094 | D77: =SUM(Monthly_Bear!$AA$91:$AL$91) -> -40820.225 | E77: =SUM(Monthly_Bear!$C$91:$AL$91) -> -97460.374
A78: Operating margin | B78: =IF(SUM(Monthly_Bear!$C$67:$N$67)=0,0,SUM(Monthly_Bear!$C$91:$N$91)/SUM(Monthly_Bear!$C$67:$N$67)) -> -6.3653964 | C78: =IF(SUM(Monthly_Bear!$O$67:$Z$67)=0,0,SUM(Monthly_Bear!$O$91:$Z$91)/SUM(Monthly_Bear!$O$67:$Z$67)) -> -3.3205204 | D78: =IF(SUM(Monthly_Bear!$AA$67:$AL$67)=0,0,SUM(Monthly_Bear!$AA$91:$AL$91)/SUM(Monthly_Bear!$AA$67:$AL$67)) -> -2.6008114 | E78: =IF(SUM(Monthly_Bear!$C$67:$AL$67)=0,0,SUM(Monthly_Bear!$C$91:$AL$91)/SUM(Monthly_Bear!$C$67:$AL$67)) -> -3.3440654
A79: MEMO
A80: Ads as share of revenue | B80: =IF(SUM(Monthly_Bear!$C$67:$N$67)=0,0,SUM(Monthly_Bear!$C$64:$N$64)/SUM(Monthly_Bear!$C$67:$N$67)) -> 0.01529507 | C80: =IF(SUM(Monthly_Bear!$O$67:$Z$67)=0,0,SUM(Monthly_Bear!$O$64:$Z$64)/SUM(Monthly_Bear!$O$67:$Z$67)) -> 0.013511593 | D80: =IF(SUM(Monthly_Bear!$AA$67:$AL$67)=0,0,SUM(Monthly_Bear!$AA$64:$AL$64)/SUM(Monthly_Bear!$AA$67:$AL$67)) -> 0.013026148 | E80: =IF(SUM(Monthly_Bear!$C$67:$AL$67)=0,0,SUM(Monthly_Bear!$C$64:$AL$64)/SUM(Monthly_Bear!$C$67:$AL$67)) -> 0.013490977
A81: EBIT if ads were switched off (no other change) | B81: =(SUM(Monthly_Bear!$C$91:$N$91)-SUM(Monthly_Bear!$C$64:$N$64)) -> -25109.244 | C81: =(SUM(Monthly_Bear!$O$91:$Z$91)-SUM(Monthly_Bear!$O$64:$Z$64)) -> -31719.642 | D81: =(SUM(Monthly_Bear!$AA$91:$AL$91)-SUM(Monthly_Bear!$AA$64:$AL$64)) -> -41024.673 | E81: =(SUM(Monthly_Bear!$C$91:$AL$91)-SUM(Monthly_Bear!$C$64:$AL$64)) -> -97853.558
A82: Operating cash flow | B82: =SUM(Monthly_Bear!$C$97:$N$97) -> -23197.214 | C82: =SUM(Monthly_Bear!$O$97:$Z$97) -> -30005.688 | D82: =SUM(Monthly_Bear!$AA$97:$AL$97) -> -38701.749 | E82: =SUM(Monthly_Bear!$C$97:$AL$97) -> -91904.652
A83: Cumulative cash, end of period | B83: =Monthly_Bear!N98 -> -23197.214 | C83: =Monthly_Bear!Z98 -> -53202.902 | D83: =Monthly_Bear!AL98 -> -91904.652 | E83: =Monthly_Bear!AL98 -> -91904.652
A84: Installs | B84: =SUM(Monthly_Bear!$C$12:$N$12) -> 9419.7506 | C84: =SUM(Monthly_Bear!$O$12:$Z$12) -> 14767.012 | D84: =SUM(Monthly_Bear!$AA$12:$AL$12) -> 23160.755 | E84: =SUM(Monthly_Bear!$C$12:$AL$12) -> 47347.517
A85: New paid subscribers | B85: =SUM(Monthly_Bear!$C$17:$N$17) -> 136.77478 | C85: =SUM(Monthly_Bear!$O$17:$Z$17) -> 214.41702 | D85: =SUM(Monthly_Bear!$AA$17:$AL$17) -> 336.29416 | E85: =SUM(Monthly_Bear!$C$17:$AL$17) -> 687.48595
A86: MAU, end of period | B86: =Monthly_Bear!N36 -> 1353.2098 | C86: =Monthly_Bear!Z36 -> 2218.7193 | D86: =Monthly_Bear!AL36 -> 3511.2271 | E86: =Monthly_Bear!AL36 -> 3511.2271
A87: Paid subscribers, end of period | B87: =Monthly_Bear!N29 -> 107.20259 | C87: =Monthly_Bear!Z29 -> 194.31226 | D87: =Monthly_Bear!AL29 -> 312.11603 | E87: =Monthly_Bear!AL29 -> 312.11603
A89: BULL CASE | B89: FY1 | C89: FY2 | D89: FY3 | E89: 3-year total
A90: REVENUE
A91: Gross in-app sales | B91: =SUM(Monthly_Bull!$C$57:$N$57) -> 112584.69 | C91: =SUM(Monthly_Bull!$O$57:$Z$57) -> 460872.95 | D91: =SUM(Monthly_Bull!$AA$57:$AL$57) -> 1335145.4 | E91: =SUM(Monthly_Bull!$C$57:$AL$57) -> 1908603
A92: Less: refunds | B92: =SUM(Monthly_Bull!$C$58:$N$58) -> -1688.7704 | C92: =SUM(Monthly_Bull!$O$58:$Z$58) -> -6913.0942 | D92: =SUM(Monthly_Bull!$AA$58:$AL$58) -> -20027.181 | E92: =SUM(Monthly_Bull!$C$58:$AL$58) -> -28629.046
A93: Less: app store commission | B93: =SUM(Monthly_Bull!$C$59:$N$59) -> -16634.388 | C93: =SUM(Monthly_Bull!$O$59:$Z$59) -> -68093.978 | D93: =SUM(Monthly_Bull!$AA$59:$AL$59) -> -197267.73 | E93: =SUM(Monthly_Bull!$C$59:$AL$59) -> -281996.1
A94: Subscriptions & in-app, net | B94: =SUM(Monthly_Bull!$C$60:$N$60) -> 94261.535 | C94: =SUM(Monthly_Bull!$O$60:$Z$60) -> 385865.88 | D94: =SUM(Monthly_Bull!$AA$60:$AL$60) -> 1117850.5 | E94: =SUM(Monthly_Bull!$C$60:$AL$60) -> 1597977.9
A95: Advertising | B95: =SUM(Monthly_Bull!$C$64:$N$64) -> 6672.1945 | C95: =SUM(Monthly_Bull!$O$64:$Z$64) -> 26764.861 | D95: =SUM(Monthly_Bull!$AA$64:$AL$64) -> 76446.386 | E95: =SUM(Monthly_Bull!$C$64:$AL$64) -> 109883.44
A96: Affiliate | B96: =SUM(Monthly_Bull!$C$65:$N$65) -> 3099.7819 | C96: =SUM(Monthly_Bull!$O$65:$Z$65) -> 16026.236 | D96: =SUM(Monthly_Bull!$AA$65:$AL$65) -> 45929.369 | E96: =SUM(Monthly_Bull!$C$65:$AL$65) -> 65055.387
A97: B2B / Edu licences | B97: =SUM(Monthly_Bull!$C$66:$N$66) -> 0 | C97: =SUM(Monthly_Bull!$O$66:$Z$66) -> 0 | D97: =SUM(Monthly_Bull!$AA$66:$AL$66) -> 0 | E97: =SUM(Monthly_Bull!$C$66:$AL$66) -> 0
A98: TOTAL REVENUE | B98: =SUM(Monthly_Bull!$C$67:$N$67) -> 104033.51 | C98: =SUM(Monthly_Bull!$O$67:$Z$67) -> 428656.97 | D98: =SUM(Monthly_Bull!$AA$67:$AL$67) -> 1240226.2 | E98: =SUM(Monthly_Bull!$C$67:$AL$67) -> 1772916.7
A99: COST OF REVENUE
A100: Data licensing | B100: =SUM(Monthly_Bull!$C$70:$N$70) -> 4200 | C100: =SUM(Monthly_Bull!$O$70:$Z$70) -> 4200 | D100: =SUM(Monthly_Bull!$AA$70:$AL$70) -> 12800 | E100: =SUM(Monthly_Bull!$C$70:$AL$70) -> 21200
A101: Plaid / aggregation | B101: =SUM(Monthly_Bull!$C$71:$N$71) -> 0 | C101: =SUM(Monthly_Bull!$O$71:$Z$71) -> 47569.116 | D101: =SUM(Monthly_Bull!$AA$71:$AL$71) -> 136479.95 | E101: =SUM(Monthly_Bull!$C$71:$AL$71) -> 184049.06
A102: Hosting | B102: =SUM(Monthly_Bull!$C$72:$N$72) -> 1566.3079 | C102: =SUM(Monthly_Bull!$O$72:$Z$72) -> 4161.3859 | D102: =SUM(Monthly_Bull!$AA$72:$AL$72) -> 10806.526 | E102: =SUM(Monthly_Bull!$C$72:$AL$72) -> 16534.22
A103: LLM tutor | B103: =SUM(Monthly_Bull!$C$73:$N$73) -> 3102.5189 | C103: =SUM(Monthly_Bull!$O$73:$Z$73) -> 17254.668 | D103: =SUM(Monthly_Bull!$AA$73:$AL$73) -> 50315.693 | E103: =SUM(Monthly_Bull!$C$73:$AL$73) -> 70672.88
...

Sheet KPIs
A1: Tenbagger: KPIs and unit economics (live formulas)
A3: Metric | B3: Base | C3: Bear | D3: Bull
A4: SCALE
A5: Installs, 36 months | B5: =SUM(Monthly_Base!$C$12:$AL$12) -> 171146.37 | C5: =SUM(Monthly_Bear!$C$12:$AL$12) -> 47347.517 | D5: =SUM(Monthly_Bull!$C$12:$AL$12) -> 589724.2
A6: MAU, month 12 | B6: =Monthly_Base!N36 -> 4428.9808 | C6: =Monthly_Bear!N36 -> 1353.2098 | D6: =Monthly_Bull!N36 -> 15059.898
A7: MAU, month 24 | B7: =Monthly_Base!Z36 -> 10630.054 | C7: =Monthly_Bear!Z36 -> 2218.7193 | D7: =Monthly_Bull!Z36 -> 46536.324
A8: MAU, month 36 | B8: =Monthly_Base!AL36 -> 23824.344 | C8: =Monthly_Bear!AL36 -> 3511.2271 | D8: =Monthly_Bull!AL36 -> 130242.65
A9: Paid subscribers, month 12 | B9: =Monthly_Base!N29 -> 440.86506 | C9: =Monthly_Bear!N29 -> 107.20259 | D9: =Monthly_Bull!N29 -> 1925.7826
A10: Paid subscribers, month 24 | B10: =Monthly_Base!Z29 -> 1136.9393 | C10: =Monthly_Bear!Z29 -> 194.31226 | D10: =Monthly_Bull!Z29 -> 6271.7643
A11: Paid subscribers, month 36 | B11: =Monthly_Base!AL29 -> 2575.9028 | C11: =Monthly_Bear!AL29 -> 312.11603 | D11: =Monthly_Bull!AL29 -> 17698.399
A12: Paid subscribers / MAU, month 36 (Duolingo FY25: 9.2%) | B12: =Monthly_Base!AL37 -> 0.10812062 | C12: =Monthly_Bear!AL37 -> 0.08889087 | D12: =Monthly_Bull!AL37 -> 0.13588789
A13: Net subscription ARR run-rate, month 36 | B13: =(Monthly_Base!AL60*12) -> 206179.14 | C13: =(Monthly_Bear!AL60*12) -> 18948.075 | D13: =(Monthly_Bull!AL60*12) -> 1714141.5
A14: Total revenue run-rate (x12), month 36 | B14: =(Monthly_Base!AL67*12) -> 215713.48 | C14: =(Monthly_Bear!AL67*12) -> 19273.832 | D14: =(Monthly_Bull!AL67*12) -> 1901482.5
A15: MONETISATION
A16: Install-to-paid conversion | B16: =Assumptions!$E$111 -> 0.0247 | C16: =Assumptions!$F$111 -> 0.01452 | D16: =Assumptions!$G$111 -> 0.042
A17: ARPU per MAU per month, FY3 | B17: =IF(SUM(Monthly_Base!$AA$36:$AL$36)=0,0,SUM(Monthly_Base!$AA$67:$AL$67)/SUM(Monthly_Base!$AA$36:$AL$36)) -> 0.75282661 | C17: =IF(SUM(Monthly_Bear!$AA$36:$AL$36)=0,0,SUM(Monthly_Bear!$AA$67:$AL$67)/SUM(Monthly_Bear!$AA$36:$AL$36)) -> 0.45559896 | D17: =IF(SUM(Monthly_Bull!$AA$36:$AL$36)=0,0,SUM(Monthly_Bull!$AA$67:$AL$67)/SUM(Monthly_Bull!$AA$36:$AL$36)) -> 1.2151306
A18: ARPPU (net subs revenue per payer per month), FY3 | B18: =IF(SUM(Monthly_Base!$AA$29:$AL$29)=0,0,SUM(Monthly_Base!$AA$60:$AL$60)/SUM(Monthly_Base!$AA$29:$AL$29)) -> 6.6805697 | C18: =IF(SUM(Monthly_Bear!$AA$29:$AL$29)=0,0,SUM(Monthly_Bear!$AA$60:$AL$60)/SUM(Monthly_Bear!$AA$29:$AL$29)) -> 5.0679518 | D18: =IF(SUM(Monthly_Bull!$AA$29:$AL$29)=0,0,SUM(Monthly_Bull!$AA$60:$AL$60)/SUM(Monthly_Bull!$AA$29:$AL$29)) -> 8.082358
A19: Ad revenue per ad-seeing free MAU per month | B19: =Assumptions!$E$113 -> 0.0374 | C19: =Assumptions!$F$113 -> 0.01085 | D19: =Assumptions!$G$113 -> 0.1083
A20: UNIT ECONOMICS (steady-state plan mix)
A21: Contribution per payer per month (net ARPPU - LLM - Plaid) | B21: =(((((Assumptions!$E$31*Assumptions!$E$35)+((Assumptions!$E$32*Assumptions!$E$36)/12))+((Assumptions!$E$109*Assumptions!$E$37)/12))*Assumptions!$E$112)-Assumptions!$E$114) -> 5.82995 | C21: =(((((Assumptions!$F$31*Assumptions!$F$35)+((Assumptions!$F$32*Assumptions!$F$36)/12))+((Assumptions!$F$109*Assumptions!$F$37)/12))*Assumptions!$F$112)-Assumptions!$F$114) -> 4.1241648 | D21: =(((((Assumptions!$G$31*Assumptions!$G$35)+((Assumptions!$G$32*Assumptions!$G$36)/12))+((Assumptions!$G$109*Assumptions!$G$37)/12))*Assumptions!$G$112)-Assumptions!$G$114) -> 6.8956457
A22: LTV per payer (net of store fee, refunds, variable cost) | B22: =((((Assumptions!$E$31*((Assumptions!$E$35*Assumptions!$E$112)-Assumptions!$E$114))/Assumptions!$E$110)+((Assumptions!$E$32*((Assumptions!$E$36*Assumptions!$E$112)-(12*Assumptions!$E$114)))/(1-Assumptions!$E$43)))+((Assumptions!$E$109*((Assumptions!$E$37*Assumptions!$E$112)-(12*Assumptions!$E$114)))/(1-Assumptions!$E$44))) -> 76.414225 | C22: =((((Assumptions!$F$31*((Assumptions!$F$35*Assumptions!$F$112)-Assumptions!$F$114))/Assumptions!$F$110)+((Assumptions!$F$32*((Assumptions!$F$36*Assumptions!$F$112)-(12*Assumptions!$F$114)))/(1-Assumptions!$F$43)))+((Assumptions!$F$109*((Assumptions!$F$37*Assumptions!$F$112)-(12*Assumptions!$F$114)))/(1-Assumptions!$F$44))) -> 39.330312 | D22: =((((Assumptions!$G$31*((Assumptions!$G$35*Assumptions!$G$112)-Assumptions!$G$114))/Assumptions!$G$110)+((Assumptions!$G$32*((Assumptions!$G$36*Assumptions!$G$112)-(12*Assumptions!$G$114)))/(1-Assumptions!$G$43)))+((Assumptions!$G$109*((Assumptions!$G$37*Assumptions!$G$112)-(12*Assumptions!$G$114)))/(1-Assumptions!$G$44))) -> 120.821
A23: CAC per payer: Apple Search Ads (CPI / install-to-paid) | B23: =IF(Assumptions!$E$111=0,0,Assumptions!$E$23/Assumptions!$E$111) -> 242.91498 | C23: =IF(Assumptions!$F$111=0,0,Assumptions!$F$23/Assumptions!$F$111) -> 619.83471 | D23: =IF(Assumptions!$G$111=0,0,Assumptions!$G$23/Assumptions!$G$111) -> 95.238095
A24: CAC per payer: creators | B24: =IF(Assumptions!$E$111=0,0,Assumptions!$E$19/Assumptions!$E$111) -> 323.88664 | C24: =IF(Assumptions!$F$111=0,0,Assumptions!$F$19/Assumptions!$F$111) -> 826.44628 | D24: =IF(Assumptions!$G$111=0,0,Assumptions!$G$19/Assumptions!$G$111) -> 119.04762
A25: CAC per payer: organic / SEO and referral (no media spend) | B25: =(0*Assumptions!$E$111) -> 0 | C25: =(0*Assumptions!$F$111) -> 0 | D25: =(0*Assumptions!$G$111) -> 0
A26: CAC blended: paid media / all new payers, FY3 | B26: =IF(SUM(Monthly_Base!$AA$17:$AL$17)=0,0,(SUM(Monthly_Base!$AA$10:$AL$10)+SUM(Monthly_Base!$AA$8:$AL$8))/SUM(Monthly_Base!$AA$17:$AL$17)) -> 14.343516 | C26: =IF(SUM(Monthly_Bear!$AA$17:$AL$17)=0,0,(SUM(Monthly_Bear!$AA$10:$AL$10)+SUM(Monthly_Bear!$AA$8:$AL$8))/SUM(Monthly_Bear!$AA$17:$AL$17)) -> 41.393543 | D26: =IF(SUM(Monthly_Bull!$AA$17:$AL$17)=0,0,(SUM(Monthly_Bull!$AA$10:$AL$10)+SUM(Monthly_Bull!$AA$8:$AL$8))/SUM(Monthly_Bull!$AA$17:$AL$17)) -> 8.5905519
